Workbook

Sheet Dash board
B2: EXECUTIVE SALES & PERFORMANCE DASHBOARD
B3: Interactive project summary & analytics across regions, product categories, and top customers.
B5: TOTAL REVENUE | F5: TOTAL PROFIT | J5: PROFIT MARGIN
B6: =SUM(data!E2:E201) | F6: =SUM(data!I2:I201) | J6: =F6/B6
B7: 200 Total Orders | F7: Net Operating Margin | J7: Overall Profitability Rate
B10: FILTER BY REGION 🎛️ | F10: FILTER BY CATEGORY 🎛️
B11: ✓ (All Regions) | F11: ✓ (All Categories)
B12: [ ] Central | F12: [ ] Books
B13: [ ] East | F13: [ ] Clothing
B14: [ ] North | F14: [ ] Electronics
B15: [ ] South | F15: [ ] Furniture
B16: [ ] West | F16: [ ] Office Supplies
B19: Region | C19: Total Sales | D19: Total Profit | F19: Product Category | G19: Total Sales | H19: Total Profit | J19: Top Customers | K19: Total Revenue | L19: Order Count
B20: Central | C20: =SUMIF(data!$C$2:$C$201, B20, data!$E$2:$E$201) | D20: =SUMIF(data!$C$2:$C$201, B20, data!$I$2:$I$201) | F20: Books | G20: =SUMIF(data!$D$2:$D$201, F20, data!$E$2:$E$201) | H20: =SUMIF(data!$D$2:$D$201, F20, data!$I$2:$I$201) | J20: James Wilson | K20: ='Customer summary'!C4 | L20: ='Customer summary'!E4
B21: East | C21: =SUMIF(data!$C$2:$C$201, B21, data!$E$2:$E$201) | D21: =SUMIF(data!$C$2:$C$201, B21, data!$I$2:$I$201) | F21: Clothing | G21: =SUMIF(data!$D$2:$D$201, F21, data!$E$2:$E$201) | H21: =SUMIF(data!$D$2:$D$201, F21, data!$I$2:$I$201) | J21: Mary Davis | K21: ='Customer summary'!C7 | L21: ='Customer summary'!E7
B22: North | C22: =SUMIF(data!$C$2:$C$201, B22, data!$E$2:$E$201) | D22: =SUMIF(data!$C$2:$C$201, B22, data!$I$2:$I$201) | F22: Electronics | G22: =SUMIF(data!$D$2:$D$201, F22, data!$E$2:$E$201) | H22: =SUMIF(data!$D$2:$D$201, F22, data!$I$2:$I$201) | J22: Emma Davis | K22: ='Customer summary'!C10 | L22: ='Customer summary'!E10
B23: South | C23: =SUMIF(data!$C$2:$C$201, B23, data!$E$2:$E$201) | D23: =SUMIF(data!$C$2:$C$201, B23, data!$I$2:$I$201) | F23: Furniture | G23: =SUMIF(data!$D$2:$D$201, F23, data!$E$2:$E$201) | H23: =SUMIF(data!$D$2:$D$201, F23, data!$I$2:$I$201) | J23: Linda Wilson | K23: ='Customer summary'!C6 | L23: ='Customer summary'!E6
B24: West | C24: =SUMIF(data!$C$2:$C$201, B24, data!$E$2:$E$201) | D24: =SUMIF(data!$C$2:$C$201, B24, data!$I$2:$I$201) | F24: Office Supplies | G24: =SUMIF(data!$D$2:$D$201, F24, data!$E$2:$E$201) | H24: =SUMIF(data!$D$2:$D$201, F24, data!$I$2:$I$201) | J24: Robert Anderson | K24: ='Customer summary'!C2 | L24: ='Customer summary'!E2

Sheet data
A1: Customer_ID | B1: Customer_Name | C1: Region | D1: Product_Category | E1: Sales | F1: Quantity | G1: Discount | H1: Order_Date | I1: Profit | J1: Timestamp | K1: Month
A2: CUST019 | B2: James Davis | C2: West | D2: Books | E2: 1036.09 | F2: 4 | G2: 0.2 | H2: 45392 | I2: 331.55 | J2: =NOW() | K2: =DATE(YEAR(H2),MONTH(H2),1)
A3: CUST012 | B3: Robert Anderson | C3: West | D3: Clothing | E3: 1101.28 | F3: 3 | G3: 0.2 | H3: 45393 | I3: 440.51 | J3: =NOW() | K3: =DATE(YEAR(H3),MONTH(H3),1)
A4: CUST017 | B4: James Taylor | C4: East | D4: Books | E4: 713.34 | F4: 17 | G4: 0 | H4: 45396 | I4: 285.34 | J4: =NOW() | K4: =DATE(YEAR(H4),MONTH(H4),1)
A5: CUST005 | B5: Robert Anderson | C5: South | D5: Electronics | E5: 760.93 | F5: 4 | G5: 0.15 | H5: 45396 | I5: 161.7 | J5: =NOW() | K5: =DATE(YEAR(H5),MONTH(H5),1)
A6: CUST030 | B6: James Wilson | C6: North | D6: Books | E6: 847 | F6: 12 | G6: 0.2 | H6: 45397 | I6: 271.04 | J6: =NOW() | K6: =DATE(YEAR(H6),MONTH(H6),1)
A7: CUST007 | B7: Michael Anderson | C7: North | D7: Furniture | E7: 965.64 | F7: 8 | G7: 0.1 | H7: 45398 | I7: 304.18 | J7: =NOW() | K7: =DATE(YEAR(H7),MONTH(H7),1)
A8: CUST001 | B8: Linda Wilson | C8: West | D8: Electronics | E8: 1317.53 | F8: 12 | G8: 0.05 | H8: 45398 | I8: 312.91 | J8: =NOW() | K8: =DATE(YEAR(H8),MONTH(H8),1)
A9: CUST026 | B9: Mary Davis | C9: East | D9: Furniture | E9: 1074.47 | F9: 6 | G9: 0.2 | H9: 45401 | I9: 300.85 | J9: =NOW() | K9: =DATE(YEAR(H9),MONTH(H9),1)
A10: CUST009 | B10: Linda Jackson | C10: Central | D10: Books | E10: 501.54 | F10: 11 | G10: 0.05 | H10: 45401 | I10: 190.59 | J10: =NOW() | K10: =DATE(YEAR(H10),MONTH(H10),1)
A11: CUST010 | B11: David Thomas | C11: Central | D11: Clothing | E11: 737.31 | F11: 2 | G11: 0.05 | H11: 45401 | I11: 350.22 | J11: =NOW() | K11: =DATE(YEAR(H11),MONTH(H11),1)
A12: CUST014 | B12: Emma Davis | C12: West | D12: Office Supplies | E12: 1572.82 | F12: 6 | G12: 0.05 | H12: 45402 | I12: 672.38 | J12: =NOW() | K12: =DATE(YEAR(H12),MONTH(H12),1)
A13: CUST014 | B13: David Thomas | C13: Central | D13: Books | E13: 1343.13 | F13: 14 | G13: 0.15 | H13: 45404 | I13: 456.66 | J13: =NOW() | K13: =DATE(YEAR(H13),MONTH(H13),1)
... A201: CUST016 | B201: David Thomas | C201: South | D201: Clothing | E201: 928.32 | F201: 2 | G201: 0.05 | H201: 45754 | I201: 440.95 | J201: =NOW() | K201: =DATE(YEAR(H201),MONTH(H201),1)

Sheet Customer summary
A1: {=_xlfn.UNIQUE(Data[[#All],[Customer_ID]])} | B1: {=_xlfn.UNIQUE(Data[[#All],[Customer_Name]])} | C1: Total Purchase (Sales) | D1: Total Profit | E1: Order Count | F1: Rank | G1: TOP 10?
A2: CUST019 | B2: James Davis | C2: =SUMIF(data!$B$2:$B$201, B2,data!$E$2:$E$201) | D2: =SUMIF(data!$B$2:$B$201,B2,data!$I$2:$I$201) | E2: =COUNTIF(data!$B$2:$B$201,B2) | F2: =RANK(C2,$C$2:$C$28) | G2: =IF(F2<=10,"Yes","No")
A3: CUST012 | B3: Robert Anderson | C3: =SUMIF(data!$B$2:$B$201, B3,data!$E$2:$E$201) | D3: =SUMIF(data!$B$2:$B$201,B3,data!$I$2:$I$201) | E3: =COUNTIF(data!$B$2:$B$201,B3) | F3: =RANK(C3,$C$2:$C$28) | G3: =IF(F3<=10,"Yes","No")
A4: CUST017 | B4: James Taylor | C4: =SUMIF(data!$B$2:$B$201, B4,data!$E$2:$E$201) | D4: =SUMIF(data!$B$2:$B$201,B4,data!$I$2:$I$201) | E4: =COUNTIF(data!$B$2:$B$201,B4) | F4: =RANK(C4,$C$2:$C$28) | G4: =IF(F4<=10,"Yes","No")
A5: CUST005 | B5: James Wilson | C5: =SUMIF(data!$B$2:$B$201, B5,data!$E$2:$E$201) | D5: =SUMIF(data!$B$2:$B$201,B5,data!$I$2:$I$201) | E5: =COUNTIF(data!$B$2:$B$201,B5) | F5: =RANK(C5,$C$2:$C$28) | G5: =IF(F5<=10,"Yes","No")
A6: CUST030 | B6: Michael Anderson | C6: =SUMIF(data!$B$2:$B$201, B6,data!$E$2:$E$201) | D6: =SUMIF(data!$B$2:$B$201,B6,data!$I$2:$I$201) | E6: =COUNTIF(data!$B$2:$B$201,B6) | F6: =RANK(C6,$C$2:$C$28) | G6: =IF(F6<=10,"Yes","No")
A7: CUST007 | B7: Linda Wilson | C7: =SUMIF(data!$B$2:$B$201, B7,data!$E$2:$E$201) | D7: =SUMIF(data!$B$2:$B$201,B7,data!$I$2:$I$201) | E7: =COUNTIF(data!$B$2:$B$201,B7) | F7: =RANK(C7,$C$2:$C$28) | G7: =IF(F7<=10,"Yes","No")
A8: CUST001 | B8: Mary Davis | C8: =SUMIF(data!$B$2:$B$201, B8,data!$E$2:$E$201) | D8: =SUMIF(data!$B$2:$B$201,B8,data!$I$2:$I$201) | E8: =COUNTIF(data!$B$2:$B$201,B8) | F8: =RANK(C8,$C$2:$C$28) | G8: =IF(F8<=10,"Yes","No")
A9: CUST026 | B9: Linda Jackson | C9: =SUMIF(data!$B$2:$B$201, B9,data!$E$2:$E$201) | D9: =SUMIF(data!$B$2:$B$201,B9,data!$I$2:$I$201) | E9: =COUNTIF(data!$B$2:$B$201,B9) | F9: =RANK(C9,$C$2:$C$28) | G9: =IF(F9<=10,"Yes","No")
A10: CUST009 | B10: David Thomas | C10: =SUMIF(data!$B$2:$B$201, B10,data!$E$2:$E$201) | D10: =SUMIF(data!$B$2:$B$201,B10,data!$I$2:$I$201) | E10: =COUNTIF(data!$B$2:$B$201,B10) | F10: =RANK(C10,$C$2:$C$28) | G10: =IF(F10<=10,"Yes","No")
A11: CUST010 | B11: Emma Davis | C11: =SUMIF(data!$B$2:$B$201, B11,data!$E$2:$E$201) | D11: =SUMIF(data!$B$2:$B$201,B11,data!$I$2:$I$201) | E11: =COUNTIF(data!$B$2:$B$201,B11) | F11: =RANK(C11,$C$2:$C$28) | G11: =IF(F11<=10,"Yes","No")
A12: CUST014 | B12: David Smith | C12: =SUMIF(data!$B$2:$B$201, B12,data!$E$2:$E$201) | D12: =SUMIF(data!$B$2:$B$201,B12,data!$I$2:$I$201) | E12: =COUNTIF(data!$B$2:$B$201,B12) | F12: =RANK(C12,$C$2:$C$28) | G12: =IF(F12<=10,"Yes","No")
A13: CUST023 | B13: Sarah Anderson | C13: =SUMIF(data!$B$2:$B$201, B13,data!$E$2:$E$201) | D13: =SUMIF(data!$B$2:$B$201,B13,data!$I$2:$I$201) | E13: =COUNTIF(data!$B$2:$B$201,B13) | F13: =RANK(C13,$C$2:$C$28) | G13: =IF(F13<=10,"Yes","No")
... A28: CUST004 | B28: David Anderson | C28: =SUMIF(data!$B$2:$B$201, B28,data!$E$2:$E$201) | D28: =SUMIF(data!$B$2:$B$201,B28,data!$I$2:$I$201) | E28: =COUNTIF(data!$B$2:$B$201,B28) | F28: =RANK(C28,$C$2:$C$28) | G28: =IF(F28<=10,"Yes","No")
A29: CUST013 | C29: =SUMIF(data!$B$2:$B$201, B29,data!$E$2:$E$201) | D29: =SUMIF(data!$B$2:$B$201,B29,data!$I$2:$I$201) | E29: =COUNTIF(data!$B$2:$B$201,B29) | F29: =RANK(C29,$C$2:$C$28) | G29: =IF(F29<=10,"Yes","No")
A30: CUST027 | C30: =SUMIF(data!$B$2:$B$201, B30,data!$E$2:$E$201) | D30: =SUMIF(data!$B$2:$B$201,B30,data!$I$2:$I$201) | E30: =COUNTIF(data!$B$2:$B$201,B30) | F30: =RANK(C30,$C$2:$C$28) | G30: =IF(F30<=10,"Yes","No")
A31: CUST018 | C31: =SUMIF(data!$B$2:$B$201, B31,data!$E$2:$E$201) | D31: =SUMIF(data!$B$2:$B$201,B31,data!$I$2:$I$201) | E31: =COUNTIF(data!$B$2:$B$201,B31) | F31: =RANK(C31,$C$2:$C$28) | G31: =IF(F31<=10,"Yes","No")

Sheet What if
A1: WHAT IF ANALYSIS: Discount impact on price
A10: WHAT IF DATA | D10: CORRENT DATA | G10: Discount Level | H10: Adjusted Total Profit | I10: Change vs Current
G11: 0 | H11: {=E13-SUMPRODUCT((G11-data!$G$2:$G$201)*data!$E$2:$E$201)} | I11: =H11-$D$5
A12: Adjusted Total Profit at New Discount | B12: 0.1 | D12: Total Sales (all orders) | E12: =SUM(Data[Sales]) | G12: 0.05 | H12: {=E14-SUMPRODUCT((G12-data!$G$2:$G$201)*data!$E$2:$E$201)} | I12: =H12-$D$5
A13: Adjusted Total Profit at New Discount | B13: {=E13-SUMPRODUCT((#REF!-data!$G$2:$G$201)*data!$E$2:$E$201)} | D13: Total Profit (current discounts) | E13: =SUM(Data[Profit]) | G13: 0.1 | H13: {=E15-SUMPRODUCT((G13-data!$G$2:$G$201)*data!$E$2:$E$201)} | I13: =H13-$D$5
A14: Profit Impact ($) | B14: =E13-B13 | D14: Current Average Discount | E14: =AVERAGE(data!$G$2:$G$201) | G14: 0.15 | H14: {=E16-SUMPRODUCT((G14-data!$G$2:$G$201)*data!$E$2:$E$201)} | I14: =H14-$D$5
A15: Profit Impact (%) | B15: =B14/E13 | G15: 0.2 | H15: {=E17-SUMPRODUCT((G15-data!$G$2:$G$201)*data!$E$2:$E$201)} | I15: =H15-$D$5
G16: 0.25 | H16: {=E18-SUMPRODUCT((G16-data!$G$2:$G$201)*data!$E$2:$E$201)} | I16: =H16-$D$5
G17: 0.3 | H17: {=E19-SUMPRODUCT((G17-data!$G$2:$G$201)*data!$E$2:$E$201)} | I17: =H17-$D$5

Sheet Monthly sales
A3: MONTHLY SALES
A4: MONTH | B4: Total Sales | C4: Total Profit | D4: Growth V/S Prior month
A5: {=_xlfn.UNIQUE(Data[Month])} | C5: =SUMIFS(data!$I$2:$I$201,data!$K$2:$K$201,A5)
A6: 45413 | B6: =SUMIFS(data!$E$2:$E$201,data!$K$2:$K$201,A6) | C6: =SUMIFS(data!$I$2:$I$201,data!$K$2:$K$201,A6) | D6: =(B6-B5)/B5
A7: 45444 | B7: =SUMIFS(data!$E$2:$E$201,data!$K$2:$K$201,A7) | C7: =SUMIFS(data!$I$2:$I$201,data!$K$2:$K$201,A7) | D7: =(B7-B6)/B6
A8: 45474 | B8: =SUMIFS(data!$E$2:$E$201,data!$K$2:$K$201,A8) | C8: =SUMIFS(data!$I$2:$I$201,data!$K$2:$K$201,A8) | D8: =(B8-B7)/B7
A9: 45505 | B9: =SUMIFS(data!$E$2:$E$201,data!$K$2:$K$201,A9) | C9: =SUMIFS(data!$I$2:$I$201,data!$K$2:$K$201,A9) | D9: =(B9-B8)/B8
A10: 45536 | B10: =SUMIFS(data!$E$2:$E$201,data!$K$2:$K$201,A10) | C10: =SUMIFS(data!$I$2:$I$201,data!$K$2:$K$201,A10) | D10: =(B10-B9)/B9
A11: 45566 | B11: =SUMIFS(data!$E$2:$E$201,data!$K$2:$K$201,A11) | C11: =SUMIFS(data!$I$2:$I$201,data!$K$2:$K$201,A11) | D11: =(B11-B10)/B10
A12: 45597 | B12: =SUMIFS(data!$E$2:$E$201,data!$K$2:$K$201,A12) | C12: =SUMIFS(data!$I$2:$I$201,data!$K$2:$K$201,A12) | D12: =(B12-B11)/B11
A13: 45627 | B13: =SUMIFS(data!$E$2:$E$201,data!$K$2:$K$201,A13) | C13: =SUMIFS(data!$I$2:$I$201,data!$K$2:$K$201,A13) | D13: =(B13-B12)/B12
A14: 45658 | B14: =SUMIFS(data!$E$2:$E$201,data!$K$2:$K$201,A14) | C14: =SUMIFS(data!$I$2:$I$201,data!$K$2:$K$201,A14) | D14: =(B14-B13)/B13
A15: 45689 | B15: =SUMIFS(data!$E$2:$E$201,data!$K$2:$K$201,A15) | C15: =SUMIFS(data!$I$2:$I$201,data!$K$2:$K$201,A15) | D15: =(B15-B14)/B14
A16: 45717 | B16: =SUMIFS(data!$E$2:$E$201,data!$K$2:$K$201,A16) | C16: =SUMIFS(data!$I$2:$I$201,data!$K$2:$K$201,A16) | D16: =(B16-B15)/B15
A17: 45748 | B17: =SUMIFS(data!$E$2:$E$201,data!$K$2:$K$201,A17) | C17: =SUMIFS(data!$I$2:$I$201,data!$K$2:$K$201,A17) | D17: =(B17-B16)/B16

Sheet Descriptive satistics
B1: Descriptive statiscs
A2: Metric | B2: Sales | C2: Quantity | D2: Discount | E2: Profit
A3: Mean | B3: =AVERAGE(data!$E$2:$E$201) | C3: =AVERAGE(data!$F$2:$F$201) | D3: =AVERAGE(data!$G$2:$G$201) | E3: =AVERAGE(data!$I$2:$I$201)
A4: Median | B4: =MEDIAN(data!$E$2:$E$201) | C4: =MEDIAN(data!$F$2:$F$201) | D4: =MEDIAN(data!$G$2:$G$201) | E4: =MEDIAN(data!$I$2:$I$201)
A5: Mode | B5: =IFERROR(MODE(data!$E$2:$E$201),"No repeated value") | C5: =IFERROR(MODE(data!$F$2:$F$201),"No repeated value") | D5: =IFERROR(MODE(data!$G$2:$G$201),"No repeated value") | E5: =IFERROR(MODE(data!$I$2:$I$201),"No repeated value")
A6: Standard Deviation | B6: =STDEV(data!$E$2:$E$201) | C6: =STDEV(data!$F$2:$F$201) | D6: =STDEV(data!$G$2:$G$201) | E6: =STDEV(data!$I$2:$I$201)
A7: Variance | B7: =VAR(data!$E$2:$E$201) | C7: =VAR(data!$F$2:$F$201) | D7: =VAR(data!$G$2:$G$201) | E7: =VAR(data!$I$2:$I$201)
A8: Minimum | B8: =MIN(data!$E$2:$E$201) | C8: =MIN(data!$F$2:$F$201) | D8: =MIN(data!$G$2:$G$201) | E8: =MIN(data!$I$2:$I$201)
A9: Maximum | B9: =MAX(data!$E$2:$E$201) | C9: =MAX(data!$F$2:$F$201) | D9: =MAX(data!$G$2:$G$201) | E9: =MAX(data!$I$2:$I$201)
A10: Range | B10: =MAX(data!$E$2:$E$201)-MIN(data!$E$2:$E$201) | C10: =MAX(data!$F$2:$F$201)-MIN(data!$F$2:$F$201) | D10: =MAX(data!$G$2:$G$201)-MIN(data!$G$2:$G$201) | E10: =MAX(data!$I$2:$I$201)
A11: Count | B11: =COUNT(data!$E$2:$E$201) | C11: =COUNT(data!$F$2:$F$201) | D11: =COUNT(data!$G$2:$G$201) | E11: =COUNT(data!$I$2:$I$201)
A12: Sum | B12: =SUM(data!$E$2:$E$201) | C12: =SUM(data!$F$2:$F$201) | D12: =SUM(data!$G$2:$G$201) | E12: =SUM(data!$I$2:$I$201)

Sheet Regression
A1: REGRESSION: Profit vs Sales
A3: Regression Statistics
A4: Multiple R | B4: 0.77340306
A5: R Square | B5: 0.5981523
A6: Adjusted R Square | B6: 0.59612277
A7: Standard Error | B7: 190.19247
A8: Observations | B8: 200
A10: ANOVA
B11: df | C11: SS | D11: MS | E11: F | F11: Significance F
A12: Regression | B12: 1 | C12: 10661103 | D12: 10661103 | E12: 294.72398 | F12: 4.6269368e-41
A13: Residual | B13: 198 | C13: 7162289 | D13: 36173.177
A14: Total | B14: 199 | C14: 17823392
B16: Coefficients | C16: Standard Error | D16: t Stat | E16: P-value | F16: Lower 95% | G16: Upper 95% | H16: Lower 95.0% | I16: Upper 95.0%
A17: Intercept | B17: 393.99767 | C17: 36.476268 | D17: 10.80148 | E17: 1.1137843e-21 | F17: 322.06583 | G17: 465.9295 | H17: 322.06583 | I17: 465.9295
A18: Profit | B18: 1.7048371 | C18: 0.099305921 | D18: 17.167527 | E18: 4.6269368e-41 | F18: 1.5090041 | G18: 1.9006701 | H18: 1.5090041 | I18: 1.9006701

Sheet Pivot Table
A1: Total sales by region and product
A6: Sum of Sales | B6: Column Labels
A7: Row Labels | B7: Central | C7: East | D7: North | E7: South | F7: West | G7: Grand Total
A8: Books | B8: 11297.15 | C8: 11389.09 | D8: 8037.01 | E8: 9588.04 | F8: 6691.17 | G8: 47002.46
A9: Clothing | B9: 12200.26 | C9: 2401.45 | D9: 8422.82 | E9: 8393.63 | F9: 10509.43 | G9: 41927.59
A10: Electronics | B10: 6621.24 | C10: 2869.54 | D10: 8191.71 | E10: 11989.07 | F10: 11372.44 | G10: 41044
A11: Furniture | B11: 4876.96 | C11: 7592.34 | D11: 6978.08 | E11: 7982.73 | F11: 9182.78 | G11: 36612.89
A12: Office Supplies | B12: 8472.72 | C12: 8189.22 | D12: 3345.8 | E12: 2295.32 | F12: 6327.76 | G12: 28630.82
A13: Grand Total | B13: 43468.33 | C13: 32441.64 | D13: 34975.42 | E13: 40248.79 | F13: 44083.58 | G13: 195217.76
