Workbook
Name Slicer_Customer_Segment: #N/A
Name Slicer_Product_Name: #N/A

Sheet Dashboard
B1: RETAIL SALES PERFORMANCE DASHBOARD | N1: CONFIDENTIAL REPORT
B2: Transaction Analytics · Apr 2024 – Apr 2025
B4: Total Revenue 💰 | F4: Total Orders 🛒 | J4: Unique Customers 👥 | N4: Avg Order Value 📊
B6: ='Dashboard Resources'!B5 -> 229192.47 | F6: ='Dashboard Resources'!B6 -> 250 | J6: ='Dashboard Resources'!B7 -> 50 | N6: ='Dashboard Resources'!B8 -> 916.76988
J25: Total Revenue: $229,192.47 across 250 orders (Average Order Value: $916.77).
J27: Top Product Category: Electronics generated 74.9% ($171,756.05) of total sales, driven primarily by Laptops and Smartphones.
F28: Electronics
J29: Top Region: East led all sales territories with $59,288.39 (25.9% share) and the highest average spend per order ($1,235.17).

Sheet Dashboard Resources
A1: Dashboard Resources — every table and figure the Dashboard sheet pulls from
A2: Kept separate from the Dashboard sheet so the dashboard itself stays clean and presentation-ready. Region and Monthly-by-Category figures reuse the PivotTables sheet (Pivot 1 & Pivot 2) directly — not duplicated here.
A4: KPI Base Figures
A5: Total Revenue | B5: =SUM(tblClean[Total_Amount]) -> 229192.47
A6: Total Orders | B6: =COUNTA(tblClean[Transaction_ID]) -> 250
A7: Unique Customers | B7: =SUMPRODUCT(1/COUNTIF(tblClean[Customer_ID],tblClean[Customer_ID])) -> 50
A8: Avg Order Value | B8: =B5/B6 -> 916.76988
A10: Revenue by Product (sorted descending) — feeds Dashboard bar chart
A11: Row Labels | B11: Sum of Total_Amount
A12: Blender | B12: 5219.13
A13: Bookshelf | B13: 15298.98
A14: Coffee Maker | B14: 3119.61
A15: Desk | B15: 23399.22
A16: Headphones | B16: 7049.53
A17: Keyboard | B17: 8009.11
A18: Laptop | B18: 67499.25
A19: Monitor | B19: 21999.12
A20: Office Chair | B20: 10399.48
A21: Smartphone | B21: 67199.04
A22: Grand Total | B22: 229192.47
A23: Revenue by Customer Segment — feeds Dashboard donut chart
A24: Row Labels | B24: Sum of Total_Amount
A25: Basic | B25: 62177.81
A26: Premium | B26: 84657.12
A27: Standard | B27: 82357.54
A28: Grand Total | B28: 229192.47

Sheet Raw_Data
A1: Transaction_ID | B1: Date | C1: Customer | D1: Customer_Name | E1: Product_ID | F1: Product_Name | G1: Category | H1: Quantity | I1: Unit_Price | J1: Payment_Method | K1: Region | L1: Customer_Segment | M1: Customer_Since | N1: Total_Amount
A2: TRX0155 | B2: 45393 | C2: CUST023 | D2: Paul Baker | E2: P009 | F2: Monitor | G2: Electronics | H2: 3 | I2: 249.99 | J2: Cash | K2: Central | L2: Basic | M2: 44425 | N2: 749.97
A3: TRX0023 | B3: 45396 | C3: CUST013 | D3: Joseph Jackson | E3: P009 | F3: Monitor | G3: Electronics | H3: 3 | I3: 249.99 | J3: Credit Card | K3: Central | L3: Premium | M3: 44575 | N3: 749.97
A4: TRX0139 | B4: 45399 | C4: CUST021 | D4: Kevin Scott | E4: P005 | F4: Blender | G4: Appliances | H4: 3 | I4: 59.99 | J4: PayPal | K4: South | L4: Standard | M4: 45262 | N4: 179.97
A5: TRX0043 | B5: 45400 | C5: CUST046 | D5: Kathleen Bennett | E5: P005 | F5: Blender | G5: Appliances | H5: 3 | I5: 59.99 | J5: Cash | K5: North | L5: Premium | M5: 45114 | N5: 179.97
A6: TRX0212 | B6: 45400 | C6: CUST003 | D6: Michael Brown | E6: P008 | F6: Bookshelf | G6: Furniture | H6: 5 | I6: 149.99 | J6: Credit Card | K6: North | L6: Premium | M6: 45295 | N6: 749.95
A7: TRX0092 | B7: 45403 | C7: CUST024 | D7: Dorothy Nelson | E7: P005 | F7: Blender | G7: Appliances | H7: 2 | I7: 59.99 | J7: Cash | K7: West | L7: Standard | M7: 44746 | N7: 119.98
A8: TRX0193 | B8: 45403 | C8: CUST024 | D8: Dorothy Nelson | E8: P003 | F8: Headphones | G8: Electronics | H8: 5 | I8: 149.99 | J8: Credit Card | K8: Central | L8: Standard | M8: 44418 | N8: 749.95
A9: TRX0240 | B9: 45403 | C9: CUST017 | D9: Charles Allen | E9: P005 | F9: Blender | G9: Appliances | H9: 3 | I9: 59.99 | J9: Debit Card | K9: South | L9: Basic | M9: 45007 | N9: 179.97
A10: TRX0135 | B10: 45405 | C10: CUST009 | D10: Robert Thomas | E10: P001 | F10: Laptop | G10: Electronics | H10: 3 | I10: 899.99 | J10: PayPal | K10: East | L10: Standard | M10: 45299 | N10: 2699.97
A11: TRX0185 | B11: 45408 | C11: CUST026 | D11: Karen Hill | E11: P005 | F11: Blender | G11: Appliances | H11: 3 | I11: 59.99 | J11: Cash | K11: West | L11: Premium | M11: 45207 | N11: 179.97
A12: TRX0138 | B12: 45408 | C12: CUST022 | D12: Susan Green | E12: P008 | F12: Bookshelf | G12: Furniture | H12: 1 | I12: 149.99 | J12: Credit Card | K12: West | L12: Standard | M12: 45103 | N12: 149.99
A13: TRX0209 | B13: 45408 | C13: CUST046 | D13: Kathleen Bennett | E13: P008 | F13: Bookshelf | G13: Furniture | H13: 5 | I13: 149.99 | J13: Debit Card | K13: North | L13: Basic | M13: 44830 | N13: 749.95
... A251: TRX0064 | B251: 45758 | C251: CUST031 | D251: Steven Turner | E251: P010 | F251: Keyboard | G251: Electronics | H251: 3 | I251: 89.99 | J251: Debit Card | K251: North | L251: Premium | M251: 44878 | N251: 269.97

Sheet Data_Cleaning
A1: Transaction_ID | B1: Date | C1: Customer_ID | D1: Customer_Name | E1: Product_ID | F1: Product_Name | G1: Category | H1: Quantity | I1: Unit_Price | J1: Payment_Method | K1: Region | L1: Customer_Segment | M1: Customer_Since | N1: Total_Amount
A2: =UPPER(TRIM(Raw_Data!A2)) -> TRX0155 | B2: =Raw_Data!B2 -> 45393 | C2: =UPPER(TRIM(Raw_Data!C2)) -> CUST023 | D2: =PROPER(TRIM(Raw_Data!D2)) -> Paul Baker | E2: =UPPER(TRIM(Raw_Data!E2)) -> P009 | F2: =PROPER(TRIM(Raw_Data!F2)) -> Monitor | G2: =PROPER(TRIM(Raw_Data!G2)) -> Electronics | H2: =Raw_Data!H2 -> 3 | I2: =Raw_Data!I2 -> 249.99 | J2: =PROPER(TRIM(Raw_Data!J2)) -> Cash | K2: =PROPER(TRIM(Raw_Data!K2)) -> Central | L2: =PROPER(TRIM(Raw_Data!L2)) -> Basic | M2: =Raw_Data!M2 -> 44425 | N2: =Raw_Data!N2 -> 749.97
A3: =UPPER(TRIM(Raw_Data!A3)) -> TRX0023 | B3: =Raw_Data!B3 -> 45396 | C3: =UPPER(TRIM(Raw_Data!C3)) -> CUST013 | D3: =PROPER(TRIM(Raw_Data!D3)) -> Joseph Jackson | E3: =UPPER(TRIM(Raw_Data!E3)) -> P009 | F3: =PROPER(TRIM(Raw_Data!F3)) -> Monitor | G3: =PROPER(TRIM(Raw_Data!G3)) -> Electronics | H3: =Raw_Data!H3 -> 3 | I3: =Raw_Data!I3 -> 249.99 | J3: =PROPER(TRIM(Raw_Data!J3)) -> Credit Card | K3: =PROPER(TRIM(Raw_Data!K3)) -> Central | L3: =PROPER(TRIM(Raw_Data!L3)) -> Premium | M3: =Raw_Data!M3 -> 44575 | N3: =Raw_Data!N3 -> 749.97
A4: =UPPER(TRIM(Raw_Data!A4)) -> TRX0139 | B4: =Raw_Data!B4 -> 45399 | C4: =UPPER(TRIM(Raw_Data!C4)) -> CUST021 | D4: =PROPER(TRIM(Raw_Data!D4)) -> Kevin Scott | E4: =UPPER(TRIM(Raw_Data!E4)) -> P005 | F4: =PROPER(TRIM(Raw_Data!F4)) -> Blender | G4: =PROPER(TRIM(Raw_Data!G4)) -> Appliances | H4: =Raw_Data!H4 -> 3 | I4: =Raw_Data!I4 -> 59.99 | J4: =PROPER(TRIM(Raw_Data!J4)) -> Paypal | K4: =PROPER(TRIM(Raw_Data!K4)) -> South | L4: =PROPER(TRIM(Raw_Data!L4)) -> Standard | M4: =Raw_Data!M4 -> 45262 | N4: =Raw_Data!N4 -> 179.97
A5: =UPPER(TRIM(Raw_Data!A5)) -> TRX0043 | B5: =Raw_Data!B5 -> 45400 | C5: =UPPER(TRIM(Raw_Data!C5)) -> CUST046 | D5: =PROPER(TRIM(Raw_Data!D5)) -> Kathleen Bennett | E5: =UPPER(TRIM(Raw_Data!E5)) -> P005 | F5: =PROPER(TRIM(Raw_Data!F5)) -> Blender | G5: =PROPER(TRIM(Raw_Data!G5)) -> Appliances | H5: =Raw_Data!H5 -> 3 | I5: =Raw_Data!I5 -> 59.99 | J5: =PROPER(TRIM(Raw_Data!J5)) -> Cash | K5: =PROPER(TRIM(Raw_Data!K5)) -> North | L5: =PROPER(TRIM(Raw_Data!L5)) -> Premium | M5: =Raw_Data!M5 -> 45114 | N5: =Raw_Data!N5 -> 179.97
A6: =UPPER(TRIM(Raw_Data!A6)) -> TRX0212 | B6: =Raw_Data!B6 -> 45400 | C6: =UPPER(TRIM(Raw_Data!C6)) -> CUST003 | D6: =PROPER(TRIM(Raw_Data!D6)) -> Michael Brown | E6: =UPPER(TRIM(Raw_Data!E6)) -> P008 | F6: =PROPER(TRIM(Raw_Data!F6)) -> Bookshelf | G6: =PROPER(TRIM(Raw_Data!G6)) -> Furniture | H6: =Raw_Data!H6 -> 5 | I6: =Raw_Data!I6 -> 149.99 | J6: =PROPER(TRIM(Raw_Data!J6)) -> Credit Card | K6: =PROPER(TRIM(Raw_Data!K6)) -> North | L6: =PROPER(TRIM(Raw_Data!L6)) -> Premium | M6: =Raw_Data!M6 -> 45295 | N6: =Raw_Data!N6 -> 749.95
A7: =UPPER(TRIM(Raw_Data!A7)) -> TRX0092 | B7: =Raw_Data!B7 -> 45403 | C7: =UPPER(TRIM(Raw_Data!C7)) -> CUST024 | D7: =PROPER(TRIM(Raw_Data!D7)) -> Dorothy Nelson | E7: =UPPER(TRIM(Raw_Data!E7)) -> P005 | F7: =PROPER(TRIM(Raw_Data!F7)) -> Blender | G7: =PROPER(TRIM(Raw_Data!G7)) -> Appliances | H7: =Raw_Data!H7 -> 2 | I7: =Raw_Data!I7 -> 59.99 | J7: =PROPER(TRIM(Raw_Data!J7)) -> Cash | K7: =PROPER(TRIM(Raw_Data!K7)) -> West | L7: =PROPER(TRIM(Raw_Data!L7)) -> Standard | M7: =Raw_Data!M7 -> 44746 | N7: =Raw_Data!N7 -> 119.98
A8: =UPPER(TRIM(Raw_Data!A8)) -> TRX0193 | B8: =Raw_Data!B8 -> 45403 | C8: =UPPER(TRIM(Raw_Data!C8)) -> CUST024 | D8: =PROPER(TRIM(Raw_Data!D8)) -> Dorothy Nelson | E8: =UPPER(TRIM(Raw_Data!E8)) -> P003 | F8: =PROPER(TRIM(Raw_Data!F8)) -> Headphones | G8: =PROPER(TRIM(Raw_Data!G8)) -> Electronics | H8: =Raw_Data!H8 -> 5 | I8: =Raw_Data!I8 -> 149.99 | J8: =PROPER(TRIM(Raw_Data!J8)) -> Credit Card | K8: =PROPER(TRIM(Raw_Data!K8)) -> Central | L8: =PROPER(TRIM(Raw_Data!L8)) -> Standard | M8: =Raw_Data!M8 -> 44418 | N8: =Raw_Data!N8 -> 749.95
A9: =UPPER(TRIM(Raw_Data!A9)) -> TRX0240 | B9: =Raw_Data!B9 -> 45403 | C9: =UPPER(TRIM(Raw_Data!C9)) -> CUST017 | D9: =PROPER(TRIM(Raw_Data!D9)) -> Charles Allen | E9: =UPPER(TRIM(Raw_Data!E9)) -> P005 | F9: =PROPER(TRIM(Raw_Data!F9)) -> Blender | G9: =PROPER(TRIM(Raw_Data!G9)) -> Appliances | H9: =Raw_Data!H9 -> 3 | I9: =Raw_Data!I9 -> 59.99 | J9: =PROPER(TRIM(Raw_Data!J9)) -> Debit Card | K9: =PROPER(TRIM(Raw_Data!K9)) -> South | L9: =PROPER(TRIM(Raw_Data!L9)) -> Basic | M9: =Raw_Data!M9 -> 45007 | N9: =Raw_Data!N9 -> 179.97
A10: =UPPER(TRIM(Raw_Data!A10)) -> TRX0135 | B10: =Raw_Data!B10 -> 45405 | C10: =UPPER(TRIM(Raw_Data!C10)) -> CUST009 | D10: =PROPER(TRIM(Raw_Data!D10)) -> Robert Thomas | E10: =UPPER(TRIM(Raw_Data!E10)) -> P001 | F10: =PROPER(TRIM(Raw_Data!F10)) -> Laptop | G10: =PROPER(TRIM(Raw_Data!G10)) -> Electronics | H10: =Raw_Data!H10 -> 3 | I10: =Raw_Data!I10 -> 899.99 | J10: =PROPER(TRIM(Raw_Data!J10)) -> Paypal | K10: =PROPER(TRIM(Raw_Data!K10)) -> East | L10: =PROPER(TRIM(Raw_Data!L10)) -> Standard | M10: =Raw_Data!M10 -> 45299 | N10: =Raw_Data!N10 -> 2699.97
A11: =UPPER(TRIM(Raw_Data!A11)) -> TRX0185 | B11: =Raw_Data!B11 -> 45408 | C11: =UPPER(TRIM(Raw_Data!C11)) -> CUST026 | D11: =PROPER(TRIM(Raw_Data!D11)) -> Karen Hill | E11: =UPPER(TRIM(Raw_Data!E11)) -> P005 | F11: =PROPER(TRIM(Raw_Data!F11)) -> Blender | G11: =PROPER(TRIM(Raw_Data!G11)) -> Appliances | H11: =Raw_Data!H11 -> 3 | I11: =Raw_Data!I11 -> 59.99 | J11: =PROPER(TRIM(Raw_Data!J11)) -> Cash | K11: =PROPER(TRIM(Raw_Data!K11)) -> West | L11: =PROPER(TRIM(Raw_Data!L11)) -> Premium | M11: =Raw_Data!M11 -> 45207 | N11: =Raw_Data!N11 -> 179.97
A12: =UPPER(TRIM(Raw_Data!A12)) -> TRX0138 | B12: =Raw_Data!B12 -> 45408 | C12: =UPPER(TRIM(Raw_Data!C12)) -> CUST022 | D12: =PROPER(TRIM(Raw_Data!D12)) -> Susan Green | E12: =UPPER(TRIM(Raw_Data!E12)) -> P008 | F12: =PROPER(TRIM(Raw_Data!F12)) -> Bookshelf | G12: =PROPER(TRIM(Raw_Data!G12)) -> Furniture | H12: =Raw_Data!H12 -> 1 | I12: =Raw_Data!I12 -> 149.99 | J12: =PROPER(TRIM(Raw_Data!J12)) -> Credit Card | K12: =PROPER(TRIM(Raw_Data!K12)) -> West | L12: =PROPER(TRIM(Raw_Data!L12)) -> Standard | M12: =Raw_Data!M12 -> 45103 | N12: =Raw_Data!N12 -> 149.99
A13: =UPPER(TRIM(Raw_Data!A13)) -> TRX0209 | B13: =Raw_Data!B13 -> 45408 | C13: =UPPER(TRIM(Raw_Data!C13)) -> CUST046 | D13: =PROPER(TRIM(Raw_Data!D13)) -> Kathleen Bennett | E13: =UPPER(TRIM(Raw_Data!E13)) -> P008 | F13: =PROPER(TRIM(Raw_Data!F13)) -> Bookshelf | G13: =PROPER(TRIM(Raw_Data!G13)) -> Furniture | H13: =Raw_Data!H13 -> 5 | I13: =Raw_Data!I13 -> 149.99 | J13: =PROPER(TRIM(Raw_Data!J13)) -> Debit Card | K13: =PROPER(TRIM(Raw_Data!K13)) -> North | L13: =PROPER(TRIM(Raw_Data!L13)) -> Basic | M13: =Raw_Data!M13 -> 44830 | N13: =Raw_Data!N13 -> 749.95
... A251: =UPPER(TRIM(Raw_Data!A251)) -> TRX0064 | B251: =Raw_Data!B251 -> 45758 | C251: =UPPER(TRIM(Raw_Data!C251)) -> CUST031 | D251: =PROPER(TRIM(Raw_Data!D251)) -> Steven Turner | E251: =UPPER(TRIM(Raw_Data!E251)) -> P010 | F251: =PROPER(TRIM(Raw_Data!F251)) -> Keyboard | G251: =PROPER(TRIM(Raw_Data!G251)) -> Electronics | H251: =Raw_Data!H251 -> 3 | I251: =Raw_Data!I251 -> 89.99 | J251: =PROPER(TRIM(Raw_Data!J251)) -> Debit Card | K251: =PROPER(TRIM(Raw_Data!K251)) -> North | L251: =PROPER(TRIM(Raw_Data!L251)) -> Premium | M251: =Raw_Data!M251 -> 44878 | N251: =Raw_Data!N251 -> 269.97

Sheet Analysis
A3: Customer_ID | B3: Customer_Name | C3: Customer_Since | D3: Tenure_Years | E3: Total_Spend | F3: Order_Count | G3: Avg_Order_Value | H3: Spend_Rank | I3: High_Value_Flag | J3: Bought_Laptop | K3: Premium_and_Laptop_Match | L3: Customer_Code | O3: 2. MOST FREQUENTLY PURCHASED PRODUCT | W3: 3. MULTI-VALUE FILTER BY CATEGORY (INDEX + SMALL + IF array formula)
A4: CUST001 | B4: =INDEX(Data_Cleaning!$D$2:$D$251,MATCH(A4,Data_Cleaning!$C$2:$C$251,0)) -> John Smith | C4: =INDEX(Data_Cleaning!$M$2:$M$251,MATCH(A4,Data_Cleaning!$C$2:$C$251,0)) -> 44560 | D4: =DATEDIF(C4,TODAY(),"y") -> 4 | E4: =SUMIFS(Data_Cleaning!$N$2:$N$251,Data_Cleaning!$C$2:$C$251,A4) -> 599.96 | F4: =COUNTIFS(Data_Cleaning!$C$2:$C$251,A4) -> 1 | G4: =IFERROR(E4/F4,0) -> 599.96 | H4: =RANK(E4,$E$4:$E$53) -> 47 | I4: =IF(H4<=10,"High Value","Standard") -> Standard | J4: =IF(COUNTIFS(Data_Cleaning!$C$2:$C$251,A4,Data_Cleaning!$F$2:$F$251,"Laptop")>0,"Yes","No") -> No | K4: =IF(AND(COUNTIFS(Data_Cleaning!$C$2:$C$251,A4,Data_Cleaning!$L$2:$L$251,"Premium")>0,J4="Yes"),B4,"") | L4: =UPPER(LEFT(B4,3))&"-"&RIGHT(A4,3) -> JOH-001
A5: CUST002 | B5: =INDEX(Data_Cleaning!$D$2:$D$251,MATCH(A5,Data_Cleaning!$C$2:$C$251,0)) -> Emma Wilson | C5: =INDEX(Data_Cleaning!$M$2:$M$251,MATCH(A5,Data_Cleaning!$C$2:$C$251,0)) -> 45068 | D5: =DATEDIF(C5,TODAY(),"y") -> 3 | E5: =SUMIFS(Data_Cleaning!$N$2:$N$251,Data_Cleaning!$C$2:$C$251,A5) -> 1229.88 | F5: =COUNTIFS(Data_Cleaning!$C$2:$C$251,A5) -> 5 | G5: =IFERROR(E5/F5,0) -> 245.976 | H5: =RANK(E5,$E$4:$E$53) -> 44 | I5: =IF(H5<=10,"High Value","Standard") -> Standard | J5: =IF(COUNTIFS(Data_Cleaning!$C$2:$C$251,A5,Data_Cleaning!$F$2:$F$251,"Laptop")>0,"Yes","No") -> No | K5: =IF(AND(COUNTIFS(Data_Cleaning!$C$2:$C$251,A5,Data_Cleaning!$L$2:$L$251,"Premium")>0,J5="Yes"),B5,"") | L5: =UPPER(LEFT(B5,3))&"-"&RIGHT(A5,3) -> EMM-002 | O5: Product_ID | P5: Product_Name | Q5: Units_Sold | R5: Times_Purchased | S5: Revenue | T5: Product_Code | W5: Select a Category: | X5: Electronics
A6: CUST003 | B6: =INDEX(Data_Cleaning!$D$2:$D$251,MATCH(A6,Data_Cleaning!$C$2:$C$251,0)) -> Michael Brown | C6: =INDEX(Data_Cleaning!$M$2:$M$251,MATCH(A6,Data_Cleaning!$C$2:$C$251,0)) -> 45295 | D6: =DATEDIF(C6,TODAY(),"y") -> 2 | E6: =SUMIFS(Data_Cleaning!$N$2:$N$251,Data_Cleaning!$C$2:$C$251,A6) -> 6169.74 | F6: =COUNTIFS(Data_Cleaning!$C$2:$C$251,A6) -> 9 | G6: =IFERROR(E6/F6,0) -> 685.52667 | H6: =RANK(E6,$E$4:$E$53) -> 14 | I6: =IF(H6<=10,"High Value","Standard") -> Standard | J6: =IF(COUNTIFS(Data_Cleaning!$C$2:$C$251,A6,Data_Cleaning!$F$2:$F$251,"Laptop")>0,"Yes","No") -> No | K6: =IF(AND(COUNTIFS(Data_Cleaning!$C$2:$C$251,A6,Data_Cleaning!$L$2:$L$251,"Premium")>0,J6="Yes"),B6,"") | L6: =UPPER(LEFT(B6,3))&"-"&RIGHT(A6,3) -> MIC-003 | O6: P001 | P6: Laptop | Q6: =SUMIFS(Data_Cleaning!$H$2:$H$251,Data_Cleaning!$E$2:$E$251,O6) -> 75 | R6: =COUNTIFS(Data_Cleaning!$E$2:$E$251,O6) -> 24 | S6: =SUMIFS(Data_Cleaning!$N$2:$N$251,Data_Cleaning!$E$2:$E$251,O6) -> 67499.25 | T6: =UPPER(LEFT(P6,1))&UPPER(LEFT(SUBSTITUTE(P6," ",""),3)) -> LLAP
A7: CUST004 | B7: =INDEX(Data_Cleaning!$D$2:$D$251,MATCH(A7,Data_Cleaning!$C$2:$C$251,0)) -> Sarah Davis | C7: =INDEX(Data_Cleaning!$M$2:$M$251,MATCH(A7,Data_Cleaning!$C$2:$C$251,0)) -> 44587 | D7: =DATEDIF(C7,TODAY(),"y") -> 4 | E7: =SUMIFS(Data_Cleaning!$N$2:$N$251,Data_Cleaning!$C$2:$C$251,A7) -> 5499.81 | F7: =COUNTIFS(Data_Cleaning!$C$2:$C$251,A7) -> 5 | G7: =IFERROR(E7/F7,0) -> 1099.962 | H7: =RANK(E7,$E$4:$E$53) -> 19 | I7: =IF(H7<=10,"High Value","Standard") -> Standard | J7: =IF(COUNTIFS(Data_Cleaning!$C$2:$C$251,A7,Data_Cleaning!$F$2:$F$251,"Laptop")>0,"Yes","No") -> No | K7: =IF(AND(COUNTIFS(Data_Cleaning!$C$2:$C$251,A7,Data_Cleaning!$L$2:$L$251,"Premium")>0,J7="Yes"),B7,"") | L7: =UPPER(LEFT(B7,3))&"-"&RIGHT(A7,3) -> SAR-004 | O7: P002 | P7: Smartphone | Q7: =SUMIFS(Data_Cleaning!$H$2:$H$251,Data_Cleaning!$E$2:$E$251,O7) -> 96 | R7: =COUNTIFS(Data_Cleaning!$E$2:$E$251,O7) -> 31 | S7: =SUMIFS(Data_Cleaning!$N$2:$N$251,Data_Cleaning!$E$2:$E$251,O7) -> 67199.04 | T7: =UPPER(LEFT(P7,1))&UPPER(LEFT(SUBSTITUTE(P7," ",""),3)) -> SSMA | W7: Transaction_ID | X7: Date | Y7: Customer_Name | Z7: Product_Name | AA7: Total_Amount
A8: CUST005 | B8: =INDEX(Data_Cleaning!$D$2:$D$251,MATCH(A8,Data_Cleaning!$C$2:$C$251,0)) -> James Johnson | C8: =INDEX(Data_Cleaning!$M$2:$M$251,MATCH(A8,Data_Cleaning!$C$2:$C$251,0)) -> 45052 | D8: =DATEDIF(C8,TODAY(),"y") -> 3 | E8: =SUMIFS(Data_Cleaning!$N$2:$N$251,Data_Cleaning!$C$2:$C$251,A8) -> 179.97 | F8: =COUNTIFS(Data_Cleaning!$C$2:$C$251,A8) -> 1 | G8: =IFERROR(E8/F8,0) -> 179.97 | H8: =RANK(E8,$E$4:$E$53) -> 50 | I8: =IF(H8<=10,"High Value","Standard") -> Standard | J8: =IF(COUNTIFS(Data_Cleaning!$C$2:$C$251,A8,Data_Cleaning!$F$2:$F$251,"Laptop")>0,"Yes","No") -> No | K8: =IF(AND(COUNTIFS(Data_Cleaning!$C$2:$C$251,A8,Data_Cleaning!$L$2:$L$251,"Premium")>0,J8="Yes"),B8,"") | L8: =UPPER(LEFT(B8,3))&"-"&RIGHT(A8,3) -> JAM-005 | O8: P003 | P8: Headphones | Q8: =SUMIFS(Data_Cleaning!$H$2:$H$251,Data_Cleaning!$E$2:$E$251,O8) -> 47 | R8: =COUNTIFS(Data_Cleaning!$E$2:$E$251,O8) -> 16 | S8: =SUMIFS(Data_Cleaning!$N$2:$N$251,Data_Cleaning!$E$2:$E$251,O8) -> 7049.53 | T8: =UPPER(LEFT(P8,1))&UPPER(LEFT(SUBSTITUTE(P8," ",""),3)) -> HHEA | W8: {=IFERROR(INDEX(Data_Cleaning!$A$2:$A$251,SMALL(IF(Data_Cleaning!$G$2:$G$251=$X5,ROW(Data_Cleaning!$G$2:$G$251)-ROW(Data_Cleaning!$G$2)+1),1)),"")} -> TRX0155 | X8: {=IFERROR(INDEX(Data_Cleaning!$B$2:$B$251,SMALL(IF(Data_Cleaning!$G$2:$G$251=$X5,ROW(Data_Cleaning!$G$2:$G$251)-ROW(Data_Cleaning!$G$2)+1),1)),"")} -> 45393 | Y8: {=IFERROR(INDEX(Data_Cleaning!$D$2:$D$251,SMALL(IF(Data_Cleaning!$G$2:$G$251=$X5,ROW(Data_Cleaning!$G$2:$G$251)-ROW(Data_Cleaning!$G$2)+1),1)),"")} -> Paul Baker | Z8: {=IFERROR(INDEX(Data_Cleaning!$F$2:$F$251,SMALL(IF(Data_Cleaning!$G$2:$G$251=$X5,ROW(Data_Cleaning!$G$2:$G$251)-ROW(Data_Cleaning!$G$2)+1),1)),"")} -> Monitor | AA8: {=IFERROR(INDEX(Data_Cleaning!$N$2:$N$251,SMALL(IF(Data_Cleaning!$G$2:$G$251=$X5,ROW(Data_Cleaning!$G$2:$G$251)-ROW(Data_Cleaning!$G$2)+1),1)),"")} -> 749.97
A9: CUST006 | B9: =INDEX(Data_Cleaning!$D$2:$D$251,MATCH(A9,Data_Cleaning!$C$2:$C$251,0)) -> Lisa Anderson | C9: =INDEX(Data_Cleaning!$M$2:$M$251,MATCH(A9,Data_Cleaning!$C$2:$C$251,0)) -> 44823 | D9: =DATEDIF(C9,TODAY(),"y") -> 4 | E9: =SUMIFS(Data_Cleaning!$N$2:$N$251,Data_Cleaning!$C$2:$C$251,A9) -> 2039.8 | F9: =COUNTIFS(Data_Cleaning!$C$2:$C$251,A9) -> 5 | G9: =IFERROR(E9/F9,0) -> 407.96 | H9: =RANK(E9,$E$4:$E$53) -> 36 | I9: =IF(H9<=10,"High Value","Standard") -> Standard | J9: =IF(COUNTIFS(Data_Cleaning!$C$2:$C$251,A9,Data_Cleaning!$F$2:$F$251,"Laptop")>0,"Yes","No") -> No | K9: =IF(AND(COUNTIFS(Data_Cleaning!$C$2:$C$251,A9,Data_Cleaning!$L$2:$L$251,"Premium")>0,J9="Yes"),B9,"") | L9: =UPPER(LEFT(B9,3))&"-"&RIGHT(A9,3) -> LIS-006 | O9: P004 | P9: Coffee Maker | Q9: =SUMIFS(Data_Cleaning!$H$2:$H$251,Data_Cleaning!$E$2:$E$251,O9) -> 39 | R9: =COUNTIFS(Data_Cleaning!$E$2:$E$251,O9) -> 14 | S9: =SUMIFS(Data_Cleaning!$N$2:$N$251,Data_Cleaning!$E$2:$E$251,O9) -> 3119.61 | T9: =UPPER(LEFT(P9,1))&UPPER(LEFT(SUBSTITUTE(P9," ",""),3)) -> CCOF | W9: {=IFERROR(INDEX(Data_Cleaning!$A$2:$A$251,SMALL(IF(Data_Cleaning!$G$2:$G$251=$X5,ROW(Data_Cleaning!$G$2:$G$251)-ROW(Data_Cleaning!$G$2)+1),2)),"")} -> TRX0023 | X9: {=IFERROR(INDEX(Data_Cleaning!$B$2:$B$251,SMALL(IF(Data_Cleaning!$G$2:$G$251=$X5,ROW(Data_Cleaning!$G$2:$G$251)-ROW(Data_Cleaning!$G$2)+1),2)),"")} -> 45396 | Y9: {=IFERROR(INDEX(Data_Cleaning!$D$2:$D$251,SMALL(IF(Data_Cleaning!$G$2:$G$251=$X5,ROW(Data_Cleaning!$G$2:$G$251)-ROW(Data_Cleaning!$G$2)+1),2)),"")} -> Joseph Jackson | Z9: {=IFERROR(INDEX(Data_Cleaning!$F$2:$F$251,SMALL(IF(Data_Cleaning!$G$2:$G$251=$X5,ROW(Data_Cleaning!$G$2:$G$251)-ROW(Data_Cleaning!$G$2)+1),2)),"")} -> Monitor | AA9: {=IFERROR(INDEX(Data_Cleaning!$N$2:$N$251,SMALL(IF(Data_Cleaning!$G$2:$G$251=$X5,ROW(Data_Cleaning!$G$2:$G$251)-ROW(Data_Cleaning!$G$2)+1),2)),"")} -> 749.97
A10: CUST007 | B10: =INDEX(Data_Cleaning!$D$2:$D$251,MATCH(A10,Data_Cleaning!$C$2:$C$251,0)) -> David Martinez | C10: =INDEX(Data_Cleaning!$M$2:$M$251,MATCH(A10,Data_Cleaning!$C$2:$C$251,0)) -> 44981 | D10: =DATEDIF(C10,TODAY(),"y") -> 3 | E10: =SUMIFS(Data_Cleaning!$N$2:$N$251,Data_Cleaning!$C$2:$C$251,A10) -> 1809.84 | F10: =COUNTIFS(Data_Cleaning!$C$2:$C$251,A10) -> 6 | G10: =IFERROR(E10/F10,0) -> 301.64 | H10: =RANK(E10,$E$4:$E$53) -> 39 | I10: =IF(H10<=10,"High Value","Standard") -> Standard | J10: =IF(COUNTIFS(Data_Cleaning!$C$2:$C$251,A10,Data_Cleaning!$F$2:$F$251,"Laptop")>0,"Yes","No") -> No | K10: =IF(AND(COUNTIFS(Data_Cleaning!$C$2:$C$251,A10,Data_Cleaning!$L$2:$L$251,"Premium")>0,J10="Yes"),B10,"") | L10: =UPPER(LEFT(B10,3))&"-"&RIGHT(A10,3) -> DAV-007 | O10: P005 | P10: Blender | Q10: =SUMIFS(Data_Cleaning!$H$2:$H$251,Data_Cleaning!$E$2:$E$251,O10) -> 87 | R10: =COUNTIFS(Data_Cleaning!$E$2:$E$251,O10) -> 29 | S10: =SUMIFS(Data_Cleaning!$N$2:$N$251,Data_Cleaning!$E$2:$E$251,O10) -> 5219.13 | T10: =UPPER(LEFT(P10,1))&UPPER(LEFT(SUBSTITUTE(P10," ",""),3)) -> BBLE | W10: {=IFERROR(INDEX(Data_Cleaning!$A$2:$A$251,SMALL(IF(Data_Cleaning!$G$2:$G$251=$X5,ROW(Data_Cleaning!$G$2:$G$251)-ROW(Data_Cleaning!$G$2)+1),3)),"")} -> TRX0193 | X10: {=IFERROR(INDEX(Data_Cleaning!$B$2:$B$251,SMALL(IF(Data_Cleaning!$G$2:$G$251=$X5,ROW(Data_Cleaning!$G$2:$G$251)-ROW(Data_Cleaning!$G$2)+1),3)),"")} -> 45403 | Y10: {=IFERROR(INDEX(Data_Cleaning!$D$2:$D$251,SMALL(IF(Data_Cleaning!$G$2:$G$251=$X5,ROW(Data_Cleaning!$G$2:$G$251)-ROW(Data_Cleaning!$G$2)+1),3)),"")} -> Dorothy Nelson | Z10: {=IFERROR(INDEX(Data_Cleaning!$F$2:$F$251,SMALL(IF(Data_Cleaning!$G$2:$G$251=$X5,ROW(Data_Cleaning!$G$2:$G$251)-ROW(Data_Cleaning!$G$2)+1),3)),"")} -> Headphones | AA10: {=IFERROR(INDEX(Data_Cleaning!$N$2:$N$251,SMALL(IF(Data_Cleaning!$G$2:$G$251=$X5,ROW(Data_Cleaning!$G$2:$G$251)-ROW(Data_Cleaning!$G$2)+1),3)),"")} -> 749.95
A11: CUST008 | B11: =INDEX(Data_Cleaning!$D$2:$D$251,MATCH(A11,Data_Cleaning!$C$2:$C$251,0)) -> Jennifer Taylor | C11: =INDEX(Data_Cleaning!$M$2:$M$251,MATCH(A11,Data_Cleaning!$C$2:$C$251,0)) -> 44407 | D11: =DATEDIF(C11,TODAY(),"y") -> 5 | E11: =SUMIFS(Data_Cleaning!$N$2:$N$251,Data_Cleaning!$C$2:$C$251,A11) -> 4739.85 | F11: =COUNTIFS(Data_Cleaning!$C$2:$C$251,A11) -> 4 | G11: =IFERROR(E11/F11,0) -> 1184.9625 | H11: =RANK(E11,$E$4:$E$53) -> 24 | I11: =IF(H11<=10,"High Value","Standard") -> Standard | J11: =IF(COUNTIFS(Data_Cleaning!$C$2:$C$251,A11,Data_Cleaning!$F$2:$F$251,"Laptop")>0,"Yes","No") -> No | K11: =IF(AND(COUNTIFS(Data_Cleaning!$C$2:$C$251,A11,Data_Cleaning!$L$2:$L$251,"Premium")>0,J11="Yes"),B11,"") | L11: =UPPER(LEFT(B11,3))&"-"&RIGHT(A11,3) -> JEN-008 | O11: P006 | P11: Office Chair | Q11: =SUMIFS(Data_Cleaning!$H$2:$H$251,Data_Cleaning!$E$2:$E$251,O11) -> 52 | R11: =COUNTIFS(Data_Cleaning!$E$2:$E$251,O11) -> 15 | S11: =SUMIFS(Data_Cleaning!$N$2:$N$251,Data_Cleaning!$E$2:$E$251,O11) -> 10399.48 | T11: =UPPER(LEFT(P11,1))&UPPER(LEFT(SUBSTITUTE(P11," ",""),3)) -> OOFF | W11: {=IFERROR(INDEX(Data_Cleaning!$A$2:$A$251,SMALL(IF(Data_Cleaning!$G$2:$G$251=$X5,ROW(Data_Cleaning!$G$2:$G$251)-ROW(Data_Cleaning!$G$2)+1),4)),"")} -> TRX0135 | X11: {=IFERROR(INDEX(Data_Cleaning!$B$2:$B$251,SMALL(IF(Data_Cleaning!$G$2:$G$251=$X5,ROW(Data_Cleaning!$G$2:$G$251)-ROW(Data_Cleaning!$G$2)+1),4)),"")} -> 45405 | Y11: {=IFERROR(INDEX(Data_Cleaning!$D$2:$D$251,SMALL(IF(Data_Cleaning!$G$2:$G$251=$X5,ROW(Data_Cleaning!$G$2:$G$251)-ROW(Data_Cleaning!$G$2)+1),4)),"")} -> Robert Thomas | Z11: {=IFERROR(INDEX(Data_Cleaning!$F$2:$F$251,SMALL(IF(Data_Cleaning!$G$2:$G$251=$X5,ROW(Data_Cleaning!$G$2:$G$251)-ROW(Data_Cleaning!$G$2)+1),4)),"")} -> Laptop | AA11: {=IFERROR(INDEX(Data_Cleaning!$N$2:$N$251,SMALL(IF(Data_Cleaning!$G$2:$G$251=$X5,ROW(Data_Cleaning!$G$2:$G$251)-ROW(Data_Cleaning!$G$2)+1),4)),"")} -> 2699.97
A12: CUST009 | B12: =INDEX(Data_Cleaning!$D$2:$D$251,MATCH(A12,Data_Cleaning!$C$2:$C$251,0)) -> Robert Thomas | C12: =INDEX(Data_Cleaning!$M$2:$M$251,MATCH(A12,Data_Cleaning!$C$2:$C$251,0)) -> 45299 | D12: =DATEDIF(C12,TODAY(),"y") -> 2 | E12: =SUMIFS(Data_Cleaning!$N$2:$N$251,Data_Cleaning!$C$2:$C$251,A12) -> 3509.9 | F12: =COUNTIFS(Data_Cleaning!$C$2:$C$251,A12) -> 5 | G12: =IFERROR(E12/F12,0) -> 701.98 | H12: =RANK(E12,$E$4:$E$53) -> 32 | I12: =IF(H12<=10,"High Value","Standard") -> Standard | J12: =IF(COUNTIFS(Data_Cleaning!$C$2:$C$251,A12,Data_Cleaning!$F$2:$F$251,"Laptop")>0,"Yes","No") -> Yes | K12: =IF(AND(COUNTIFS(Data_Cleaning!$C$2:$C$251,A12,Data_Cleaning!$L$2:$L$251,"Premium")>0,J12="Yes"),B12,"") -> Robert Thomas | L12: =UPPER(LEFT(B12,3))&"-"&RIGHT(A12,3) -> ROB-009 | O12: P007 | P12: Desk | Q12: =SUMIFS(Data_Cleaning!$H$2:$H$251,Data_Cleaning!$E$2:$E$251,O12) -> 78 | R12: =COUNTIFS(Data_Cleaning!$E$2:$E$251,O12) -> 26 | S12: =SUMIFS(Data_Cleaning!$N$2:$N$251,Data_Cleaning!$E$2:$E$251,O12) -> 23399.22 | T12: =UPPER(LEFT(P12,1))&UPPER(LEFT(SUBSTITUTE(P12," ",""),3)) -> DDES | W12: {=IFERROR(INDEX(Data_Cleaning!$A$2:$A$251,SMALL(IF(Data_Cleaning!$G$2:$G$251=$X5,ROW(Data_Cleaning!$G$2:$G$251)-ROW(Data_Cleaning!$G$2)+1),5)),"")} -> TRX0191 | X12: {=IFERROR(INDEX(Data_Cleaning!$B$2:$B$251,SMALL(IF(Data_Cleaning!$G$2:$G$251=$X5,ROW(Data_Cleaning!$G$2:$G$251)-ROW(Data_Cleaning!$G$2)+1),5)),"")} -> 45409 | Y12: {=IFERROR(INDEX(Data_Cleaning!$D$2:$D$251,SMALL(IF(Data_Cleaning!$G$2:$G$251=$X5,ROW(Data_Cleaning!$G$2:$G$251)-ROW(Data_Cleaning!$G$2)+1),5)),"")} -> Michelle Rogers | Z12: {=IFERROR(INDEX(Data_Cleaning!$F$2:$F$251,SMALL(IF(Data_Cleaning!$G$2:$G$251=$X5,ROW(Data_Cleaning!$G$2:$G$251)-ROW(Data_Cleaning!$G$2)+1),5)),"")} -> Smartphone | AA12: {=IFERROR(INDEX(Data_Cleaning!$N$2:$N$251,SMALL(IF(Data_Cleaning!$G$2:$G$251=$X5,ROW(Data_Cleaning!$G$2:$G$251)-ROW(Data_Cleaning!$G$2)+1),5)),"")} -> 2099.97
A13: CUST010 | B13: =INDEX(Data_Cleaning!$D$2:$D$251,MATCH(A13,Data_Cleaning!$C$2:$C$251,0)) -> Maria Garcia | C13: =INDEX(Data_Cleaning!$M$2:$M$251,MATCH(A13,Data_Cleaning!$C$2:$C$251,0)) -> 44781 | D13: =DATEDIF(C13,TODAY(),"y") -> 4 | E13: =SUMIFS(Data_Cleaning!$N$2:$N$251,Data_Cleaning!$C$2:$C$251,A13) -> 1909.93 | F13: =COUNTIFS(Data_Cleaning!$C$2:$C$251,A13) -> 4 | G13: =IFERROR(E13/F13,0) -> 477.4825 | H13: =RANK(E13,$E$4:$E$53) -> 38 | I13: =IF(H13<=10,"High Value","Standard") -> Standard | J13: =IF(COUNTIFS(Data_Cleaning!$C$2:$C$251,A13,Data_Cleaning!$F$2:$F$251,"Laptop")>0,"Yes","No") -> No | K13: =IF(AND(COUNTIFS(Data_Cleaning!$C$2:$C$251,A13,Data_Cleaning!$L$2:$L$251,"Premium")>0,J13="Yes"),B13,"") | L13: =UPPER(LEFT(B13,3))&"-"&RIGHT(A13,3) -> MAR-010 | O13: P008 | P13: Bookshelf | Q13: =SUMIFS(Data_Cleaning!$H$2:$H$251,Data_Cleaning!$E$2:$E$251,O13) -> 102 | R13: =COUNTIFS(Data_Cleaning!$E$2:$E$251,O13) -> 35 | S13: =SUMIFS(Data_Cleaning!$N$2:$N$251,Data_Cleaning!$E$2:$E$251,O13) -> 15298.98 | T13: =UPPER(LEFT(P13,1))&UPPER(LEFT(SUBSTITUTE(P13," ",""),3)) -> BBOO | W13: {=IFERROR(INDEX(Data_Cleaning!$A$2:$A$251,SMALL(IF(Data_Cleaning!$G$2:$G$251=$X5,ROW(Data_Cleaning!$G$2:$G$251)-ROW(Data_Cleaning!$G$2)+1),6)),"")} -> TRX0230 | X13: {=IFERROR(INDEX(Data_Cleaning!$B$2:$B$251,SMALL(IF(Data_Cleaning!$G$2:$G$251=$X5,ROW(Data_Cleaning!$G$2:$G$251)-ROW(Data_Cleaning!$G$2)+1),6)),"")} -> 45409 | Y13: {=IFERROR(INDEX(Data_Cleaning!$D$2:$D$251,SMALL(IF(Data_Cleaning!$G$2:$G$251=$X5,ROW(Data_Cleaning!$G$2:$G$251)-ROW(Data_Cleaning!$G$2)+1),6)),"")} -> George Adams | Z13: {=IFERROR(INDEX(Data_Cleaning!$F$2:$F$251,SMALL(IF(Data_Cleaning!$G$2:$G$251=$X5,ROW(Data_Cleaning!$G$2:$G$251)-ROW(Data_Cleaning!$G$2)+1),6)),"")} -> Laptop | AA13: {=IFERROR(INDEX(Data_Cleaning!$N$2:$N$251,SMALL(IF(Data_Cleaning!$G$2:$G$251=$X5,ROW(Data_Cleaning!$G$2:$G$251)-ROW(Data_Cleaning!$G$2)+1),6)),"")} -> 899.99
A14: CUST011 | B14: =INDEX(Data_Cleaning!$D$2:$D$251,MATCH(A14,Data_Cleaning!$C$2:$C$251,0)) -> William White | C14: =INDEX(Data_Cleaning!$M$2:$M$251,MATCH(A14,Data_Cleaning!$C$2:$C$251,0)) -> 44482 | D14: =DATEDIF(C14,TODAY(),"y") -> 4 | E14: =SUMIFS(Data_Cleaning!$N$2:$N$251,Data_Cleaning!$C$2:$C$251,A14) -> 4749.91 | F14: =COUNTIFS(Data_Cleaning!$C$2:$C$251,A14) -> 3 | G14: =IFERROR(E14/F14,0) -> 1583.3033 | H14: =RANK(E14,$E$4:$E$53) -> 23 | I14: =IF(H14<=10,"High Value","Standard") -> Standard | J14: =IF(COUNTIFS(Data_Cleaning!$C$2:$C$251,A14,Data_Cleaning!$F$2:$F$251,"Laptop")>0,"Yes","No") -> Yes | K14: =IF(AND(COUNTIFS(Data_Cleaning!$C$2:$C$251,A14,Data_Cleaning!$L$2:$L$251,"Premium")>0,J14="Yes"),B14,"") -> William White | L14: =UPPER(LEFT(B14,3))&"-"&RIGHT(A14,3) -> WIL-011 | O14: P009 | P14: Monitor | Q14: =SUMIFS(Data_Cleaning!$H$2:$H$251,Data_Cleaning!$E$2:$E$251,O14) -> 88 | R14: =COUNTIFS(Data_Cleaning!$E$2:$E$251,O14) -> 26 | S14: =SUMIFS(Data_Cleaning!$N$2:$N$251,Data_Cleaning!$E$2:$E$251,O14) -> 21999.12 | T14: =UPPER(LEFT(P14,1))&UPPER(LEFT(SUBSTITUTE(P14," ",""),3)) -> MMON | W14: {=IFERROR(INDEX(Data_Cleaning!$A$2:$A$251,SMALL(IF(Data_Cleaning!$G$2:$G$251=$X5,ROW(Data_Cleaning!$G$2:$G$251)-ROW(Data_Cleaning!$G$2)+1),7)),"")} -> TRX0134 | X14: {=IFERROR(INDEX(Data_Cleaning!$B$2:$B$251,SMALL(IF(Data_Cleaning!$G$2:$G$251=$X5,ROW(Data_Cleaning!$G$2:$G$251)-ROW(Data_Cleaning!$G$2)+1),7)),"")} -> 45410 | Y14: {=IFERROR(INDEX(Data_Cleaning!$D$2:$D$251,SMALL(IF(Data_Cleaning!$G$2:$G$251=$X5,ROW(Data_Cleaning!$G$2:$G$251)-ROW(Data_Cleaning!$G$2)+1),7)),"")} -> Maria Garcia | Z14: {=IFERROR(INDEX(Data_Cleaning!$F$2:$F$251,SMALL(IF(Data_Cleaning!$G$2:$G$251=$X5,ROW(Data_Cleaning!$G$2:$G$251)-ROW(Data_Cleaning!$G$2)+1),7)),"")} -> Smartphone | AA14: {=IFERROR(INDEX(Data_Cleaning!$N$2:$N$251,SMALL(IF(Data_Cleaning!$G$2:$G$251=$X5,ROW(Data_Cleaning!$G$2:$G$251)-ROW(Data_Cleaning!$G$2)+1),7)),"")} -> 1399.98
A15: CUST012 | B15: =INDEX(Data_Cleaning!$D$2:$D$251,MATCH(A15,Data_Cleaning!$C$2:$C$251,0)) -> Patricia Moore | C15: =INDEX(Data_Cleaning!$M$2:$M$251,MATCH(A15,Data_Cleaning!$C$2:$C$251,0)) -> 44409 | D15: =DATEDIF(C15,TODAY(),"y") -> 5 | E15: =SUMIFS(Data_Cleaning!$N$2:$N$251,Data_Cleaning!$C$2:$C$251,A15) -> 9799.73 | F15: =COUNTIFS(Data_Cleaning!$C$2:$C$251,A15) -> 8 | G15: =IFERROR(E15/F15,0) -> 1224.9662 | H15: =RANK(E15,$E$4:$E$53) -> 4 | I15: =IF(H15<=10,"High Value","Standard") -> High Value | J15: =IF(COUNTIFS(Data_Cleaning!$C$2:$C$251,A15,Data_Cleaning!$F$2:$F$251,"Laptop")>0,"Yes","No") -> Yes | K15: =IF(AND(COUNTIFS(Data_Cleaning!$C$2:$C$251,A15,Data_Cleaning!$L$2:$L$251,"Premium")>0,J15="Yes"),B15,"") -> Patricia Moore | L15: =UPPER(LEFT(B15,3))&"-"&RIGHT(A15,3) -> PAT-012 | O15: P010 | P15: Keyboard | Q15: =SUMIFS(Data_Cleaning!$H$2:$H$251,Data_Cleaning!$E$2:$E$251,O15) -> 89 | R15: =COUNTIFS(Data_Cleaning!$E$2:$E$251,O15) -> 34 | S15: =SUMIFS(Data_Cleaning!$N$2:$N$251,Data_Cleaning!$E$2:$E$251,O15) -> 8009.11 | T15: =UPPER(LEFT(P15,1))&UPPER(LEFT(SUBSTITUTE(P15," ",""),3)) -> KKEY | W15: {=IFERROR(INDEX(Data_Cleaning!$A$2:$A$251,SMALL(IF(Data_Cleaning!$G$2:$G$251=$X5,ROW(Data_Cleaning!$G$2:$G$251)-ROW(Data_Cleaning!$G$2)+1),8)),"")} -> TRX0122 | X15: {=IFERROR(INDEX(Data_Cleaning!$B$2:$B$251,SMALL(IF(Data_Cleaning!$G$2:$G$251=$X5,ROW(Data_Cleaning!$G$2:$G$251)-ROW(Data_Cleaning!$G$2)+1),8)),"")} -> 45410 | Y15: {=IFERROR(INDEX(Data_Cleaning!$D$2:$D$251,SMALL(IF(Data_Cleaning!$G$2:$G$251=$X5,ROW(Data_Cleaning!$G$2:$G$251)-ROW(Data_Cleaning!$G$2)+1),8)),"")} -> Mark Carter | Z15: {=IFERROR(INDEX(Data_Cleaning!$F$2:$F$251,SMALL(IF(Data_Cleaning!$G$2:$G$251=$X5,ROW(Data_Cleaning!$G$2:$G$251)-ROW(Data_Cleaning!$G$2)+1),8)),"")} -> Laptop | AA15: {=IFERROR(INDEX(Data_Cleaning!$N$2:$N$251,SMALL(IF(Data_Cleaning!$G$2:$G$251=$X5,ROW(Data_Cleaning!$G$2:$G$251)-ROW(Data_Cleaning!$G$2)+1),8)),"")} -> 3599.96
A16: CUST013 | B16: =INDEX(Data_Cleaning!$D$2:$D$251,MATCH(A16,Data_Cleaning!$C$2:$C$251,0)) -> Joseph Jackson | C16: =INDEX(Data_Cleaning!$M$2:$M$251,MATCH(A16,Data_Cleaning!$C$2:$C$251,0)) -> 44575 | D16: =DATEDIF(C16,TODAY(),"y") -> 4 | E16: =SUMIFS(Data_Cleaning!$N$2:$N$251,Data_Cleaning!$C$2:$C$251,A16) -> 6949.84 | F16: =COUNTIFS(Data_Cleaning!$C$2:$C$251,A16) -> 5 | G16: =IFERROR(E16/F16,0) -> 1389.968 | H16: =RANK(E16,$E$4:$E$53) -> 10 | I16: =IF(H16<=10,"High Value","Standard") -> High Value | J16: =IF(COUNTIFS(Data_Cleaning!$C$2:$C$251,A16,Data_Cleaning!$F$2:$F$251,"Laptop")>0,"Yes","No") -> Yes | K16: =IF(AND(COUNTIFS(Data_Cleaning!$C$2:$C$251,A16,Data_Cleaning!$L$2:$L$251,"Premium")>0,J16="Yes"),B16,"") -> Joseph Jackson | L16: =UPPER(LEFT(B16,3))&"-"&RIGHT(A16,3) -> JOS-013 | W16: {=IFERROR(INDEX(Data_Cleaning!$A$2:$A$251,SMALL(IF(Data_Cleaning!$G$2:$G$251=$X5,ROW(Data_Cleaning!$G$2:$G$251)-ROW(Data_Cleaning!$G$2)+1),9)),"")} -> TRX0222 | X16: {=IFERROR(INDEX(Data_Cleaning!$B$2:$B$251,SMALL(IF(Data_Cleaning!$G$2:$G$251=$X5,ROW(Data_Cleaning!$G$2:$G$251)-ROW(Data_Cleaning!$G$2)+1),9)),"")} -> 45410 | Y16: {=IFERROR(INDEX(Data_Cleaning!$D$2:$D$251,SMALL(IF(Data_Cleaning!$G$2:$G$251=$X5,ROW(Data_Cleaning!$G$2:$G$251)-ROW(Data_Cleaning!$G$2)+1),9)),"")} -> Virginia Sanders | Z16: {=IFERROR(INDEX(Data_Cleaning!$F$2:$F$251,SMALL(IF(Data_Cleaning!$G$2:$G$251=$X5,ROW(Data_Cleaning!$G$2:$G$251)-ROW(Data_Cleaning!$G$2)+1),9)),"")} -> Monitor | AA16: {=IFERROR(INDEX(Data_Cleaning!$N$2:$N$251,SMALL(IF(Data_Cleaning!$G$2:$G$251=$X5,ROW(Data_Cleaning!$G$2:$G$251)-ROW(Data_Cleaning!$G$2)+1),9)),"")} -> 749.97
A17: CUST014 | B17: =INDEX(Data_Cleaning!$D$2:$D$251,MATCH(A17,Data_Cleaning!$C$2:$C$251,0)) -> Linda Martin | C17: =INDEX(Data_Cleaning!$M$2:$M$251,MATCH(A17,Data_Cleaning!$C$2:$C$251,0)) -> 45012 | D17: =DATEDIF(C17,TODAY(),"y") -> 3 | E17: =SUMIFS(Data_Cleaning!$N$2:$N$251,Data_Cleaning!$C$2:$C$251,A17) -> 1289.9 | F17: =COUNTIFS(Data_Cleaning!$C$2:$C$251,A17) -> 4 | G17: =IFERROR(E17/F17,0) -> 322.475 | H17: =RANK(E17,$E$4:$E$53) -> 43 | I17: =IF(H17<=10,"High Value","Standard") -> Standard | J17: =IF(COUNTIFS(Data_Cleaning!$C$2:$C$251,A17,Data_Cleaning!$F$2:$F$251,"Laptop")>0,"Yes","No") -> No | K17: =IF(AND(COUNTIFS(Data_Cleaning!$C$2:$C$251,A17,Data_Cleaning!$L$2:$L$251,"Premium")>0,J17="Yes"),B17,"") | L17: =UPPER(LEFT(B17,3))&"-"&RIGHT(A17,3) -> LIN-014 | O17: Most Frequently Purchased Product (by Units Sold): | P17: =INDEX(P6:P15,MATCH(MAX(Q6:Q15),Q6:Q15,0)) -> Bookshelf | W17: {=IFERROR(INDEX(Data_Cleaning!$A$2:$A$251,SMALL(IF(Data_Cleaning!$G$2:$G$251=$X5,ROW(Data_Cleaning!$G$2:$G$251)-ROW(Data_Cleaning!$G$2)+1),10)),"")} -> TRX0231 | X17: {=IFERROR(INDEX(Data_Cleaning!$B$2:$B$251,SMALL(IF(Data_Cleaning!$G$2:$G$251=$X5,ROW(Data_Cleaning!$G$2:$G$251)-ROW(Data_Cleaning!$G$2)+1),10)),"")} -> 45412 | Y17: {=IFERROR(INDEX(Data_Cleaning!$D$2:$D$251,SMALL(IF(Data_Cleaning!$G$2:$G$251=$X5,ROW(Data_Cleaning!$G$2:$G$251)-ROW(Data_Cleaning!$G$2)+1),10)),"")} -> Barbara Young | Z17: {=IFERROR(INDEX(Data_Cleaning!$F$2:$F$251,SMALL(IF(Data_Cleaning!$G$2:$G$251=$X5,ROW(Data_Cleaning!$G$2:$G$251)-ROW(Data_Cleaning!$G$2)+1),10)),"")} -> Smartphone | AA17: {=IFERROR(INDEX(Data_Cleaning!$N$2:$N$251,SMALL(IF(Data_Cleaning!$G$2:$G$251=$X5,ROW(Data_Cleaning!$G$2:$G$251)-ROW(Data_Cleaning!$G$2)+1),10)),"")} -> 3499.95
A18: CUST015 | B18: =INDEX(Data_Cleaning!$D$2:$D$251,MATCH(A18,Data_Cleaning!$C$2:$C$251,0)) -> Richard Lee | C18: =INDEX(Data_Cleaning!$M$2:$M$251,MATCH(A18,Data_Cleaning!$C$2:$C$251,0)) -> 44953 | D18: =DATEDIF(C18,TODAY(),"y") -> 3 | E18: =SUMIFS(Data_Cleaning!$N$2:$N$251,Data_Cleaning!$C$2:$C$251,A18) -> 739.93 | F18: =COUNTIFS(Data_Cleaning!$C$2:$C$251,A18) -> 3 | G18: =IFERROR(E18/F18,0) -> 246.64333 | H18: =RANK(E18,$E$4:$E$53) -> 46 | I18: =IF(H18<=10,"High Value","Standard") -> Standard | J18: =IF(COUNTIFS(Data_Cleaning!$C$2:$C$251,A18,Data_Cleaning!$F$2:$F$251,"Laptop")>0,"Yes","No") -> No | K18: =IF(AND(COUNTIFS(Data_Cleaning!$C$2:$C$251,A18,Data_Cleaning!$L$2:$L$251,"Premium")>0,J18="Yes"),B18,"") | L18: =UPPER(LEFT(B18,3))&"-"&RIGHT(A18,3) -> RIC-015 | O18: Units Sold for that Product: | P18: =MAX(Q6:Q15) -> 102 | W18: {=IFERROR(INDEX(Data_Cleaning!$A$2:$A$251,SMALL(IF(Data_Cleaning!$G$2:$G$251=$X5,ROW(Data_Cleaning!$G$2:$G$251)-ROW(Data_Cleaning!$G$2)+1),11)),"")} -> TRX0239 | X18: {=IFERROR(INDEX(Data_Cleaning!$B$2:$B$251,SMALL(IF(Data_Cleaning!$G$2:$G$251=$X5,ROW(Data_Cleaning!$G$2:$G$251)-ROW(Data_Cleaning!$G$2)+1),11)),"")} -> 45413 | Y18: {=IFERROR(INDEX(Data_Cleaning!$D$2:$D$251,SMALL(IF(Data_Cleaning!$G$2:$G$251=$X5,ROW(Data_Cleaning!$G$2:$G$251)-ROW(Data_Cleaning!$G$2)+1),11)),"")} -> Patricia Moore | Z18: {=IFERROR(INDEX(Data_Cleaning!$F$2:$F$251,SMALL(IF(Data_Cleaning!$G$2:$G$251=$X5,ROW(Data_Cleaning!$G$2:$G$251)-ROW(Data_Cleaning!$G$2)+1),11)),"")} -> Smartphone | AA18: {=IFERROR(INDEX(Data_Cleaning!$N$2:$N$251,SMALL(IF(Data_Cleaning!$G$2:$G$251=$X5,ROW(Data_Cleaning!$G$2:$G$251)-ROW(Data_Cleaning!$G$2)+1),11)),"")} -> 2799.96
A19: CUST016 | B19: =INDEX(Data_Cleaning!$D$2:$D$251,MATCH(A19,Data_Cleaning!$C$2:$C$251,0)) -> Elizabeth Hall | C19: =INDEX(Data_Cleaning!$M$2:$M$251,MATCH(A19,Data_Cleaning!$C$2:$C$251,0)) -> 44542 | D19: =DATEDIF(C19,TODAY(),"y") -> 4 | E19: =SUMIFS(Data_Cleaning!$N$2:$N$251,Data_Cleaning!$C$2:$C$251,A19) -> 3649.86 | F19: =COUNTIFS(Data_Cleaning!$C$2:$C$251,A19) -> 4 | G19: =IFERROR(E19/F19,0) -> 912.465 | H19: =RANK(E19,$E$4:$E$53) -> 31 | I19: =IF(H19<=10,"High Value","Standard") -> Standard | J19: =IF(COUNTIFS(Data_Cleaning!$C$2:$C$251,A19,Data_Cleaning!$F$2:$F$251,"Laptop")>0,"Yes","No") -> No | K19: =IF(AND(COUNTIFS(Data_Cleaning!$C$2:$C$251,A19,Data_Cleaning!$L$2:$L$251,"Premium")>0,J19="Yes"),B19,"") | L19: =UPPER(LEFT(B19,3))&"-"&RIGHT(A19,3) -> ELI-016 | W19: {=IFERROR(INDEX(Data_Cleaning!$A$2:$A$251,SMALL(IF(Data_Cleaning!$G$2:$G$251=$X5,ROW(Data_Cleaning!$G$2:$G$251)-ROW(Data_Cleaning!$G$2)+1),12)),"")} -> TRX0204 | X19: {=IFERROR(INDEX(Data_Cleaning!$B$2:$B$251,SMALL(IF(Data_Cleaning!$G$2:$G$251=$X5,ROW(Data_Cleaning!$G$2:$G$251)-ROW(Data_Cleaning!$G$2)+1),12)),"")} -> 45415 | Y19: {=IFERROR(INDEX(Data_Cleaning!$D$2:$D$251,SMALL(IF(Data_Cleaning!$G$2:$G$251=$X5,ROW(Data_Cleaning!$G$2:$G$251)-ROW(Data_Cleaning!$G$2)+1),12)),"")} -> Cynthia Price | Z19: {=IFERROR(INDEX(Data_Cleaning!$F$2:$F$251,SMALL(IF(Data_Cleaning!$G$2:$G$251=$X5,ROW(Data_Cleaning!$G$2:$G$251)-ROW(Data_Cleaning!$G$2)+1),12)),"")} -> Monitor | AA19: {=IFERROR(INDEX(Data_Cleaning!$N$2:$N$251,SMALL(IF(Data_Cleaning!$G$2:$G$251=$X5,ROW(Data_Cleaning!$G$2:$G$251)-ROW(Data_Cleaning!$G$2)+1),12)),"")} -> 999.96
A20: CUST017 | B20: =INDEX(Data_Cleaning!$D$2:$D$251,MATCH(A20,Data_Cleaning!$C$2:$C$251,0)) -> Charles Allen | C20: =INDEX(Data_Cleaning!$M$2:$M$251,MATCH(A20,Data_Cleaning!$C$2:$C$251,0)) -> 45007 | D20: =DATEDIF(C20,TODAY(),"y") -> 3 | E20: =SUMIFS(Data_Cleaning!$N$2:$N$251,Data_Cleaning!$C$2:$C$251,A20) -> 5089.73 | F20: =COUNTIFS(Data_Cleaning!$C$2:$C$251,A20) -> 9 | G20: =IFERROR(E20/F20,0) -> 565.52556 | H20: =RANK(E20,$E$4:$E$53) -> 20 | I20: =IF(H20<=10,"High Value","Standard") -> Standard | J20: =IF(COUNTIFS(Data_Cleaning!$C$2:$C$251,A20,Data_Cleaning!$F$2:$F$251,"Laptop")>0,"Yes","No") -> No | K20: =IF(AND(COUNTIFS(Data_Cleaning!$C$2:$C$251,A20,Data_Cleaning!$L$2:$L$251,"Premium")>0,J20="Yes"),B20,"") | L20: =UPPER(LEFT(B20,3))&"-"&RIGHT(A20,3) -> CHA-017 | W20: {=IFERROR(INDEX(Data_Cleaning!$A$2:$A$251,SMALL(IF(Data_Cleaning!$G$2:$G$251=$X5,ROW(Data_Cleaning!$G$2:$G$251)-ROW(Data_Cleaning!$G$2)+1),13)),"")} -> TRX0071 | X20: {=IFERROR(INDEX(Data_Cleaning!$B$2:$B$251,SMALL(IF(Data_Cleaning!$G$2:$G$251=$X5,ROW(Data_Cleaning!$G$2:$G$251)-ROW(Data_Cleaning!$G$2)+1),13)),"")} -> 45422 | Y20: {=IFERROR(INDEX(Data_Cleaning!$D$2:$D$251,SMALL(IF(Data_Cleaning!$G$2:$G$251=$X5,ROW(Data_Cleaning!$G$2:$G$251)-ROW(Data_Cleaning!$G$2)+1),13)),"")} -> Nancy Collins | Z20: {=IFERROR(INDEX(Data_Cleaning!$F$2:$F$251,SMALL(IF(Data_Cleaning!$G$2:$G$251=$X5,ROW(Data_Cleaning!$G$2:$G$251)-ROW(Data_Cleaning!$G$2)+1),13)),"")} -> Monitor | AA20: {=IFERROR(INDEX(Data_Cleaning!$N$2:$N$251,SMALL(IF(Data_Cleaning!$G$2:$G$251=$X5,ROW(Data_Cleaning!$G$2:$G$251)-ROW(Data_Cleaning!$G$2)+1),13)),"")} -> 1249.95
A21: CUST018 | B21: =INDEX(Data_Cleaning!$D$2:$D$251,MATCH(A21,Data_Cleaning!$C$2:$C$251,0)) -> Barbara Young | C21: =INDEX(Data_Cleaning!$M$2:$M$251,MATCH(A21,Data_Cleaning!$C$2:$C$251,0)) -> 45167 | D21: =DATEDIF(C21,TODAY(),"y") -> 3 | E21: =SUMIFS(Data_Cleaning!$N$2:$N$251,Data_Cleaning!$C$2:$C$251,A21) -> 10649.8 | F21: =COUNTIFS(Data_Cleaning!$C$2:$C$251,A21) -> 5 | G21: =IFERROR(E21/F21,0) -> 2129.96 | H21: =RANK(E21,$E$4:$E$53) -> 3 | I21: =IF(H21<=10,"High Value","Standard") -> High Value | J21: =IF(COUNTIFS(Data_Cleaning!$C$2:$C$251,A21,Data_Cleaning!$F$2:$F$251,"Laptop")>0,"Yes","No") -> Yes | K21: =IF(AND(COUNTIFS(Data_Cleaning!$C$2:$C$251,A21,Data_Cleaning!$L$2:$L$251,"Premium")>0,J21="Yes"),B21,"") -> Barbara Young | L21: =UPPER(LEFT(B21,3))&"-"&RIGHT(A21,3) -> BAR-018 | O21: 4. MONTHLY REVENUE TREND WITH GROWTH % (Icon Set Conditional Formatting) | W21: {=IFERROR(INDEX(Data_Cleaning!$A$2:$A$251,SMALL(IF(Data_Cleaning!$G$2:$G$251=$X5,ROW(Data_Cleaning!$G$2:$G$251)-ROW(Data_Cleaning!$G$2)+1),14)),"")} -> TRX0004 | X21: {=IFERROR(INDEX(Data_Cleaning!$B$2:$B$251,SMALL(IF(Data_Cleaning!$G$2:$G$251=$X5,ROW(Data_Cleaning!$G$2:$G$251)-ROW(Data_Cleaning!$G$2)+1),14)),"")} -> 45424 | Y21: {=IFERROR(INDEX(Data_Cleaning!$D$2:$D$251,SMALL(IF(Data_Cleaning!$G$2:$G$251=$X5,ROW(Data_Cleaning!$G$2:$G$251)-ROW(Data_Cleaning!$G$2)+1),14)),"")} -> Patricia Moore | Z21: {=IFERROR(INDEX(Data_Cleaning!$F$2:$F$251,SMALL(IF(Data_Cleaning!$G$2:$G$251=$X5,ROW(Data_Cleaning!$G$2:$G$251)-ROW(Data_Cleaning!$G$2)+1),14)),"")} -> Keyboard | AA21: {=IFERROR(INDEX(Data_Cleaning!$N$2:$N$251,SMALL(IF(Data_Cleaning!$G$2:$G$251=$X5,ROW(Data_Cleaning!$G$2:$G$251)-ROW(Data_Cleaning!$G$2)+1),14)),"")} -> 449.95
A22: CUST019 | B22: =INDEX(Data_Cleaning!$D$2:$D$251,MATCH(A22,Data_Cleaning!$C$2:$C$251,0)) -> Daniel King | C22: =INDEX(Data_Cleaning!$M$2:$M$251,MATCH(A22,Data_Cleaning!$C$2:$C$251,0)) -> 44917 | D22: =DATEDIF(C22,TODAY(),"y") -> 3 | E22: =SUMIFS(Data_Cleaning!$N$2:$N$251,Data_Cleaning!$C$2:$C$251,A22) -> 7309.8 | F22: =COUNTIFS(Data_Cleaning!$C$2:$C$251,A22) -> 7 | G22: =IFERROR(E22/F22,0) -> 1044.2571 | H22: =RANK(E22,$E$4:$E$53) -> 8 | I22: =IF(H22<=10,"High Value","Standard") -> High Value | J22: =IF(COUNTIFS(Data_Cleaning!$C$2:$C$251,A22,Data_Cleaning!$F$2:$F$251,"Laptop")>0,"Yes","No") -> Yes | K22: =IF(AND(COUNTIFS(Data_Cleaning!$C$2:$C$251,A22,Data_Cleaning!$L$2:$L$251,"Premium")>0,J22="Yes"),B22,"") -> Daniel King | L22: =UPPER(LEFT(B22,3))&"-"&RIGHT(A22,3) -> DAN-019 | W22: {=IFERROR(INDEX(Data_Cleaning!$A$2:$A$251,SMALL(IF(Data_Cleaning!$G$2:$G$251=$X5,ROW(Data_Cleaning!$G$2:$G$251)-ROW(Data_Cleaning!$G$2)+1),15)),"")} -> TRX0041 | X22: {=IFERROR(INDEX(Data_Cleaning!$B$2:$B$251,SMALL(IF(Data_Cleaning!$G$2:$G$251=$X5,ROW(Data_Cleaning!$G$2:$G$251)-ROW(Data_Cleaning!$G$2)+1),15)),"")} -> 45432 | Y22: {=IFERROR(INDEX(Data_Cleaning!$D$2:$D$251,SMALL(IF(Data_Cleaning!$G$2:$G$251=$X5,ROW(Data_Cleaning!$G$2:$G$251)-ROW(Data_Cleaning!$G$2)+1),15)),"")} -> Kevin Scott | Z22: {=IFERROR(INDEX(Data_Cleaning!$F$2:$F$251,SMALL(IF(Data_Cleaning!$G$2:$G$251=$X5,ROW(Data_Cleaning!$G$2:$G$251)-ROW(Data_Cleaning!$G$2)+1),15)),"")} -> Laptop | AA22: {=IFERROR(INDEX(Data_Cleaning!$N$2:$N$251,SMALL(IF(Data_Cleaning!$G$2:$G$251=$X5,ROW(Data_Cleaning!$G$2:$G$251)-ROW(Data_Cleaning!$G$2)+1),15)),"")} -> 899.99
A23: CUST020 | B23: =INDEX(Data_Cleaning!$D$2:$D$251,MATCH(A23,Data_Cleaning!$C$2:$C$251,0)) -> Margaret Wright | C23: =INDEX(Data_Cleaning!$M$2:$M$251,MATCH(A23,Data_Cleaning!$C$2:$C$251,0)) -> 44421 | D23: =DATEDIF(C23,TODAY(),"y") -> 5 | E23: =SUMIFS(Data_Cleaning!$N$2:$N$251,Data_Cleaning!$C$2:$C$251,A23) -> 2099.88 | F23: =COUNTIFS(Data_Cleaning!$C$2:$C$251,A23) -> 4 | G23: =IFERROR(E23/F23,0) -> 524.97 | H23: =RANK(E23,$E$4:$E$53) -> 35 | I23: =IF(H23<=10,"High Value","Standard") -> Standard | J23: =IF(COUNTIFS(Data_Cleaning!$C$2:$C$251,A23,Data_Cleaning!$F$2:$F$251,"Laptop")>0,"Yes","No") -> No | K23: =IF(AND(COUNTIFS(Data_Cleaning!$C$2:$C$251,A23,Data_Cleaning!$L$2:$L$251,"Premium")>0,J23="Yes"),B23,"") | L23: =UPPER(LEFT(B23,3))&"-"&RIGHT(A23,3) -> MAR-020 | O23: Month | P23: Month_Label | Q23: Monthly_Revenue | R23: Growth_% | W23: {=IFERROR(INDEX(Data_Cleaning!$A$2:$A$251,SMALL(IF(Data_Cleaning!$G$2:$G$251=$X5,ROW(Data_Cleaning!$G$2:$G$251)-ROW(Data_Cleaning!$G$2)+1),16)),"")} -> TRX0015 | X23: {=IFERROR(INDEX(Data_Cleaning!$B$2:$B$251,SMALL(IF(Data_Cleaning!$G$2:$G$251=$X5,ROW(Data_Cleaning!$G$2:$G$251)-ROW(Data_Cleaning!$G$2)+1),16)),"")} -> 45440 | Y23: {=IFERROR(INDEX(Data_Cleaning!$D$2:$D$251,SMALL(IF(Data_Cleaning!$G$2:$G$251=$X5,ROW(Data_Cleaning!$G$2:$G$251)-ROW(Data_Cleaning!$G$2)+1),16)),"")} -> Jennifer Taylor | Z23: {=IFERROR(INDEX(Data_Cleaning!$F$2:$F$251,SMALL(IF(Data_Cleaning!$G$2:$G$251=$X5,ROW(Data_Cleaning!$G$2:$G$251)-ROW(Data_Cleaning!$G$2)+1),16)),"")} -> Smartphone | AA23: {=IFERROR(INDEX(Data_Cleaning!$N$2:$N$251,SMALL(IF(Data_Cleaning!$G$2:$G$251=$X5,ROW(Data_Cleaning!$G$2:$G$251)-ROW(Data_Cleaning!$G$2)+1),16)),"")} -> 3499.95
A24: CUST021 | B24: =INDEX(Data_Cleaning!$D$2:$D$251,MATCH(A24,Data_Cleaning!$C$2:$C$251,0)) -> Kevin Scott | C24: =INDEX(Data_Cleaning!$M$2:$M$251,MATCH(A24,Data_Cleaning!$C$2:$C$251,0)) -> 45262 | D24: =DATEDIF(C24,TODAY(),"y") -> 2 | E24: =SUMIFS(Data_Cleaning!$N$2:$N$251,Data_Cleaning!$C$2:$C$251,A24) -> 3259.87 | F24: =COUNTIFS(Data_Cleaning!$C$2:$C$251,A24) -> 6 | G24: =IFERROR(E24/F24,0) -> 543.31167 | H24: =RANK(E24,$E$4:$E$53) -> 33 | I24: =IF(H24<=10,"High Value","Standard") -> Standard | J24: =IF(COUNTIFS(Data_Cleaning!$C$2:$C$251,A24,Data_Cleaning!$F$2:$F$251,"Laptop")>0,"Yes","No") -> Yes | K24: =IF(AND(COUNTIFS(Data_Cleaning!$C$2:$C$251,A24,Data_Cleaning!$L$2:$L$251,"Premium")>0,J24="Yes"),B24,"") -> Kevin Scott | L24: =UPPER(LEFT(B24,3))&"-"&RIGHT(A24,3) -> KEV-021 | O24: =DATE(2024,4,1) -> 45383 | P24: =TEXT(O24,"mmm-yy") -> Apr-24 | Q24: =SUMIFS(Data_Cleaning!$N$2:$N$251,Data_Cleaning!$B$2:$B$251,">="&O24,Data_Cleaning!$B$2:$B$251,"<"&EDATE(O24,1)) -> 20919.33 | W24: {=IFERROR(INDEX(Data_Cleaning!$A$2:$A$251,SMALL(IF(Data_Cleaning!$G$2:$G$251=$X5,ROW(Data_Cleaning!$G$2:$G$251)-ROW(Data_Cleaning!$G$2)+1),17)),"")} -> TRX0202 | X24: {=IFERROR(INDEX(Data_Cleaning!$B$2:$B$251,SMALL(IF(Data_Cleaning!$G$2:$G$251=$X5,ROW(Data_Cleaning!$G$2:$G$251)-ROW(Data_Cleaning!$G$2)+1),17)),"")} -> 45441 | Y24: {=IFERROR(INDEX(Data_Cleaning!$D$2:$D$251,SMALL(IF(Data_Cleaning!$G$2:$G$251=$X5,ROW(Data_Cleaning!$G$2:$G$251)-ROW(Data_Cleaning!$G$2)+1),17)),"")} -> Harry Morgan | Z24: {=IFERROR(INDEX(Data_Cleaning!$F$2:$F$251,SMALL(IF(Data_Cleaning!$G$2:$G$251=$X5,ROW(Data_Cleaning!$G$2:$G$251)-ROW(Data_Cleaning!$G$2)+1),17)),"")} -> Keyboard | AA24: {=IFERROR(INDEX(Data_Cleaning!$N$2:$N$251,SMALL(IF(Data_Cleaning!$G$2:$G$251=$X5,ROW(Data_Cleaning!$G$2:$G$251)-ROW(Data_Cleaning!$G$2)+1),17)),"")} -> 269.97
A25: CUST022 | B25: =INDEX(Data_Cleaning!$D$2:$D$251,MATCH(A25,Data_Cleaning!$C$2:$C$251,0)) -> Susan Green | C25: =INDEX(Data_Cleaning!$M$2:$M$251,MATCH(A25,Data_Cleaning!$C$2:$C$251,0)) -> 45103 | D25: =DATEDIF(C25,TODAY(),"y") -> 3 | E25: =SUMIFS(Data_Cleaning!$N$2:$N$251,Data_Cleaning!$C$2:$C$251,A25) -> 1979.89 | F25: =COUNTIFS(Data_Cleaning!$C$2:$C$251,A25) -> 4 | G25: =IFERROR(E25/F25,0) -> 494.9725 | H25: =RANK(E25,$E$4:$E$53) -> 37 | I25: =IF(H25<=10,"High Value","Standard") -> Standard | J25: =IF(COUNTIFS(Data_Cleaning!$C$2:$C$251,A25,Data_Cleaning!$F$2:$F$251,"Laptop")>0,"Yes","No") -> No | K25: =IF(AND(COUNTIFS(Data_Cleaning!$C$2:$C$251,A25,Data_Cleaning!$L$2:$L$251,"Premium")>0,J25="Yes"),B25,"") | L25: =UPPER(LEFT(B25,3))&"-"&RIGHT(A25,3) -> SUS-022 | O25: =DATE(2024,5,1) -> 45413 | P25: =TEXT(O25,"mmm-yy") -> May-24 | Q25: =SUMIFS(Data_Cleaning!$N$2:$N$251,Data_Cleaning!$B$2:$B$251,">="&O25,Data_Cleaning!$B$2:$B$251,"<"&EDATE(O25,1)) -> 17039.35 | R25: =IFERROR((Q25-Q24)/Q24,"") -> -0.18547344 | W25: {=IFERROR(INDEX(Data_Cleaning!$A$2:$A$251,SMALL(IF(Data_Cleaning!$G$2:$G$251=$X5,ROW(Data_Cleaning!$G$2:$G$251)-ROW(Data_Cleaning!$G$2)+1),18)),"")} -> TRX0117 | X25: {=IFERROR(INDEX(Data_Cleaning!$B$2:$B$251,SMALL(IF(Data_Cleaning!$G$2:$G$251=$X5,ROW(Data_Cleaning!$G$2:$G$251)-ROW(Data_Cleaning!$G$2)+1),18)),"")} -> 45444 | Y25: {=IFERROR(INDEX(Data_Cleaning!$D$2:$D$251,SMALL(IF(Data_Cleaning!$G$2:$G$251=$X5,ROW(Data_Cleaning!$G$2:$G$251)-ROW(Data_Cleaning!$G$2)+1),18)),"")} -> Charles Allen | Z25: {=IFERROR(INDEX(Data_Cleaning!$F$2:$F$251,SMALL(IF(Data_Cleaning!$G$2:$G$251=$X5,ROW(Data_Cleaning!$G$2:$G$251)-ROW(Data_Cleaning!$G$2)+1),18)),"")} -> Keyboard | AA25: {=IFERROR(INDEX(Data_Cleaning!$N$2:$N$251,SMALL(IF(Data_Cleaning!$G$2:$G$251=$X5,ROW(Data_Cleaning!$G$2:$G$251)-ROW(Data_Cleaning!$G$2)+1),18)),"")} -> 89.99
A26: CUST023 | B26: =INDEX(Data_Cleaning!$D$2:$D$251,MATCH(A26,Data_Cleaning!$C$2:$C$251,0)) -> Paul Baker | C26: =INDEX(Data_Cleaning!$M$2:$M$251,MATCH(A26,Data_Cleaning!$C$2:$C$251,0)) -> 44425 | D26: =DATEDIF(C26,TODAY(),"y") -> 5 | E26: =SUMIFS(Data_Cleaning!$N$2:$N$251,Data_Cleaning!$C$2:$C$251,A26) -> 8309.74 | F26: =COUNTIFS(Data_Cleaning!$C$2:$C$251,A26) -> 8 | G26: =IFERROR(E26/F26,0) -> 1038.7175 | H26: =RANK(E26,$E$4:$E$53) -> 5 | I26: =IF(H26<=10,"High Value","Standard") -> High Value | J26: =IF(COUNTIFS(Data_Cleaning!$C$2:$C$251,A26,Data_Cleaning!$F$2:$F$251,"Laptop")>0,"Yes","No") -> Yes | K26: =IF(AND(COUNTIFS(Data_Cleaning!$C$2:$C$251,A26,Data_Cleaning!$L$2:$L$251,"Premium")>0,J26="Yes"),B26,"") -> Paul Baker | L26: =UPPER(LEFT(B26,3))&"-"&RIGHT(A26,3) -> PAU-023 | O26: =DATE(2024,6,1) -> 45444 | P26: =TEXT(O26,"mmm-yy") -> Jun-24 | Q26: =SUMIFS(Data_Cleaning!$N$2:$N$251,Data_Cleaning!$B$2:$B$251,">="&O26,Data_Cleaning!$B$2:$B$251,"<"&EDATE(O26,1)) -> 19299.45 | R26: =IFERROR((Q26-Q25)/Q25,"") -> 0.13264004 | W26: {=IFERROR(INDEX(Data_Cleaning!$A$2:$A$251,SMALL(IF(Data_Cleaning!$G$2:$G$251=$X5,ROW(Data_Cleaning!$G$2:$G$251)-ROW(Data_Cleaning!$G$2)+1),19)),"")} -> TRX0208 | X26: {=IFERROR(INDEX(Data_Cleaning!$B$2:$B$251,SMALL(IF(Data_Cleaning!$G$2:$G$251=$X5,ROW(Data_Cleaning!$G$2:$G$251)-ROW(Data_Cleaning!$G$2)+1),19)),"")} -> 45446 | Y26: {=IFERROR(INDEX(Data_Cleaning!$D$2:$D$251,SMALL(IF(Data_Cleaning!$G$2:$G$251=$X5,ROW(Data_Cleaning!$G$2:$G$251)-ROW(Data_Cleaning!$G$2)+1),19)),"")} -> Sarah Davis | Z26: {=IFERROR(INDEX(Data_Cleaning!$F$2:$F$251,SMALL(IF(Data_Cleaning!$G$2:$G$251=$X5,ROW(Data_Cleaning!$G$2:$G$251)-ROW(Data_Cleaning!$G$2)+1),19)),"")} -> Keyboard | AA26: {=IFERROR(INDEX(Data_Cleaning!$N$2:$N$251,SMALL(IF(Data_Cleaning!$G$2:$G$251=$X5,ROW(Data_Cleaning!$G$2:$G$251)-ROW(Data_Cleaning!$G$2)+1),19)),"")} -> 449.95
A27: CUST024 | B27: =INDEX(Data_Cleaning!$D$2:$D$251,MATCH(A27,Data_Cleaning!$C$2:$C$251,0)) -> Dorothy Nelson | C27: =INDEX(Data_Cleaning!$M$2:$M$251,MATCH(A27,Data_Cleaning!$C$2:$C$251,0)) -> 44746 | D27: =DATEDIF(C27,TODAY(),"y") -> 4 | E27: =SUMIFS(Data_Cleaning!$N$2:$N$251,Data_Cleaning!$C$2:$C$251,A27) -> 8269.79 | F27: =COUNTIFS(Data_Cleaning!$C$2:$C$251,A27) -> 6 | G27: =IFERROR(E27/F27,0) -> 1378.2983 | H27: =RANK(E27,$E$4:$E$53) -> 6 | I27: =IF(H27<=10,"High Value","Standard") -> High Value | J27: =IF(COUNTIFS(Data_Cleaning!$C$2:$C$251,A27,Data_Cleaning!$F$2:$F$251,"Laptop")>0,"Yes","No") -> Yes | K27: =IF(AND(COUNTIFS(Data_Cleaning!$C$2:$C$251,A27,Data_Cleaning!$L$2:$L$251,"Premium")>0,J27="Yes"),B27,"") -> Dorothy Nelson | L27: =UPPER(LEFT(B27,3))&"-"&RIGHT(A27,3) -> DOR-024 | O27: =DATE(2024,7,1) -> 45474 | P27: =TEXT(O27,"mmm-yy") -> Jul-24 | Q27: =SUMIFS(Data_Cleaning!$N$2:$N$251,Data_Cleaning!$B$2:$B$251,">="&O27,Data_Cleaning!$B$2:$B$251,"<"&EDATE(O27,1)) -> 18479.4 | R27: =IFERROR((Q27-Q26)/Q26,"") -> -0.042490848 | W27: {=IFERROR(INDEX(Data_Cleaning!$A$2:$A$251,SMALL(IF(Data_Cleaning!$G$2:$G$251=$X5,ROW(Data_Cleaning!$G$2:$G$251)-ROW(Data_Cleaning!$G$2)+1),20)),"")} -> TRX0234 | X27: {=IFERROR(INDEX(Data_Cleaning!$B$2:$B$251,SMALL(IF(Data_Cleaning!$G$2:$G$251=$X5,ROW(Data_Cleaning!$G$2:$G$251)-ROW(Data_Cleaning!$G$2)+1),20)),"")} -> 45449 | Y27: {=IFERROR(INDEX(Data_Cleaning!$D$2:$D$251,SMALL(IF(Data_Cleaning!$G$2:$G$251=$X5,ROW(Data_Cleaning!$G$2:$G$251)-ROW(Data_Cleaning!$G$2)+1),20)),"")} -> Joseph Jackson | Z27: {=IFERROR(INDEX(Data_Cleaning!$F$2:$F$251,SMALL(IF(Data_Cleaning!$G$2:$G$251=$X5,ROW(Data_Cleaning!$G$2:$G$251)-ROW(Data_Cleaning!$G$2)+1),20)),"")} -> Monitor | AA27: {=IFERROR(INDEX(Data_Cleaning!$N$2:$N$251,SMALL(IF(Data_Cleaning!$G$2:$G$251=$X5,ROW(Data_Cleaning!$G$2:$G$251)-ROW(Data_Cleaning!$G$2)+1),20)),"")} -> 1249.95
A28: CUST025 | B28: =INDEX(Data_Cleaning!$D$2:$D$251,MATCH(A28,Data_Cleaning!$C$2:$C$251,0)) -> Mark Carter | C28: =INDEX(Data_Cleaning!$M$2:$M$251,MATCH(A28,Data_Cleaning!$C$2:$C$251,0)) -> 45374 | D28: =DATEDIF(C28,TODAY(),"y") -> 2 | E28: =SUMIFS(Data_Cleaning!$N$2:$N$251,Data_Cleaning!$C$2:$C$251,A28) -> 15659.65 | F28: =COUNTIFS(Data_Cleaning!$C$2:$C$251,A28) -> 12 | G28: =IFERROR(E28/F28,0) -> 1304.9708 | H28: =RANK(E28,$E$4:$E$53) -> 1 | I28: =IF(H28<=10,"High Value","Standard") -> High Value | J28: =IF(COUNTIFS(Data_Cleaning!$C$2:$C$251,A28,Data_Cleaning!$F$2:$F$251,"Laptop")>0,"Yes","No") -> Yes | K28: =IF(AND(COUNTIFS(Data_Cleaning!$C$2:$C$251,A28,Data_Cleaning!$L$2:$L$251,"Premium")>0,J28="Yes"),B28,"") -> Mark Carter | L28: =UPPER(LEFT(B28,3))&"-"&RIGHT(A28,3) -> MAR-025 | O28: =DATE(2024,8,1) -> 45505 | P28: =TEXT(O28,"mmm-yy") -> Aug-24 | Q28: =SUMIFS(Data_Cleaning!$N$2:$N$251,Data_Cleaning!$B$2:$B$251,">="&O28,Data_Cleaning!$B$2:$B$251,"<"&EDATE(O28,1)) -> 15759.43 | R28: =IFERROR((Q28-Q27)/Q27,"") -> -0.1471893 | W28: {=IFERROR(INDEX(Data_Cleaning!$A$2:$A$251,SMALL(IF(Data_Cleaning!$G$2:$G$251=$X5,ROW(Data_Cleaning!$G$2:$G$251)-ROW(Data_Cleaning!$G$2)+1),21)),"")} -> TRX0121 | X28: {=IFERROR(INDEX(Data_Cleaning!$B$2:$B$251,SMALL(IF(Data_Cleaning!$G$2:$G$251=$X5,ROW(Data_Cleaning!$G$2:$G$251)-ROW(Data_Cleaning!$G$2)+1),21)),"")} -> 45449 | Y28: {=IFERROR(INDEX(Data_Cleaning!$D$2:$D$251,SMALL(IF(Data_Cleaning!$G$2:$G$251=$X5,ROW(Data_Cleaning!$G$2:$G$251)-ROW(Data_Cleaning!$G$2)+1),21)),"")} -> Betty Campbell | Z28: {=IFERROR(INDEX(Data_Cleaning!$F$2:$F$251,SMALL(IF(Data_Cleaning!$G$2:$G$251=$X5,ROW(Data_Cleaning!$G$2:$G$251)-ROW(Data_Cleaning!$G$2)+1),21)),"")} -> Keyboard | AA28: {=IFERROR(INDEX(Data_Cleaning!$N$2:$N$251,SMALL(IF(Data_Cleaning!$G$2:$G$251=$X5,ROW(Data_Cleaning!$G$2:$G$251)-ROW(Data_Cleaning!$G$2)+1),21)),"")} -> 89.99
A29: CUST026 | B29: =INDEX(Data_Cleaning!$D$2:$D$251,MATCH(A29,Data_Cleaning!$C$2:$C$251,0)) -> Karen Hill | C29: =INDEX(Data_Cleaning!$M$2:$M$251,MATCH(A29,Data_Cleaning!$C$2:$C$251,0)) -> 45207 | D29: =DATEDIF(C29,TODAY(),"y") -> 2 | E29: =SUMIFS(Data_Cleaning!$N$2:$N$251,Data_Cleaning!$C$2:$C$251,A29) -> 8009.77 | F29: =COUNTIFS(Data_Cleaning!$C$2:$C$251,A29) -> 8 | G29: =IFERROR(E29/F29,0) -> 1001.2212 | H29: =RANK(E29,$E$4:$E$53) -> 7 | I29: =IF(H29<=10,"High Value","Standard") -> High Value | J29: =IF(COUNTIFS(Data_Cleaning!$C$2:$C$251,A29,Data_Cleaning!$F$2:$F$251,"Laptop")>0,"Yes","No") -> No | K29: =IF(AND(COUNTIFS(Data_Cleaning!$C$2:$C$251,A29,Data_Cleaning!$L$2:$L$251,"Premium")>0,J29="Yes"),B29,"") | L29: =UPPER(LEFT(B29,3))&"-"&RIGHT(A29,3) -> KAR-026 | O29: =DATE(2024,9,1) -> 45536 | P29: =TEXT(O29,"mmm-yy") -> Sep-24 | Q29: =SUMIFS(Data_Cleaning!$N$2:$N$251,Data_Cleaning!$B$2:$B$251,">="&O29,Data_Cleaning!$B$2:$B$251,"<"&EDATE(O29,1)) -> 12989.51 | R29: =IFERROR((Q29-Q28)/Q28,"") -> -0.1757627 | W29: {=IFERROR(INDEX(Data_Cleaning!$A$2:$A$251,SMALL(IF(Data_Cleaning!$G$2:$G$251=$X5,ROW(Data_Cleaning!$G$2:$G$251)-ROW(Data_Cleaning!$G$2)+1),22)),"")} -> TRX0088 | X29: {=IFERROR(INDEX(Data_Cleaning!$B$2:$B$251,SMALL(IF(Data_Cleaning!$G$2:$G$251=$X5,ROW(Data_Cleaning!$G$2:$G$251)-ROW(Data_Cleaning!$G$2)+1),22)),"")} -> 45456 | Y29: {=IFERROR(INDEX(Data_Cleaning!$D$2:$D$251,SMALL(IF(Data_Cleaning!$G$2:$G$251=$X5,ROW(Data_Cleaning!$G$2:$G$251)-ROW(Data_Cleaning!$G$2)+1),22)),"")} -> Lisa Anderson | Z29: {=IFERROR(INDEX(Data_Cleaning!$F$2:$F$251,SMALL(IF(Data_Cleaning!$G$2:$G$251=$X5,ROW(Data_Cleaning!$G$2:$G$251)-ROW(Data_Cleaning!$G$2)+1),22)),"")} -> Keyboard | AA29: {=IFERROR(INDEX(Data_Cleaning!$N$2:$N$251,SMALL(IF(Data_Cleaning!$G$2:$G$251=$X5,ROW(Data_Cleaning!$G$2:$G$251)-ROW(Data_Cleaning!$G$2)+1),22)),"")} -> 449.95
A30: CUST027 | B30: =INDEX(Data_Cleaning!$D$2:$D$251,MATCH(A30,Data_Cleaning!$C$2:$C$251,0)) -> George Adams | C30: =INDEX(Data_Cleaning!$M$2:$M$251,MATCH(A30,Data_Cleaning!$C$2:$C$251,0)) -> 44920 | D30: =DATEDIF(C30,TODAY(),"y") -> 3 | E30: =SUMIFS(Data_Cleaning!$N$2:$N$251,Data_Cleaning!$C$2:$C$251,A30) -> 3779.93 | F30: =COUNTIFS(Data_Cleaning!$C$2:$C$251,A30) -> 3 | G30: =IFERROR(E30/F30,0) -> 1259.9767 | H30: =RANK(E30,$E$4:$E$53) -> 28 | I30: =IF(H30<=10,"High Value","Standard") -> Standard | J30: =IF(COUNTIFS(Data_Cleaning!$C$2:$C$251,A30,Data_Cleaning!$F$2:$F$251,"Laptop")>0,"Yes","No") -> Yes | K30: =IF(AND(COUNTIFS(Data_Cleaning!$C$2:$C$251,A30,Data_Cleaning!$L$2:$L$251,"Premium")>0,J30="Yes"),B30,"") | L30: =UPPER(LEFT(B30,3))&"-"&RIGHT(A30,3) -> GEO-027 | O30: =DATE(2024,10,1) -> 45566 | P30: =TEXT(O30,"mmm-yy") -> Oct-24 | Q30: =SUMIFS(Data_Cleaning!$N$2:$N$251,Data_Cleaning!$B$2:$B$251,">="&O30,Data_Cleaning!$B$2:$B$251,"<"&EDATE(O30,1)) -> 20609.52 | R30: =IFERROR((Q30-Q29)/Q29,"") -> 0.58662798 | W30: {=IFERROR(INDEX(Data_Cleaning!$A$2:$A$251,SMALL(IF(Data_Cleaning!$G$2:$G$251=$X5,ROW(Data_Cleaning!$G$2:$G$251)-ROW(Data_Cleaning!$G$2)+1),23)),"")} -> TRX0115 | X30: {=IFERROR(INDEX(Data_Cleaning!$B$2:$B$251,SMALL(IF(Data_Cleaning!$G$2:$G$251=$X5,ROW(Data_Cleaning!$G$2:$G$251)-ROW(Data_Cleaning!$G$2)+1),23)),"")} -> 45459 | Y30: {=IFERROR(INDEX(Data_Cleaning!$D$2:$D$251,SMALL(IF(Data_Cleaning!$G$2:$G$251=$X5,ROW(Data_Cleaning!$G$2:$G$251)-ROW(Data_Cleaning!$G$2)+1),23)),"")} -> Patricia Moore | Z30: {=IFERROR(INDEX(Data_Cleaning!$F$2:$F$251,SMALL(IF(Data_Cleaning!$G$2:$G$251=$X5,ROW(Data_Cleaning!$G$2:$G$251)-ROW(Data_Cleaning!$G$2)+1),23)),"")} -> Keyboard | AA30: {=IFERROR(INDEX(Data_Cleaning!$N$2:$N$251,SMALL(IF(Data_Cleaning!$G$2:$G$251=$X5,ROW(Data_Cleaning!$G$2:$G$251)-ROW(Data_Cleaning!$G$2)+1),23)),"")} -> 179.98
A31: CUST028 | B31: =INDEX(Data_Cleaning!$D$2:$D$251,MATCH(A31,Data_Cleaning!$C$2:$C$251,0)) -> Betty Campbell | C31: =INDEX(Data_Cleaning!$M$2:$M$251,MATCH(A31,Data_Cleaning!$C$2:$C$251,0)) -> 44582 | D31: =DATEDIF(C31,TODAY(),"y") -> 4 | E31: =SUMIFS(Data_Cleaning!$N$2:$N$251,Data_Cleaning!$C$2:$C$251,A31) -> 5649.84 | F31: =COUNTIFS(Data_Cleaning!$C$2:$C$251,A31) -> 5 | G31: =IFERROR(E31/F31,0) -> 1129.968 | H31: =RANK(E31,$E$4:$E$53) -> 16 | I31: =IF(H31<=10,"High Value","Standard") -> Standard | J31: =IF(COUNTIFS(Data_Cleaning!$C$2:$C$251,A31,Data_Cleaning!$F$2:$F$251,"Laptop")>0,"Yes","No") -> No | K31: =IF(AND(COUNTIFS(Data_Cleaning!$C$2:$C$251,A31,Data_Cleaning!$L$2:$L$251,"Premium")>0,J31="Yes"),B31,"") | L31: =UPPER(LEFT(B31,3))&"-"&RIGHT(A31,3) -> BET-028 | O31: =DATE(2024,11,1) -> 45597 | P31: =TEXT(O31,"mmm-yy") -> Nov-24 | Q31: =SUMIFS(Data_Cleaning!$N$2:$N$251,Data_Cleaning!$B$2:$B$251,">="&O31,Data_Cleaning!$B$2:$B$251,"<"&EDATE(O31,1)) -> 12309.44 | R31: =IFERROR((Q31-Q30)/Q30,"") -> -0.40273039 | W31: {=IFERROR(INDEX(Data_Cleaning!$A$2:$A$251,SMALL(IF(Data_Cleaning!$G$2:$G$251=$X5,ROW(Data_Cleaning!$G$2:$G$251)-ROW(Data_Cleaning!$G$2)+1),24)),"")} -> TRX0154 | X31: {=IFERROR(INDEX(Data_Cleaning!$B$2:$B$251,SMALL(IF(Data_Cleaning!$G$2:$G$251=$X5,ROW(Data_Cleaning!$G$2:$G$251)-ROW(Data_Cleaning!$G$2)+1),24)),"")} -> 45459 | Y31: {=IFERROR(INDEX(Data_Cleaning!$D$2:$D$251,SMALL(IF(Data_Cleaning!$G$2:$G$251=$X5,ROW(Data_Cleaning!$G$2:$G$251)-ROW(Data_Cleaning!$G$2)+1),24)),"")} -> Paul Baker | Z31: {=IFERROR(INDEX(Data_Cleaning!$F$2:$F$251,SMALL(IF(Data_Cleaning!$G$2:$G$251=$X5,ROW(Data_Cleaning!$G$2:$G$251)-ROW(Data_Cleaning!$G$2)+1),24)),"")} -> Laptop | AA31: {=IFERROR(INDEX(Data_Cleaning!$N$2:$N$251,SMALL(IF(Data_Cleaning!$G$2:$G$251=$X5,ROW(Data_Cleaning!$G$2:$G$251)-ROW(Data_Cleaning!$G$2)+1),24)),"")} -> 4499.95
A32: CUST029 | B32: =INDEX(Data_Cleaning!$D$2:$D$251,MATCH(A32,Data_Cleaning!$C$2:$C$251,0)) -> Edward Mitchell | C32: =INDEX(Data_Cleaning!$M$2:$M$251,MATCH(A32,Data_Cleaning!$C$2:$C$251,0)) -> 44867 | D32: =DATEDIF(C32,TODAY(),"y") -> 3 | E32: =SUMIFS(Data_Cleaning!$N$2:$N$251,Data_Cleaning!$C$2:$C$251,A32) -> 11919.77 | F32: =COUNTIFS(Data_Cleaning!$C$2:$C$251,A32) -> 6 | G32: =IFERROR(E32/F32,0) -> 1986.6283 | H32: =RANK(E32,$E$4:$E$53) -> 2 | I32: =IF(H32<=10,"High Value","Standard") -> High Value | J32: =IF(COUNTIFS(Data_Cleaning!$C$2:$C$251,A32,Data_Cleaning!$F$2:$F$251,"Laptop")>0,"Yes","No") -> Yes | K32: =IF(AND(COUNTIFS(Data_Cleaning!$C$2:$C$251,A32,Data_Cleaning!$L$2:$L$251,"Premium")>0,J32="Yes"),B32,"") -> Edward Mitchell | L32: =UPPER(LEFT(B32,3))&"-"&RIGHT(A32,3) -> EDW-029 | O32: =DATE(2024,12,1) -> 45627 | P32: =TEXT(O32,"mmm-yy") -> Dec-24 | Q32: =SUMIFS(Data_Cleaning!$N$2:$N$251,Data_Cleaning!$B$2:$B$251,">="&O32,Data_Cleaning!$B$2:$B$251,"<"&EDATE(O32,1)) -> 23039.3 | R32: =IFERROR((Q32-Q31)/Q31,"") -> 0.87167735 | W32: {=IFERROR(INDEX(Data_Cleaning!$A$2:$A$251,SMALL(IF(Data_Cleaning!$G$2:$G$251=$X5,ROW(Data_Cleaning!$G$2:$G$251)-ROW(Data_Cleaning!$G$2)+1),25)),"")} -> TRX0044 | X32: {=IFERROR(INDEX(Data_Cleaning!$B$2:$B$251,SMALL(IF(Data_Cleaning!$G$2:$G$251=$X5,ROW(Data_Cleaning!$G$2:$G$251)-ROW(Data_Cleaning!$G$2)+1),25)),"")} -> 45459 | Y32: {=IFERROR(INDEX(Data_Cleaning!$D$2:$D$251,SMALL(IF(Data_Cleaning!$G$2:$G$251=$X5,ROW(Data_Cleaning!$G$2:$G$251)-ROW(Data_Cleaning!$G$2)+1),25)),"")} -> Edward Mitchell | Z32: {=IFERROR(INDEX(Data_Cleaning!$F$2:$F$251,SMALL(IF(Data_Cleaning!$G$2:$G$251=$X5,ROW(Data_Cleaning!$G$2:$G$251)-ROW(Data_Cleaning!$G$2)+1),25)),"")} -> Laptop | AA32: {=IFERROR(INDEX(Data_Cleaning!$N$2:$N$251,SMALL(IF(Data_Cleaning!$G$2:$G$251=$X5,ROW(Data_Cleaning!$G$2:$G$251)-ROW(Data_Cleaning!$G$2)+1),25)),"")} -> 4499.95
A33: CUST030 | B33: =INDEX(Data_Cleaning!$D$2:$D$251,MATCH(A33,Data_Cleaning!$C$2:$C$251,0)) -> Helen Roberts | C33: =INDEX(Data_Cleaning!$M$2:$M$251,MATCH(A33,Data_Cleaning!$C$2:$C$251,0)) -> 45214 | D33: =DATEDIF(C33,TODAY(),"y") -> 2 | E33: =SUMIFS(Data_Cleaning!$N$2:$N$251,Data_Cleaning!$C$2:$C$251,A33) -> 6459.79 | F33: =COUNTIFS(Data_Cleaning!$C$2:$C$251,A33) -> 7 | G33: =IFERROR(E33/F33,0) -> 922.82714 | H33: =RANK(E33,$E$4:$E$53) -> 11 | I33: =IF(H33<=10,"High Value","Standard") -> Standard | J33: =IF(COUNTIFS(Data_Cleaning!$C$2:$C$251,A33,Data_Cleaning!$F$2:$F$251,"Laptop")>0,"Yes","No") -> Yes | K33: =IF(AND(COUNTIFS(Data_Cleaning!$C$2:$C$251,A33,Data_Cleaning!$L$2:$L$251,"Premium")>0,J33="Yes"),B33,"") | L33: =UPPER(LEFT(B33,3))&"-"&RIGHT(A33,3) -> HEL-030 | O33: =DATE(2025,1,1) -> 45658 | P33: =TEXT(O33,"mmm-yy") -> Jan-25 | Q33: =SUMIFS(Data_Cleaning!$N$2:$N$251,Data_Cleaning!$B$2:$B$251,">="&O33,Data_Cleaning!$B$2:$B$251,"<"&EDATE(O33,1)) -> 25799.15 | R33: =IFERROR((Q33-Q32)/Q32,"") -> 0.1197888 | W33: {=IFERROR(INDEX(Data_Cleaning!$A$2:$A$251,SMALL(IF(Data_Cleaning!$G$2:$G$251=$X5,ROW(Data_Cleaning!$G$2:$G$251)-ROW(Data_Cleaning!$G$2)+1),26)),"")} -> TRX0025 | X33: {=IFERROR(INDEX(Data_Cleaning!$B$2:$B$251,SMALL(IF(Data_Cleaning!$G$2:$G$251=$X5,ROW(Data_Cleaning!$G$2:$G$251)-ROW(Data_Cleaning!$G$2)+1),26)),"")} -> 45468 | Y33: {=IFERROR(INDEX(Data_Cleaning!$D$2:$D$251,SMALL(IF(Data_Cleaning!$G$2:$G$251=$X5,ROW(Data_Cleaning!$G$2:$G$251)-ROW(Data_Cleaning!$G$2)+1),26)),"")} -> Raymond Ross | Z33: {=IFERROR(INDEX(Data_Cleaning!$F$2:$F$251,SMALL(IF(Data_Cleaning!$G$2:$G$251=$X5,ROW(Data_Cleaning!$G$2:$G$251)-ROW(Data_Cleaning!$G$2)+1),26)),"")} -> Keyboard | AA33: {=IFERROR(INDEX(Data_Cleaning!$N$2:$N$251,SMALL(IF(Data_Cleaning!$G$2:$G$251=$X5,ROW(Data_Cleaning!$G$2:$G$251)-ROW(Data_Cleaning!$G$2)+1),26)),"")} -> 359.96
A34: CUST031 | B34: =INDEX(Data_Cleaning!$D$2:$D$251,MATCH(A34,Data_Cleaning!$C$2:$C$251,0)) -> Steven Turner | C34: =INDEX(Data_Cleaning!$M$2:$M$251,MATCH(A34,Data_Cleaning!$C$2:$C$251,0)) -> 45292 | D34: =DATEDIF(C34,TODAY(),"y") -> 2 | E34: =SUMIFS(Data_Cleaning!$N$2:$N$251,Data_Cleaning!$C$2:$C$251,A34) -> 2649.83 | F34: =COUNTIFS(Data_Cleaning!$C$2:$C$251,A34) -> 6 | G34: =IFERROR(E34/F34,0) -> 441.63833 | H34: =RANK(E34,$E$4:$E$53) -> 34 | I34: =IF(H34<=10,"High Value","Standard") -> Standard | J34: =IF(COUNTIFS(Data_Cleaning!$C$2:$C$251,A34,Data_Cleaning!$F$2:$F$251,"Laptop")>0,"Yes","No") -> No | K34: =IF(AND(COUNTIFS(Data_Cleaning!$C$2:$C$251,A34,Data_Cleaning!$L$2:$L$251,"Premium")>0,J34="Yes"),B34,"") | L34: =UPPER(LEFT(B34,3))&"-"&RIGHT(A34,3) -> STE-031 | O34: =DATE(2025,2,1) -> 45689 | P34: =TEXT(O34,"mmm-yy") -> Feb-25 | Q34: =SUMIFS(Data_Cleaning!$N$2:$N$251,Data_Cleaning!$B$2:$B$251,">="&O34,Data_Cleaning!$B$2:$B$251,"<"&EDATE(O34,1)) -> 16069.38 | R34: =IFERROR((Q34-Q33)/Q33,"") -> -0.37713529 | W34: {=IFERROR(INDEX(Data_Cleaning!$A$2:$A$251,SMALL(IF(Data_Cleaning!$G$2:$G$251=$X5,ROW(Data_Cleaning!$G$2:$G$251)-ROW(Data_Cleaning!$G$2)+1),27)),"")} -> TRX0007 | X34: {=IFERROR(INDEX(Data_Cleaning!$B$2:$B$251,SMALL(IF(Data_Cleaning!$G$2:$G$251=$X5,ROW(Data_Cleaning!$G$2:$G$251)-ROW(Data_Cleaning!$G$2)+1),27)),"")} -> 45469 | Y34: {=IFERROR(INDEX(Data_Cleaning!$D$2:$D$251,SMALL(IF(Data_Cleaning!$G$2:$G$251=$X5,ROW(Data_Cleaning!$G$2:$G$251)-ROW(Data_Cleaning!$G$2)+1),27)),"")} -> Robert Thomas | Z34: {=IFERROR(INDEX(Data_Cleaning!$F$2:$F$251,SMALL(IF(Data_Cleaning!$G$2:$G$251=$X5,ROW(Data_Cleaning!$G$2:$G$251)-ROW(Data_Cleaning!$G$2)+1),27)),"")} -> Keyboard | AA34: {=IFERROR(INDEX(Data_Cleaning!$N$2:$N$251,SMALL(IF(Data_Cleaning!$G$2:$G$251=$X5,ROW(Data_Cleaning!$G$2:$G$251)-ROW(Data_Cleaning!$G$2)+1),27)),"")} -> 179.98
A35: CUST032 | B35: =INDEX(Data_Cleaning!$D$2:$D$251,MATCH(A35,Data_Cleaning!$C$2:$C$251,0)) -> Sandra Phillips | C35: =INDEX(Data_Cleaning!$M$2:$M$251,MATCH(A35,Data_Cleaning!$C$2:$C$251,0)) -> 44421 | D35: =DATEDIF(C35,TODAY(),"y") -> 5 | E35: =SUMIFS(Data_Cleaning!$N$2:$N$251,Data_Cleaning!$C$2:$C$251,A35) -> 6349.83 | F35: =COUNTIFS(Data_Cleaning!$C$2:$C$251,A35) -> 5 | G35: =IFERROR(E35/F35,0) -> 1269.966 | H35: =RANK(E35,$E$4:$E$53) -> 13 | I35: =IF(H35<=10,"High Value","Standard") -> Standard | J35: =IF(COUNTIFS(Data_Cleaning!$C$2:$C$251,A35,Data_Cleaning!$F$2:$F$251,"Laptop")>0,"Yes","No") -> Yes | K35: =IF(AND(COUNTIFS(Data_Cleaning!$C$2:$C$251,A35,Data_Cleaning!$L$2:$L$251,"Premium")>0,J35="Yes"),B35,"") -> Sandra Phillips | L35: =UPPER(LEFT(B35,3))&"-"&RIGHT(A35,3) -> SAN-032 | O35: =DATE(2025,3,1) -> 45717 | P35: =TEXT(O35,"mmm-yy") -> Mar-25 | Q35: =SUMIFS(Data_Cleaning!$N$2:$N$251,Data_Cleaning!$B$2:$B$251,">="&O35,Data_Cleaning!$B$2:$B$251,"<"&EDATE(O35,1)) -> 19899.38 | R35: =IFERROR((Q35-Q34)/Q34,"") -> 0.23834149 | W35: {=IFERROR(INDEX(Data_Cleaning!$A$2:$A$251,SMALL(IF(Data_Cleaning!$G$2:$G$251=$X5,ROW(Data_Cleaning!$G$2:$G$251)-ROW(Data_Cleaning!$G$2)+1),28)),"")} -> TRX0184 | X35: {=IFERROR(INDEX(Data_Cleaning!$B$2:$B$251,SMALL(IF(Data_Cleaning!$G$2:$G$251=$X5,ROW(Data_Cleaning!$G$2:$G$251)-ROW(Data_Cleaning!$G$2)+1),28)),"")} -> 45471 | Y35: {=IFERROR(INDEX(Data_Cleaning!$D$2:$D$251,SMALL(IF(Data_Cleaning!$G$2:$G$251=$X5,ROW(Data_Cleaning!$G$2:$G$251)-ROW(Data_Cleaning!$G$2)+1),28)),"")} -> Kathleen Bennett | Z35: {=IFERROR(INDEX(Data_Cleaning!$F$2:$F$251,SMALL(IF(Data_Cleaning!$G$2:$G$251=$X5,ROW(Data_Cleaning!$G$2:$G$251)-ROW(Data_Cleaning!$G$2)+1),28)),"")} -> Smartphone | AA35: {=IFERROR(INDEX(Data_Cleaning!$N$2:$N$251,SMALL(IF(Data_Cleaning!$G$2:$G$251=$X5,ROW(Data_Cleaning!$G$2:$G$251)-ROW(Data_Cleaning!$G$2)+1),28)),"")} -> 2099.97
A36: CUST033 | B36: =INDEX(Data_Cleaning!$D$2:$D$251,MATCH(A36,Data_Cleaning!$C$2:$C$251,0)) -> Frank Torres | C36: =INDEX(Data_Cleaning!$M$2:$M$251,MATCH(A36,Data_Cleaning!$C$2:$C$251,0)) -> 44891 | D36: =DATEDIF(C36,TODAY(),"y") -> 3 | E36: =SUMIFS(Data_Cleaning!$N$2:$N$251,Data_Cleaning!$C$2:$C$251,A36) -> 1479.91 | F36: =COUNTIFS(Data_Cleaning!$C$2:$C$251,A36) -> 5 | G36: =IFERROR(E36/F36,0) -> 295.982 | H36: =RANK(E36,$E$4:$E$53) -> 42 | I36: =IF(H36<=10,"High Value","Standard") -> Standard | J36: =IF(COUNTIFS(Data_Cleaning!$C$2:$C$251,A36,Data_Cleaning!$F$2:$F$251,"Laptop")>0,"Yes","No") -> No | K36: =IF(AND(COUNTIFS(Data_Cleaning!$C$2:$C$251,A36,Data_Cleaning!$L$2:$L$251,"Premium")>0,J36="Yes"),B36,"") | L36: =UPPER(LEFT(B36,3))&"-"&RIGHT(A36,3) -> FRA-033 | O36: =DATE(2025,4,1) -> 45748 | P36: =TEXT(O36,"mmm-yy") -> Apr-25 | Q36: =SUMIFS(Data_Cleaning!$N$2:$N$251,Data_Cleaning!$B$2:$B$251,">="&O36,Data_Cleaning!$B$2:$B$251,"<"&EDATE(O36,1)) -> 6979.83 | R36: =IFERROR((Q36-Q35)/Q35,"") -> -0.64924385 | W36: {=IFERROR(INDEX(Data_Cleaning!$A$2:$A$251,SMALL(IF(Data_Cleaning!$G$2:$G$251=$X5,ROW(Data_Cleaning!$G$2:$G$251)-ROW(Data_Cleaning!$G$2)+1),29)),"")} -> TRX0104 | X36: {=IFERROR(INDEX(Data_Cleaning!$B$2:$B$251,SMALL(IF(Data_Cleaning!$G$2:$G$251=$X5,ROW(Data_Cleaning!$G$2:$G$251)-ROW(Data_Cleaning!$G$2)+1),29)),"")} -> 45471 | Y36: {=IFERROR(INDEX(Data_Cleaning!$D$2:$D$251,SMALL(IF(Data_Cleaning!$G$2:$G$251=$X5,ROW(Data_Cleaning!$G$2:$G$251)-ROW(Data_Cleaning!$G$2)+1),29)),"")} -> Patricia Moore | Z36: {=IFERROR(INDEX(Data_Cleaning!$F$2:$F$251,SMALL(IF(Data_Cleaning!$G$2:$G$251=$X5,ROW(Data_Cleaning!$G$2:$G$251)-ROW(Data_Cleaning!$G$2)+1),29)),"")} -> Laptop | AA36: {=IFERROR(INDEX(Data_Cleaning!$N$2:$N$251,SMALL(IF(Data_Cleaning!$G$2:$G$251=$X5,ROW(Data_Cleaning!$G$2:$G$251)-ROW(Data_Cleaning!$G$2)+1),29)),"")} -> 3599.96
A37: CUST034 | B37: =INDEX(Data_Cleaning!$D$2:$D$251,MATCH(A37,Data_Cleaning!$C$2:$C$251,0)) -> Carol Evans | C37: =INDEX(Data_Cleaning!$M$2:$M$251,MATCH(A37,Data_Cleaning!$C$2:$C$251,0)) -> 45212 | D37: =DATEDIF(C37,TODAY(),"y") -> 2 | E37: =SUMIFS(Data_Cleaning!$N$2:$N$251,Data_Cleaning!$C$2:$C$251,A37) -> 1149.93 | F37: =COUNTIFS(Data_Cleaning!$C$2:$C$251,A37) -> 3 | G37: =IFERROR(E37/F37,0) -> 383.31 | H37: =RANK(E37,$E$4:$E$53) -> 45 | I37: =IF(H37<=10,"High Value","Standard") -> Standard | J37: =IF(COUNTIFS(Data_Cleaning!$C$2:$C$251,A37,Data_Cleaning!$F$2:$F$251,"Laptop")>0,"Yes","No") -> No | K37: =IF(AND(COUNTIFS(Data_Cleaning!$C$2:$C$251,A37,Data_Cleaning!$L$2:$L$251,"Premium")>0,J37="Yes"),B37,"") | L37: =UPPER(LEFT(B37,3))&"-"&RIGHT(A37,3) -> CAR-034 | W37: {=IFERROR(INDEX(Data_Cleaning!$A$2:$A$251,SMALL(IF(Data_Cleaning!$G$2:$G$251=$X5,ROW(Data_Cleaning!$G$2:$G$251)-ROW(Data_Cleaning!$G$2)+1),30)),"")} -> TRX0096 | X37: {=IFERROR(INDEX(Data_Cleaning!$B$2:$B$251,SMALL(IF(Data_Cleaning!$G$2:$G$251=$X5,ROW(Data_Cleaning!$G$2:$G$251)-ROW(Data_Cleaning!$G$2)+1),30)),"")} -> 45474 | Y37: {=IFERROR(INDEX(Data_Cleaning!$D$2:$D$251,SMALL(IF(Data_Cleaning!$G$2:$G$251=$X5,ROW(Data_Cleaning!$G$2:$G$251)-ROW(Data_Cleaning!$G$2)+1),30)),"")} -> Emma Wilson | Z37: {=IFERROR(INDEX(Data_Cleaning!$F$2:$F$251,SMALL(IF(Data_Cleaning!$G$2:$G$251=$X5,ROW(Data_Cleaning!$G$2:$G$251)-ROW(Data_Cleaning!$G$2)+1),30)),"")} -> Keyboard | AA37: {=IFERROR(INDEX(Data_Cleaning!$N$2:$N$251,SMALL(IF(Data_Cleaning!$G$2:$G$251=$X5,ROW(Data_Cleaning!$G$2:$G$251)-ROW(Data_Cleaning!$G$2)+1),30)),"")} -> 179.98
A38: CUST035 | B38: =INDEX(Data_Cleaning!$D$2:$D$251,MATCH(A38,Data_Cleaning!$C$2:$C$251,0)) -> Harry Morgan | C38: =INDEX(Data_Cleaning!$M$2:$M$251,MATCH(A38,Data_Cleaning!$C$2:$C$251,0)) -> 45120 | D38: =DATEDIF(C38,TODAY(),"y") -> 3 | E38: =SUMIFS(Data_Cleaning!$N$2:$N$251,Data_Cleaning!$C$2:$C$251,A38) -> 5519.89 | F38: =COUNTIFS(Data_Cleaning!$C$2:$C$251,A38) -> 4 | G38: =IFERROR(E38/F38,0) -> 1379.9725 | H38: =RANK(E38,$E$4:$E$53) -> 18 | I38: =IF(H38<=10,"High Value","Standard") -> Standard | J38: =IF(COUNTIFS(Data_Cleaning!$C$2:$C$251,A38,Data_Cleaning!$F$2:$F$251,"Laptop")>0,"Yes","No") -> Yes | K38: =IF(AND(COUNTIFS(Data_Cleaning!$C$2:$C$251,A38,Data_Cleaning!$L$2:$L$251,"Premium")>0,J38="Yes"),B38,"") -> Harry Morgan | L38: =UPPER(LEFT(B38,3))&"-"&RIGHT(A38,3) -> HAR-035 | W38: {=IFERROR(INDEX(Data_Cleaning!$A$2:$A$251,SMALL(IF(Data_Cleaning!$G$2:$G$251=$X5,ROW(Data_Cleaning!$G$2:$G$251)-ROW(Data_Cleaning!$G$2)+1),31)),"")} -> TRX0192 | X38: {=IFERROR(INDEX(Data_Cleaning!$B$2:$B$251,SMALL(IF(Data_Cleaning!$G$2:$G$251=$X5,ROW(Data_Cleaning!$G$2:$G$251)-ROW(Data_Cleaning!$G$2)+1),31)),"")} -> 45475 | Y38: {=IFERROR(INDEX(Data_Cleaning!$D$2:$D$251,SMALL(IF(Data_Cleaning!$G$2:$G$251=$X5,ROW(Data_Cleaning!$G$2:$G$251)-ROW(Data_Cleaning!$G$2)+1),31)),"")} -> Charles Allen | Z38: {=IFERROR(INDEX(Data_Cleaning!$F$2:$F$251,SMALL(IF(Data_Cleaning!$G$2:$G$251=$X5,ROW(Data_Cleaning!$G$2:$G$251)-ROW(Data_Cleaning!$G$2)+1),31)),"")} -> Keyboard | AA38: {=IFERROR(INDEX(Data_Cleaning!$N$2:$N$251,SMALL(IF(Data_Cleaning!$G$2:$G$251=$X5,ROW(Data_Cleaning!$G$2:$G$251)-ROW(Data_Cleaning!$G$2)+1),31)),"")} -> 89.99
A39: CUST036 | B39: =INDEX(Data_Cleaning!$D$2:$D$251,MATCH(A39,Data_Cleaning!$C$2:$C$251,0)) -> Nancy Collins | C39: =INDEX(Data_Cleaning!$M$2:$M$251,MATCH(A39,Data_Cleaning!$C$2:$C$251,0)) -> 44525 | D39: =DATEDIF(C39,TODAY(),"y") -> 4 | E39: =SUMIFS(Data_Cleaning!$N$2:$N$251,Data_Cleaning!$C$2:$C$251,A39) -> 4189.77 | F39: =COUNTIFS(Data_Cleaning!$C$2:$C$251,A39) -> 6 | G39: =IFERROR(E39/F39,0) -> 698.295 | H39: =RANK(E39,$E$4:$E$53) -> 27 | I39: =IF(H39<=10,"High Value","Standard") -> Standard | J39: =IF(COUNTIFS(Data_Cleaning!$C$2:$C$251,A39,Data_Cleaning!$F$2:$F$251,"Laptop")>0,"Yes","No") -> No | K39: =IF(AND(COUNTIFS(Data_Cleaning!$C$2:$C$251,A39,Data_Cleaning!$L$2:$L$251,"Premium")>0,J39="Yes"),B39,"") | L39: =UPPER(LEFT(B39,3))&"-"&RIGHT(A39,3) -> NAN-036 | W39: {=IFERROR(INDEX(Data_Cleaning!$A$2:$A$251,SMALL(IF(Data_Cleaning!$G$2:$G$251=$X5,ROW(Data_Cleaning!$G$2:$G$251)-ROW(Data_Cleaning!$G$2)+1),32)),"")} -> TRX0052 | X39: {=IFERROR(INDEX(Data_Cleaning!$B$2:$B$251,SMALL(IF(Data_Cleaning!$G$2:$G$251=$X5,ROW(Data_Cleaning!$G$2:$G$251)-ROW(Data_Cleaning!$G$2)+1),32)),"")} -> 45476 | Y39: {=IFERROR(INDEX(Data_Cleaning!$D$2:$D$251,SMALL(IF(Data_Cleaning!$G$2:$G$251=$X5,ROW(Data_Cleaning!$G$2:$G$251)-ROW(Data_Cleaning!$G$2)+1),32)),"")} -> Susan Green | Z39: {=IFERROR(INDEX(Data_Cleaning!$F$2:$F$251,SMALL(IF(Data_Cleaning!$G$2:$G$251=$X5,ROW(Data_Cleaning!$G$2:$G$251)-ROW(Data_Cleaning!$G$2)+1),32)),"")} -> Keyboard | AA39: {=IFERROR(INDEX(Data_Cleaning!$N$2:$N$251,SMALL(IF(Data_Cleaning!$G$2:$G$251=$X5,ROW(Data_Cleaning!$G$2:$G$251)-ROW(Data_Cleaning!$G$2)+1),32)),"")} -> 89.99
A40: CUST037 | B40: =INDEX(Data_Cleaning!$D$2:$D$251,MATCH(A40,Data_Cleaning!$C$2:$C$251,0)) -> Arthur Edwards | C40: =INDEX(Data_Cleaning!$M$2:$M$251,MATCH(A40,Data_Cleaning!$C$2:$C$251,0)) -> 44752 | D40: =DATEDIF(C40,TODAY(),"y") -> 4 | E40: =SUMIFS(Data_Cleaning!$N$2:$N$251,Data_Cleaning!$C$2:$C$251,A40) -> 1559.94 | F40: =COUNTIFS(Data_Cleaning!$C$2:$C$251,A40) -> 3 | G40: =IFERROR(E40/F40,0) -> 519.98 | H40: =RANK(E40,$E$4:$E$53) -> 41 | I40: =IF(H40<=10,"High Value","Standard") -> Standard | J40: =IF(COUNTIFS(Data_Cleaning!$C$2:$C$251,A40,Data_Cleaning!$F$2:$F$251,"Laptop")>0,"Yes","No") -> Yes | K40: =IF(AND(COUNTIFS(Data_Cleaning!$C$2:$C$251,A40,Data_Cleaning!$L$2:$L$251,"Premium")>0,J40="Yes"),B40,"") -> Arthur Edwards | L40: =UPPER(LEFT(B40,3))&"-"&RIGHT(A40,3) -> ART-037 | W40: {=IFERROR(INDEX(Data_Cleaning!$A$2:$A$251,SMALL(IF(Data_Cleaning!$G$2:$G$251=$X5,ROW(Data_Cleaning!$G$2:$G$251)-ROW(Data_Cleaning!$G$2)+1),33)),"")} -> TRX0113 | X40: {=IFERROR(INDEX(Data_Cleaning!$B$2:$B$251,SMALL(IF(Data_Cleaning!$G$2:$G$251=$X5,ROW(Data_Cleaning!$G$2:$G$251)-ROW(Data_Cleaning!$G$2)+1),33)),"")} -> 45481 | Y40: {=IFERROR(INDEX(Data_Cleaning!$D$2:$D$251,SMALL(IF(Data_Cleaning!$G$2:$G$251=$X5,ROW(Data_Cleaning!$G$2:$G$251)-ROW(Data_Cleaning!$G$2)+1),33)),"")} -> Michael Brown | Z40: {=IFERROR(INDEX(Data_Cleaning!$F$2:$F$251,SMALL(IF(Data_Cleaning!$G$2:$G$251=$X5,ROW(Data_Cleaning!$G$2:$G$251)-ROW(Data_Cleaning!$G$2)+1),33)),"")} -> Smartphone | AA40: {=IFERROR(INDEX(Data_Cleaning!$N$2:$N$251,SMALL(IF(Data_Cleaning!$G$2:$G$251=$X5,ROW(Data_Cleaning!$G$2:$G$251)-ROW(Data_Cleaning!$G$2)+1),33)),"")} -> 1399.98
A41: CUST038 | B41: =INDEX(Data_Cleaning!$D$2:$D$251,MATCH(A41,Data_Cleaning!$C$2:$C$251,0)) -> Michelle Rogers | C41: =INDEX(Data_Cleaning!$M$2:$M$251,MATCH(A41,Data_Cleaning!$C$2:$C$251,0)) -> 44577 | D41: =DATEDIF(C41,TODAY(),"y") -> 4 | E41: =SUMIFS(Data_Cleaning!$N$2:$N$251,Data_Cleaning!$C$2:$C$251,A41) -> 4199.94 | F41: =COUNTIFS(Data_Cleaning!$C$2:$C$251,A41) -> 2 | G41: =IFERROR(E41/F41,0) -> 2099.97 | H41: =RANK(E41,$E$4:$E$53) -> 26 | I41: =IF(H41<=10,"High Value","Standard") -> Standard | J41: =IF(COUNTIFS(Data_Cleaning!$C$2:$C$251,A41,Data_Cleaning!$F$2:$F$251,"Laptop")>0,"Yes","No") -> No | K41: =IF(AND(COUNTIFS(Data_Cleaning!$C$2:$C$251,A41,Data_Cleaning!$L$2:$L$251,"Premium")>0,J41="Yes"),B41,"") | L41: =UPPER(LEFT(B41,3))&"-"&RIGHT(A41,3) -> MIC-038 | W41: {=IFERROR(INDEX(Data_Cleaning!$A$2:$A$251,SMALL(IF(Data_Cleaning!$G$2:$G$251=$X5,ROW(Data_Cleaning!$G$2:$G$251)-ROW(Data_Cleaning!$G$2)+1),34)),"")} -> TRX0114 | X41: {=IFERROR(INDEX(Data_Cleaning!$B$2:$B$251,SMALL(IF(Data_Cleaning!$G$2:$G$251=$X5,ROW(Data_Cleaning!$G$2:$G$251)-ROW(Data_Cleaning!$G$2)+1),34)),"")} -> 45481 | Y41: {=IFERROR(INDEX(Data_Cleaning!$D$2:$D$251,SMALL(IF(Data_Cleaning!$G$2:$G$251=$X5,ROW(Data_Cleaning!$G$2:$G$251)-ROW(Data_Cleaning!$G$2)+1),34)),"")} -> Barbara Young | Z41: {=IFERROR(INDEX(Data_Cleaning!$F$2:$F$251,SMALL(IF(Data_Cleaning!$G$2:$G$251=$X5,ROW(Data_Cleaning!$G$2:$G$251)-ROW(Data_Cleaning!$G$2)+1),34)),"")} -> Keyboard | AA41: {=IFERROR(INDEX(Data_Cleaning!$N$2:$N$251,SMALL(IF(Data_Cleaning!$G$2:$G$251=$X5,ROW(Data_Cleaning!$G$2:$G$251)-ROW(Data_Cleaning!$G$2)+1),34)),"")} -> 449.95
A42: CUST039 | B42: =INDEX(Data_Cleaning!$D$2:$D$251,MATCH(A42,Data_Cleaning!$C$2:$C$251,0)) -> Lawrence Reed | C42: =INDEX(Data_Cleaning!$M$2:$M$251,MATCH(A42,Data_Cleaning!$C$2:$C$251,0)) -> 44779 | D42: =DATEDIF(C42,TODAY(),"y") -> 4 | E42: =SUMIFS(Data_Cleaning!$N$2:$N$251,Data_Cleaning!$C$2:$C$251,A42) -> 6989.77 | F42: =COUNTIFS(Data_Cleaning!$C$2:$C$251,A42) -> 8 | G42: =IFERROR(E42/F42,0) -> 873.72125 | H42: =RANK(E42,$E$4:$E$53) -> 9 | I42: =IF(H42<=10,"High Value","Standard") -> High Value | J42: =IF(COUNTIFS(Data_Cleaning!$C$2:$C$251,A42,Data_Cleaning!$F$2:$F$251,"Laptop")>0,"Yes","No") -> No | K42: =IF(AND(COUNTIFS(Data_Cleaning!$C$2:$C$251,A42,Data_Cleaning!$L$2:$L$251,"Premium")>0,J42="Yes"),B42,"") | L42: =UPPER(LEFT(B42,3))&"-"&RIGHT(A42,3) -> LAW-039 | W42: {=IFERROR(INDEX(Data_Cleaning!$A$2:$A$251,SMALL(IF(Data_Cleaning!$G$2:$G$251=$X5,ROW(Data_Cleaning!$G$2:$G$251)-ROW(Data_Cleaning!$G$2)+1),35)),"")} -> TRX0018 | X42: {=IFERROR(INDEX(Data_Cleaning!$B$2:$B$251,SMALL(IF(Data_Cleaning!$G$2:$G$251=$X5,ROW(Data_Cleaning!$G$2:$G$251)-ROW(Data_Cleaning!$G$2)+1),35)),"")} -> 45484 | Y42: {=IFERROR(INDEX(Data_Cleaning!$D$2:$D$251,SMALL(IF(Data_Cleaning!$G$2:$G$251=$X5,ROW(Data_Cleaning!$G$2:$G$251)-ROW(Data_Cleaning!$G$2)+1),35)),"")} -> Joseph Jackson | Z42: {=IFERROR(INDEX(Data_Cleaning!$F$2:$F$251,SMALL(IF(Data_Cleaning!$G$2:$G$251=$X5,ROW(Data_Cleaning!$G$2:$G$251)-ROW(Data_Cleaning!$G$2)+1),35)),"")} -> Headphones | AA42: {=IFERROR(INDEX(Data_Cleaning!$N$2:$N$251,SMALL(IF(Data_Cleaning!$G$2:$G$251=$X5,ROW(Data_Cleaning!$G$2:$G$251)-ROW(Data_Cleaning!$G$2)+1),35)),"")} -> 149.99
A43: CUST040 | B43: =INDEX(Data_Cleaning!$D$2:$D$251,MATCH(A43,Data_Cleaning!$C$2:$C$251,0)) -> Sharon Butler | C43: =INDEX(Data_Cleaning!$M$2:$M$251,MATCH(A43,Data_Cleaning!$C$2:$C$251,0)) -> 45390 | D43: =DATEDIF(C43,TODAY(),"y") -> 2 | E43: =SUMIFS(Data_Cleaning!$N$2:$N$251,Data_Cleaning!$C$2:$C$251,A43) -> 5619.87 | F43: =COUNTIFS(Data_Cleaning!$C$2:$C$251,A43) -> 6 | G43: =IFERROR(E43/F43,0) -> 936.645 | H43: =RANK(E43,$E$4:$E$53) -> 17 | I43: =IF(H43<=10,"High Value","Standard") -> Standard | J43: =IF(COUNTIFS(Data_Cleaning!$C$2:$C$251,A43,Data_Cleaning!$F$2:$F$251,"Laptop")>0,"Yes","No") -> Yes | K43: =IF(AND(COUNTIFS(Data_Cleaning!$C$2:$C$251,A43,Data_Cleaning!$L$2:$L$251,"Premium")>0,J43="Yes"),B43,"") -> Sharon Butler | L43: =UPPER(LEFT(B43,3))&"-"&RIGHT(A43,3) -> SHA-040 | W43: {=IFERROR(INDEX(Data_Cleaning!$A$2:$A$251,SMALL(IF(Data_Cleaning!$G$2:$G$251=$X5,ROW(Data_Cleaning!$G$2:$G$251)-ROW(Data_Cleaning!$G$2)+1),36)),"")} -> TRX0162 | X43: {=IFERROR(INDEX(Data_Cleaning!$B$2:$B$251,SMALL(IF(Data_Cleaning!$G$2:$G$251=$X5,ROW(Data_Cleaning!$G$2:$G$251)-ROW(Data_Cleaning!$G$2)+1),36)),"")} -> 45496 | Y43: {=IFERROR(INDEX(Data_Cleaning!$D$2:$D$251,SMALL(IF(Data_Cleaning!$G$2:$G$251=$X5,ROW(Data_Cleaning!$G$2:$G$251)-ROW(Data_Cleaning!$G$2)+1),36)),"")} -> Sharon Butler | Z43: {=IFERROR(INDEX(Data_Cleaning!$F$2:$F$251,SMALL(IF(Data_Cleaning!$G$2:$G$251=$X5,ROW(Data_Cleaning!$G$2:$G$251)-ROW(Data_Cleaning!$G$2)+1),36)),"")} -> Laptop | AA43: {=IFERROR(INDEX(Data_Cleaning!$N$2:$N$251,SMALL(IF(Data_Cleaning!$G$2:$G$251=$X5,ROW(Data_Cleaning!$G$2:$G$251)-ROW(Data_Cleaning!$G$2)+1),36)),"")} -> 899.99
A44: CUST041 | B44: =INDEX(Data_Cleaning!$D$2:$D$251,MATCH(A44,Data_Cleaning!$C$2:$C$251,0)) -> Peter Richardson | C44: =INDEX(Data_Cleaning!$M$2:$M$251,MATCH(A44,Data_Cleaning!$C$2:$C$251,0)) -> 44806 | D44: =DATEDIF(C44,TODAY(),"y") -> 4 | E44: =SUMIFS(Data_Cleaning!$N$2:$N$251,Data_Cleaning!$C$2:$C$251,A44) -> 5949.85 | F44: =COUNTIFS(Data_Cleaning!$C$2:$C$251,A44) -> 5 | G44: =IFERROR(E44/F44,0) -> 1189.97 | H44: =RANK(E44,$E$4:$E$53) -> 15 | I44: =IF(H44<=10,"High Value","Standard") -> Standard | J44: =IF(COUNTIFS(Data_Cleaning!$C$2:$C$251,A44,Data_Cleaning!$F$2:$F$251,"Laptop")>0,"Yes","No") -> Yes | K44: =IF(AND(COUNTIFS(Data_Cleaning!$C$2:$C$251,A44,Data_Cleaning!$L$2:$L$251,"Premium")>0,J44="Yes"),B44,"") -> Peter Richardson | L44: =UPPER(LEFT(B44,3))&"-"&RIGHT(A44,3) -> PET-041 | W44: {=IFERROR(INDEX(Data_Cleaning!$A$2:$A$251,SMALL(IF(Data_Cleaning!$G$2:$G$251=$X5,ROW(Data_Cleaning!$G$2:$G$251)-ROW(Data_Cleaning!$G$2)+1),37)),"")} -> TRX0244 | X44: {=IFERROR(INDEX(Data_Cleaning!$B$2:$B$251,SMALL(IF(Data_Cleaning!$G$2:$G$251=$X5,ROW(Data_Cleaning!$G$2:$G$251)-ROW(Data_Cleaning!$G$2)+1),37)),"")} -> 45497 | Y44: {=IFERROR(INDEX(Data_Cleaning!$D$2:$D$251,SMALL(IF(Data_Cleaning!$G$2:$G$251=$X5,ROW(Data_Cleaning!$G$2:$G$251)-ROW(Data_Cleaning!$G$2)+1),37)),"")} -> Joseph Jackson | Z44: {=IFERROR(INDEX(Data_Cleaning!$F$2:$F$251,SMALL(IF(Data_Cleaning!$G$2:$G$251=$X5,ROW(Data_Cleaning!$G$2:$G$251)-ROW(Data_Cleaning!$G$2)+1),37)),"")} -> Laptop | AA44: {=IFERROR(INDEX(Data_Cleaning!$N$2:$N$251,SMALL(IF(Data_Cleaning!$G$2:$G$251=$X5,ROW(Data_Cleaning!$G$2:$G$251)-ROW(Data_Cleaning!$G$2)+1),37)),"")} -> 4499.95
A45: CUST042 | B45: =INDEX(Data_Cleaning!$D$2:$D$251,MATCH(A45,Data_Cleaning!$C$2:$C$251,0)) -> Ruth Brooks | C45: =INDEX(Data_Cleaning!$M$2:$M$251,MATCH(A45,Data_Cleaning!$C$2:$C$251,0)) -> 44909 | D45: =DATEDIF(C45,TODAY(),"y") -> 3 | E45: =SUMIFS(Data_Cleaning!$N$2:$N$251,Data_Cleaning!$C$2:$C$251,A45) -> 1749.92 | F45: =COUNTIFS(Data_Cleaning!$C$2:$C$251,A45) -> 3 | G45: =IFERROR(E45/F45,0) -> 583.30667 | H45: =RANK(E45,$E$4:$E$53) -> 40 | I45: =IF(H45<=10,"High Value","Standard") -> Standard | J45: =IF(COUNTIFS(Data_Cleaning!$C$2:$C$251,A45,Data_Cleaning!$F$2:$F$251,"Laptop")>0,"Yes","No") -> No | K45: =IF(AND(COUNTIFS(Data_Cleaning!$C$2:$C$251,A45,Data_Cleaning!$L$2:$L$251,"Premium")>0,J45="Yes"),B45,"") | L45: =UPPER(LEFT(B45,3))&"-"&RIGHT(A45,3) -> RUT-042 | W45: {=IFERROR(INDEX(Data_Cleaning!$A$2:$A$251,SMALL(IF(Data_Cleaning!$G$2:$G$251=$X5,ROW(Data_Cleaning!$G$2:$G$251)-ROW(Data_Cleaning!$G$2)+1),38)),"")} -> TRX0215 | X45: {=IFERROR(INDEX(Data_Cleaning!$B$2:$B$251,SMALL(IF(Data_Cleaning!$G$2:$G$251=$X5,ROW(Data_Cleaning!$G$2:$G$251)-ROW(Data_Cleaning!$G$2)+1),38)),"")} -> 45498 | Y45: {=IFERROR(INDEX(Data_Cleaning!$D$2:$D$251,SMALL(IF(Data_Cleaning!$G$2:$G$251=$X5,ROW(Data_Cleaning!$G$2:$G$251)-ROW(Data_Cleaning!$G$2)+1),38)),"")} -> Gerald Murphy | Z45: {=IFERROR(INDEX(Data_Cleaning!$F$2:$F$251,SMALL(IF(Data_Cleaning!$G$2:$G$251=$X5,ROW(Data_Cleaning!$G$2:$G$251)-ROW(Data_Cleaning!$G$2)+1),38)),"")} -> Monitor | AA45: {=IFERROR(INDEX(Data_Cleaning!$N$2:$N$251,SMALL(IF(Data_Cleaning!$G$2:$G$251=$X5,ROW(Data_Cleaning!$G$2:$G$251)-ROW(Data_Cleaning!$G$2)+1),38)),"")} -> 999.96
A46: CUST043 | B46: =INDEX(Data_Cleaning!$D$2:$D$251,MATCH(A46,Data_Cleaning!$C$2:$C$251,0)) -> Dennis Gray | C46: =INDEX(Data_Cleaning!$M$2:$M$251,MATCH(A46,Data_Cleaning!$C$2:$C$251,0)) -> 45351 | D46: =DATEDIF(C46,TODAY(),"y") -> 2 | E46: =SUMIFS(Data_Cleaning!$N$2:$N$251,Data_Cleaning!$C$2:$C$251,A46) -> 479.92 | F46: =COUNTIFS(Data_Cleaning!$C$2:$C$251,A46) -> 2 | G46: =IFERROR(E46/F46,0) -> 239.96 | H46: =RANK(E46,$E$4:$E$53) -> 48 | I46: =IF(H46<=10,"High Value","Standard") -> Standard | J46: =IF(COUNTIFS(Data_Cleaning!$C$2:$C$251,A46,Data_Cleaning!$F$2:$F$251,"Laptop")>0,"Yes","No") -> No | K46: =IF(AND(COUNTIFS(Data_Cleaning!$C$2:$C$251,A46,Data_Cleaning!$L$2:$L$251,"Premium")>0,J46="Yes"),B46,"") | L46: =UPPER(LEFT(B46,3))&"-"&RIGHT(A46,3) -> DEN-043 | W46: {=IFERROR(INDEX(Data_Cleaning!$A$2:$A$251,SMALL(IF(Data_Cleaning!$G$2:$G$251=$X5,ROW(Data_Cleaning!$G$2:$G$251)-ROW(Data_Cleaning!$G$2)+1),39)),"")} -> TRX0080 | X46: {=IFERROR(INDEX(Data_Cleaning!$B$2:$B$251,SMALL(IF(Data_Cleaning!$G$2:$G$251=$X5,ROW(Data_Cleaning!$G$2:$G$251)-ROW(Data_Cleaning!$G$2)+1),39)),"")} -> 45500 | Y46: {=IFERROR(INDEX(Data_Cleaning!$D$2:$D$251,SMALL(IF(Data_Cleaning!$G$2:$G$251=$X5,ROW(Data_Cleaning!$G$2:$G$251)-ROW(Data_Cleaning!$G$2)+1),39)),"")} -> Barbara Young | Z46: {=IFERROR(INDEX(Data_Cleaning!$F$2:$F$251,SMALL(IF(Data_Cleaning!$G$2:$G$251=$X5,ROW(Data_Cleaning!$G$2:$G$251)-ROW(Data_Cleaning!$G$2)+1),39)),"")} -> Monitor | AA46: {=IFERROR(INDEX(Data_Cleaning!$N$2:$N$251,SMALL(IF(Data_Cleaning!$G$2:$G$251=$X5,ROW(Data_Cleaning!$G$2:$G$251)-ROW(Data_Cleaning!$G$2)+1),39)),"")} -> 499.98
A47: CUST044 | B47: =INDEX(Data_Cleaning!$D$2:$D$251,MATCH(A47,Data_Cleaning!$C$2:$C$251,0)) -> Cynthia Price | C47: =INDEX(Data_Cleaning!$M$2:$M$251,MATCH(A47,Data_Cleaning!$C$2:$C$251,0)) -> 44468 | D47: =DATEDIF(C47,TODAY(),"y") -> 4 | E47: =SUMIFS(Data_Cleaning!$N$2:$N$251,Data_Cleaning!$C$2:$C$251,A47) -> 3769.83 | F47: =COUNTIFS(Data_Cleaning!$C$2:$C$251,A47) -> 5 | G47: =IFERROR(E47/F47,0) -> 753.966 | H47: =RANK(E47,$E$4:$E$53) -> 29 | I47: =IF(H47<=10,"High Value","Standard") -> Standard | J47: =IF(COUNTIFS(Data_Cleaning!$C$2:$C$251,A47,Data_Cleaning!$F$2:$F$251,"Laptop")>0,"Yes","No") -> No | K47: =IF(AND(COUNTIFS(Data_Cleaning!$C$2:$C$251,A47,Data_Cleaning!$L$2:$L$251,"Premium")>0,J47="Yes"),B47,"") | L47: =UPPER(LEFT(B47,3))&"-"&RIGHT(A47,3) -> CYN-044 | W47: {=IFERROR(INDEX(Data_Cleaning!$A$2:$A$251,SMALL(IF(Data_Cleaning!$G$2:$G$251=$X5,ROW(Data_Cleaning!$G$2:$G$251)-ROW(Data_Cleaning!$G$2)+1),40)),"")} -> TRX0157 | X47: {=IFERROR(INDEX(Data_Cleaning!$B$2:$B$251,SMALL(IF(Data_Cleaning!$G$2:$G$251=$X5,ROW(Data_Cleaning!$G$2:$G$251)-ROW(Data_Cleaning!$G$2)+1),40)),"")} -> 45501 | Y47: {=IFERROR(INDEX(Data_Cleaning!$D$2:$D$251,SMALL(IF(Data_Cleaning!$G$2:$G$251=$X5,ROW(Data_Cleaning!$G$2:$G$251)-ROW(Data_Cleaning!$G$2)+1),40)),"")} -> Mark Carter | Z47: {=IFERROR(INDEX(Data_Cleaning!$F$2:$F$251,SMALL(IF(Data_Cleaning!$G$2:$G$251=$X5,ROW(Data_Cleaning!$G$2:$G$251)-ROW(Data_Cleaning!$G$2)+1),40)),"")} -> Keyboard | AA47: {=IFERROR(INDEX(Data_Cleaning!$N$2:$N$251,SMALL(IF(Data_Cleaning!$G$2:$G$251=$X5,ROW(Data_Cleaning!$G$2:$G$251)-ROW(Data_Cleaning!$G$2)+1),40)),"")} -> 179.98
A48: CUST045 | B48: =INDEX(Data_Cleaning!$D$2:$D$251,MATCH(A48,Data_Cleaning!$C$2:$C$251,0)) -> Douglas Watson | C48: =INDEX(Data_Cleaning!$M$2:$M$251,MATCH(A48,Data_Cleaning!$C$2:$C$251,0)) -> 44873 | D48: =DATEDIF(C48,TODAY(),"y") -> 3 | E48: =SUMIFS(Data_Cleaning!$N$2:$N$251,Data_Cleaning!$C$2:$C$251,A48) -> 4829.89 | F48: =COUNTIFS(Data_Cleaning!$C$2:$C$251,A48) -> 4 | G48: =IFERROR(E48/F48,0) -> 1207.4725 | H48: =RANK(E48,$E$4:$E$53) -> 21 | I48: =IF(H48<=10,"High Value","Standard") -> Standard | J48: =IF(COUNTIFS(Data_Cleaning!$C$2:$C$251,A48,Data_Cleaning!$F$2:$F$251,"Laptop")>0,"Yes","No") -> No | K48: =IF(AND(COUNTIFS(Data_Cleaning!$C$2:$C$251,A48,Data_Cleaning!$L$2:$L$251,"Premium")>0,J48="Yes"),B48,"") | L48: =UPPER(LEFT(B48,3))&"-"&RIGHT(A48,3) -> DOU-045 | W48: {=IFERROR(INDEX(Data_Cleaning!$A$2:$A$251,SMALL(IF(Data_Cleaning!$G$2:$G$251=$X5,ROW(Data_Cleaning!$G$2:$G$251)-ROW(Data_Cleaning!$G$2)+1),41)),"")} -> TRX0217 | X48: {=IFERROR(INDEX(Data_Cleaning!$B$2:$B$251,SMALL(IF(Data_Cleaning!$G$2:$G$251=$X5,ROW(Data_Cleaning!$G$2:$G$251)-ROW(Data_Cleaning!$G$2)+1),41)),"")} -> 45503 | Y48: {=IFERROR(INDEX(Data_Cleaning!$D$2:$D$251,SMALL(IF(Data_Cleaning!$G$2:$G$251=$X5,ROW(Data_Cleaning!$G$2:$G$251)-ROW(Data_Cleaning!$G$2)+1),41)),"")} -> Mark Carter | Z48: {=IFERROR(INDEX(Data_Cleaning!$F$2:$F$251,SMALL(IF(Data_Cleaning!$G$2:$G$251=$X5,ROW(Data_Cleaning!$G$2:$G$251)-ROW(Data_Cleaning!$G$2)+1),41)),"")} -> Smartphone | AA48: {=IFERROR(INDEX(Data_Cleaning!$N$2:$N$251,SMALL(IF(Data_Cleaning!$G$2:$G$251=$X5,ROW(Data_Cleaning!$G$2:$G$251)-ROW(Data_Cleaning!$G$2)+1),41)),"")} -> 1399.98
A49: CUST046 | B49: =INDEX(Data_Cleaning!$D$2:$D$251,MATCH(A49,Data_Cleaning!$C$2:$C$251,0)) -> Kathleen Bennett | C49: =INDEX(Data_Cleaning!$M$2:$M$251,MATCH(A49,Data_Cleaning!$C$2:$C$251,0)) -> 45114 | D49: =DATEDIF(C49,TODAY(),"y") -> 3 | E49: =SUMIFS(Data_Cleaning!$N$2:$N$251,Data_Cleaning!$C$2:$C$251,A49) -> 4309.81 | F49: =COUNTIFS(Data_Cleaning!$C$2:$C$251,A49) -> 6 | G49: =IFERROR(E49/F49,0) -> 718.30167 | H49: =RANK(E49,$E$4:$E$53) -> 25 | I49: =IF(H49<=10,"High Value","Standard") -> Standard | J49: =IF(COUNTIFS(Data_Cleaning!$C$2:$C$251,A49,Data_Cleaning!$F$2:$F$251,"Laptop")>0,"Yes","No") -> No | K49: =IF(AND(COUNTIFS(Data_Cleaning!$C$2:$C$251,A49,Data_Cleaning!$L$2:$L$251,"Premium")>0,J49="Yes"),B49,"") | L49: =UPPER(LEFT(B49,3))&"-"&RIGHT(A49,3) -> KAT-046 | W49: {=IFERROR(INDEX(Data_Cleaning!$A$2:$A$251,SMALL(IF(Data_Cleaning!$G$2:$G$251=$X5,ROW(Data_Cleaning!$G$2:$G$251)-ROW(Data_Cleaning!$G$2)+1),42)),"")} -> TRX0249 | X49: {=IFERROR(INDEX(Data_Cleaning!$B$2:$B$251,SMALL(IF(Data_Cleaning!$G$2:$G$251=$X5,ROW(Data_Cleaning!$G$2:$G$251)-ROW(Data_Cleaning!$G$2)+1),42)),"")} -> 45504 | Y49: {=IFERROR(INDEX(Data_Cleaning!$D$2:$D$251,SMALL(IF(Data_Cleaning!$G$2:$G$251=$X5,ROW(Data_Cleaning!$G$2:$G$251)-ROW(Data_Cleaning!$G$2)+1),42)),"")} -> Helen Roberts | Z49: {=IFERROR(INDEX(Data_Cleaning!$F$2:$F$251,SMALL(IF(Data_Cleaning!$G$2:$G$251=$X5,ROW(Data_Cleaning!$G$2:$G$251)-ROW(Data_Cleaning!$G$2)+1),42)),"")} -> Laptop | AA49: {=IFERROR(INDEX(Data_Cleaning!$N$2:$N$251,SMALL(IF(Data_Cleaning!$G$2:$G$251=$X5,ROW(Data_Cleaning!$G$2:$G$251)-ROW(Data_Cleaning!$G$2)+1),42)),"")} -> 3599.96
A50: CUST047 | B50: =INDEX(Data_Cleaning!$D$2:$D$251,MATCH(A50,Data_Cleaning!$C$2:$C$251,0)) -> Gerald Murphy | C50: =INDEX(Data_Cleaning!$M$2:$M$251,MATCH(A50,Data_Cleaning!$C$2:$C$251,0)) -> 45130 | D50: =DATEDIF(C50,TODAY(),"y") -> 3 | E50: =SUMIFS(Data_Cleaning!$N$2:$N$251,Data_Cleaning!$C$2:$C$251,A50) -> 6379.87 | F50: =COUNTIFS(Data_Cleaning!$C$2:$C$251,A50) -> 4 | G50: =IFERROR(E50/F50,0) -> 1594.9675 | H50: =RANK(E50,$E$4:$E$53) -> 12 | I50: =IF(H50<=10,"High Value","Standard") -> Standard | J50: =IF(COUNTIFS(Data_Cleaning!$C$2:$C$251,A50,Data_Cleaning!$F$2:$F$251,"Laptop")>0,"Yes","No") -> Yes | K50: =IF(AND(COUNTIFS(Data_Cleaning!$C$2:$C$251,A50,Data_Cleaning!$L$2:$L$251,"Premium")>0,J50="Yes"),B50,"") -> Gerald Murphy | L50: =UPPER(LEFT(B50,3))&"-"&RIGHT(A50,3) -> GER-047 | W50: {=IFERROR(INDEX(Data_Cleaning!$A$2:$A$251,SMALL(IF(Data_Cleaning!$G$2:$G$251=$X5,ROW(Data_Cleaning!$G$2:$G$251)-ROW(Data_Cleaning!$G$2)+1),43)),"")} -> TRX0101 | X50: {=IFERROR(INDEX(Data_Cleaning!$B$2:$B$251,SMALL(IF(Data_Cleaning!$G$2:$G$251=$X5,ROW(Data_Cleaning!$G$2:$G$251)-ROW(Data_Cleaning!$G$2)+1),43)),"")} -> 45513 | Y50: {=IFERROR(INDEX(Data_Cleaning!$D$2:$D$251,SMALL(IF(Data_Cleaning!$G$2:$G$251=$X5,ROW(Data_Cleaning!$G$2:$G$251)-ROW(Data_Cleaning!$G$2)+1),43)),"")} -> Maria Garcia | Z50: {=IFERROR(INDEX(Data_Cleaning!$F$2:$F$251,SMALL(IF(Data_Cleaning!$G$2:$G$251=$X5,ROW(Data_Cleaning!$G$2:$G$251)-ROW(Data_Cleaning!$G$2)+1),43)),"")} -> Keyboard | AA50: {=IFERROR(INDEX(Data_Cleaning!$N$2:$N$251,SMALL(IF(Data_Cleaning!$G$2:$G$251=$X5,ROW(Data_Cleaning!$G$2:$G$251)-ROW(Data_Cleaning!$G$2)+1),43)),"")} -> 89.99
A51: CUST048 | B51: =INDEX(Data_Cleaning!$D$2:$D$251,MATCH(A51,Data_Cleaning!$C$2:$C$251,0)) -> Virginia Sanders | C51: =INDEX(Data_Cleaning!$M$2:$M$251,MATCH(A51,Data_Cleaning!$C$2:$C$251,0)) -> 45224 | D51: =DATEDIF(C51,TODAY(),"y") -> 2 | E51: =SUMIFS(Data_Cleaning!$N$2:$N$251,Data_Cleaning!$C$2:$C$251,A51) -> 4789.79 | F51: =COUNTIFS(Data_Cleaning!$C$2:$C$251,A51) -> 6 | G51: =IFERROR(E51/F51,0) -> 798.29833 | H51: =RANK(E51,$E$4:$E$53) -> 22 | I51: =IF(H51<=10,"High Value","Standard") -> Standard | J51: =IF(COUNTIFS(Data_Cleaning!$C$2:$C$251,A51,Data_Cleaning!$F$2:$F$251,"Laptop")>0,"Yes","No") -> No | K51: =IF(AND(COUNTIFS(Data_Cleaning!$C$2:$C$251,A51,Data_Cleaning!$L$2:$L$251,"Premium")>0,J51="Yes"),B51,"") | L51: =UPPER(LEFT(B51,3))&"-"&RIGHT(A51,3) -> VIR-048 | W51: {=IFERROR(INDEX(Data_Cleaning!$A$2:$A$251,SMALL(IF(Data_Cleaning!$G$2:$G$251=$X5,ROW(Data_Cleaning!$G$2:$G$251)-ROW(Data_Cleaning!$G$2)+1),44)),"")} -> TRX0020 | X51: {=IFERROR(INDEX(Data_Cleaning!$B$2:$B$251,SMALL(IF(Data_Cleaning!$G$2:$G$251=$X5,ROW(Data_Cleaning!$G$2:$G$251)-ROW(Data_Cleaning!$G$2)+1),44)),"")} -> 45517 | Y51: {=IFERROR(INDEX(Data_Cleaning!$D$2:$D$251,SMALL(IF(Data_Cleaning!$G$2:$G$251=$X5,ROW(Data_Cleaning!$G$2:$G$251)-ROW(Data_Cleaning!$G$2)+1),44)),"")} -> David Martinez | Z51: {=IFERROR(INDEX(Data_Cleaning!$F$2:$F$251,SMALL(IF(Data_Cleaning!$G$2:$G$251=$X5,ROW(Data_Cleaning!$G$2:$G$251)-ROW(Data_Cleaning!$G$2)+1),44)),"")} -> Headphones | AA51: {=IFERROR(INDEX(Data_Cleaning!$N$2:$N$251,SMALL(IF(Data_Cleaning!$G$2:$G$251=$X5,ROW(Data_Cleaning!$G$2:$G$251)-ROW(Data_Cleaning!$G$2)+1),44)),"")} -> 599.96
A52: CUST049 | B52: =INDEX(Data_Cleaning!$D$2:$D$251,MATCH(A52,Data_Cleaning!$C$2:$C$251,0)) -> Raymond Ross | C52: =INDEX(Data_Cleaning!$M$2:$M$251,MATCH(A52,Data_Cleaning!$C$2:$C$251,0)) -> 45281 | D52: =DATEDIF(C52,TODAY(),"y") -> 2 | E52: =SUMIFS(Data_Cleaning!$N$2:$N$251,Data_Cleaning!$C$2:$C$251,A52) -> 3669.85 | F52: =COUNTIFS(Data_Cleaning!$C$2:$C$251,A52) -> 4 | G52: =IFERROR(E52/F52,0) -> 917.4625 | H52: =RANK(E52,$E$4:$E$53) -> 30 | I52: =IF(H52<=10,"High Value","Standard") -> Standard | J52: =IF(COUNTIFS(Data_Cleaning!$C$2:$C$251,A52,Data_Cleaning!$F$2:$F$251,"Laptop")>0,"Yes","No") -> No | K52: =IF(AND(COUNTIFS(Data_Cleaning!$C$2:$C$251,A52,Data_Cleaning!$L$2:$L$251,"Premium")>0,J52="Yes"),B52,"") | L52: =UPPER(LEFT(B52,3))&"-"&RIGHT(A52,3) -> RAY-049 | W52: {=IFERROR(INDEX(Data_Cleaning!$A$2:$A$251,SMALL(IF(Data_Cleaning!$G$2:$G$251=$X5,ROW(Data_Cleaning!$G$2:$G$251)-ROW(Data_Cleaning!$G$2)+1),45)),"")} -> TRX0075 | X52: {=IFERROR(INDEX(Data_Cleaning!$B$2:$B$251,SMALL(IF(Data_Cleaning!$G$2:$G$251=$X5,ROW(Data_Cleaning!$G$2:$G$251)-ROW(Data_Cleaning!$G$2)+1),45)),"")} -> 45517 | Y52: {=IFERROR(INDEX(Data_Cleaning!$D$2:$D$251,SMALL(IF(Data_Cleaning!$G$2:$G$251=$X5,ROW(Data_Cleaning!$G$2:$G$251)-ROW(Data_Cleaning!$G$2)+1),45)),"")} -> Margaret Wright | Z52: {=IFERROR(INDEX(Data_Cleaning!$F$2:$F$251,SMALL(IF(Data_Cleaning!$G$2:$G$251=$X5,ROW(Data_Cleaning!$G$2:$G$251)-ROW(Data_Cleaning!$G$2)+1),45)),"")} -> Monitor | AA52: {=IFERROR(INDEX(Data_Cleaning!$N$2:$N$251,SMALL(IF(Data_Cleaning!$G$2:$G$251=$X5,ROW(Data_Cleaning!$G$2:$G$251)-ROW(Data_Cleaning!$G$2)+1),45)),"")} -> 1249.95
A53: CUST050 | B53: =INDEX(Data_Cleaning!$D$2:$D$251,MATCH(A53,Data_Cleaning!$C$2:$C$251,0)) -> Julie Foster | C53: =INDEX(Data_Cleaning!$M$2:$M$251,MATCH(A53,Data_Cleaning!$C$2:$C$251,0)) -> 44435 | D53: =DATEDIF(C53,TODAY(),"y") -> 5 | E53: =SUMIFS(Data_Cleaning!$N$2:$N$251,Data_Cleaning!$C$2:$C$251,A53) -> 239.96 | F53: =COUNTIFS(Data_Cleaning!$C$2:$C$251,A53) -> 1 | G53: =IFERROR(E53/F53,0) -> 239.96 | H53: =RANK(E53,$E$4:$E$53) -> 49 | I53: =IF(H53<=10,"High Value","Standard") -> Standard | J53: =IF(COUNTIFS(Data_Cleaning!$C$2:$C$251,A53,Data_Cleaning!$F$2:$F$251,"Laptop")>0,"Yes","No") -> No | K53: =IF(AND(COUNTIFS(Data_Cleaning!$C$2:$C$251,A53,Data_Cleaning!$L$2:$L$251,"Premium")>0,J53="Yes"),B53,"") | L53: =UPPER(LEFT(B53,3))&"-"&RIGHT(A53,3) -> JUL-050 | W53: {=IFERROR(INDEX(Data_Cleaning!$A$2:$A$251,SMALL(IF(Data_Cleaning!$G$2:$G$251=$X5,ROW(Data_Cleaning!$G$2:$G$251)-ROW(Data_Cleaning!$G$2)+1),46)),"")} -> TRX0098 | X53: {=IFERROR(INDEX(Data_Cleaning!$B$2:$B$251,SMALL(IF(Data_Cleaning!$G$2:$G$251=$X5,ROW(Data_Cleaning!$G$2:$G$251)-ROW(Data_Cleaning!$G$2)+1),46)),"")} -> 45517 | Y53: {=IFERROR(INDEX(Data_Cleaning!$D$2:$D$251,SMALL(IF(Data_Cleaning!$G$2:$G$251=$X5,ROW(Data_Cleaning!$G$2:$G$251)-ROW(Data_Cleaning!$G$2)+1),46)),"")} -> Karen Hill | Z53: {=IFERROR(INDEX(Data_Cleaning!$F$2:$F$251,SMALL(IF(Data_Cleaning!$G$2:$G$251=$X5,ROW(Data_Cleaning!$G$2:$G$251)-ROW(Data_Cleaning!$G$2)+1),46)),"")} -> Monitor | AA53: {=IFERROR(INDEX(Data_Cleaning!$N$2:$N$251,SMALL(IF(Data_Cleaning!$G$2:$G$251=$X5,ROW(Data_Cleaning!$G$2:$G$251)-ROW(Data_Cleaning!$G$2)+1),46)),"")} -> 749.97
W54: {=IFERROR(INDEX(Data_Cleaning!$A$2:$A$251,SMALL(IF(Data_Cleaning!$G$2:$G$251=$X5,ROW(Data_Cleaning!$G$2:$G$251)-ROW(Data_Cleaning!$G$2)+1),47)),"")} -> TRX0140 | X54: {=IFERROR(INDEX(Data_Cleaning!$B$2:$B$251,SMALL(IF(Data_Cleaning!$G$2:$G$251=$X5,ROW(Data_Cleaning!$G$2:$G$251)-ROW(Data_Cleaning!$G$2)+1),47)),"")} -> 45522 | Y54: {=IFERROR(INDEX(Data_Cleaning!$D$2:$D$251,SMALL(IF(Data_Cleaning!$G$2:$G$251=$X5,ROW(Data_Cleaning!$G$2:$G$251)-ROW(Data_Cleaning!$G$2)+1),47)),"")} -> Mark Carter | Z54: {=IFERROR(INDEX(Data_Cleaning!$F$2:$F$251,SMALL(IF(Data_Cleaning!$G$2:$G$251=$X5,ROW(Data_Cleaning!$G$2:$G$251)-ROW(Data_Cleaning!$G$2)+1),47)),"")} -> Keyboard | AA54: {=IFERROR(INDEX(Data_Cleaning!$N$2:$N$251,SMALL(IF(Data_Cleaning!$G$2:$G$251=$X5,ROW(Data_Cleaning!$G$2:$G$251)-ROW(Data_Cleaning!$G$2)+1),47)),"")} -> 179.98
W55: {=IFERROR(INDEX(Data_Cleaning!$A$2:$A$251,SMALL(IF(Data_Cleaning!$G$2:$G$251=$X5,ROW(Data_Cleaning!$G$2:$G$251)-ROW(Data_Cleaning!$G$2)+1),48)),"")} -> TRX0132 | X55: {=IFERROR(INDEX(Data_Cleaning!$B$2:$B$251,SMALL(IF(Data_Cleaning!$G$2:$G$251=$X5,ROW(Data_Cleaning!$G$2:$G$251)-ROW(Data_Cleaning!$G$2)+1),48)),"")} -> 45523 | Y55: {=IFERROR(INDEX(Data_Cleaning!$D$2:$D$251,SMALL(IF(Data_Cleaning!$G$2:$G$251=$X5,ROW(Data_Cleaning!$G$2:$G$251)-ROW(Data_Cleaning!$G$2)+1),48)),"")} -> Gerald Murphy | Z55: {=IFERROR(INDEX(Data_Cleaning!$F$2:$F$251,SMALL(IF(Data_Cleaning!$G$2:$G$251=$X5,ROW(Data_Cleaning!$G$2:$G$251)-ROW(Data_Cleaning!$G$2)+1),48)),"")} -> Laptop | AA55: {=IFERROR(INDEX(Data_Cleaning!$N$2:$N$251,SMALL(IF(Data_Cleaning!$G$2:$G$251=$X5,ROW(Data_Cleaning!$G$2:$G$251)-ROW(Data_Cleaning!$G$2)+1),48)),"")} -> 4499.95
W56: {=IFERROR(INDEX(Data_Cleaning!$A$2:$A$251,SMALL(IF(Data_Cleaning!$G$2:$G$251=$X5,ROW(Data_Cleaning!$G$2:$G$251)-ROW(Data_Cleaning!$G$2)+1),49)),"")} -> TRX0031 | X56: {=IFERROR(INDEX(Data_Cleaning!$B$2:$B$251,SMALL(IF(Data_Cleaning!$G$2:$G$251=$X5,ROW(Data_Cleaning!$G$2:$G$251)-ROW(Data_Cleaning!$G$2)+1),49)),"")} -> 45523 | Y56: {=IFERROR(INDEX(Data_Cleaning!$D$2:$D$251,SMALL(IF(Data_Cleaning!$G$2:$G$251=$X5,ROW(Data_Cleaning!$G$2:$G$251)-ROW(Data_Cleaning!$G$2)+1),49)),"")} -> Nancy Collins | Z56: {=IFERROR(INDEX(Data_Cleaning!$F$2:$F$251,SMALL(IF(Data_Cleaning!$G$2:$G$251=$X5,ROW(Data_Cleaning!$G$2:$G$251)-ROW(Data_Cleaning!$G$2)+1),49)),"")} -> Headphones | AA56: {=IFERROR(INDEX(Data_Cleaning!$N$2:$N$251,SMALL(IF(Data_Cleaning!$G$2:$G$251=$X5,ROW(Data_Cleaning!$G$2:$G$251)-ROW(Data_Cleaning!$G$2)+1),49)),"")} -> 449.97
W57: {=IFERROR(INDEX(Data_Cleaning!$A$2:$A$251,SMALL(IF(Data_Cleaning!$G$2:$G$251=$X5,ROW(Data_Cleaning!$G$2:$G$251)-ROW(Data_Cleaning!$G$2)+1),50)),"")} -> TRX0037 | X57: {=IFERROR(INDEX(Data_Cleaning!$B$2:$B$251,SMALL(IF(Data_Cleaning!$G$2:$G$251=$X5,ROW(Data_Cleaning!$G$2:$G$251)-ROW(Data_Cleaning!$G$2)+1),50)),"")} -> 45528 | Y57: {=IFERROR(INDEX(Data_Cleaning!$D$2:$D$251,SMALL(IF(Data_Cleaning!$G$2:$G$251=$X5,ROW(Data_Cleaning!$G$2:$G$251)-ROW(Data_Cleaning!$G$2)+1),50)),"")} -> Harry Morgan | Z57: {=IFERROR(INDEX(Data_Cleaning!$F$2:$F$251,SMALL(IF(Data_Cleaning!$G$2:$G$251=$X5,ROW(Data_Cleaning!$G$2:$G$251)-ROW(Data_Cleaning!$G$2)+1),50)),"")} -> Monitor | AA57: {=IFERROR(INDEX(Data_Cleaning!$N$2:$N$251,SMALL(IF(Data_Cleaning!$G$2:$G$251=$X5,ROW(Data_Cleaning!$G$2:$G$251)-ROW(Data_Cleaning!$G$2)+1),50)),"")} -> 499.98
W58: {=IFERROR(INDEX(Data_Cleaning!$A$2:$A$251,SMALL(IF(Data_Cleaning!$G$2:$G$251=$X5,ROW(Data_Cleaning!$G$2:$G$251)-ROW(Data_Cleaning!$G$2)+1),51)),"")} -> TRX0058 | X58: {=IFERROR(INDEX(Data_Cleaning!$B$2:$B$251,SMALL(IF(Data_Cleaning!$G$2:$G$251=$X5,ROW(Data_Cleaning!$G$2:$G$251)-ROW(Data_Cleaning!$G$2)+1),51)),"")} -> 45532 | Y58: {=IFERROR(INDEX(Data_Cleaning!$D$2:$D$251,SMALL(IF(Data_Cleaning!$G$2:$G$251=$X5,ROW(Data_Cleaning!$G$2:$G$251)-ROW(Data_Cleaning!$G$2)+1),51)),"")} -> Gerald Murphy | Z58: {=IFERROR(INDEX(Data_Cleaning!$F$2:$F$251,SMALL(IF(Data_Cleaning!$G$2:$G$251=$X5,ROW(Data_Cleaning!$G$2:$G$251)-ROW(Data_Cleaning!$G$2)+1),51)),"")} -> Smartphone | AA58: {=IFERROR(INDEX(Data_Cleaning!$N$2:$N$251,SMALL(IF(Data_Cleaning!$G$2:$G$251=$X5,ROW(Data_Cleaning!$G$2:$G$251)-ROW(Data_Cleaning!$G$2)+1),51)),"")} -> 699.99
W59: {=IFERROR(INDEX(Data_Cleaning!$A$2:$A$251,SMALL(IF(Data_Cleaning!$G$2:$G$251=$X5,ROW(Data_Cleaning!$G$2:$G$251)-ROW(Data_Cleaning!$G$2)+1),52)),"")} -> TRX0170 | X59: {=IFERROR(INDEX(Data_Cleaning!$B$2:$B$251,SMALL(IF(Data_Cleaning!$G$2:$G$251=$X5,ROW(Data_Cleaning!$G$2:$G$251)-ROW(Data_Cleaning!$G$2)+1),52)),"")} -> 45532 | Y59: {=IFERROR(INDEX(Data_Cleaning!$D$2:$D$251,SMALL(IF(Data_Cleaning!$G$2:$G$251=$X5,ROW(Data_Cleaning!$G$2:$G$251)-ROW(Data_Cleaning!$G$2)+1),52)),"")} -> Carol Evans | Z59: {=IFERROR(INDEX(Data_Cleaning!$F$2:$F$251,SMALL(IF(Data_Cleaning!$G$2:$G$251=$X5,ROW(Data_Cleaning!$G$2:$G$251)-ROW(Data_Cleaning!$G$2)+1),52)),"")} -> Headphones | AA59: {=IFERROR(INDEX(Data_Cleaning!$N$2:$N$251,SMALL(IF(Data_Cleaning!$G$2:$G$251=$X5,ROW(Data_Cleaning!$G$2:$G$251)-ROW(Data_Cleaning!$G$2)+1),52)),"")} -> 449.97
W60: {=IFERROR(INDEX(Data_Cleaning!$A$2:$A$251,SMALL(IF(Data_Cleaning!$G$2:$G$251=$X5,ROW(Data_Cleaning!$G$2:$G$251)-ROW(Data_Cleaning!$G$2)+1),53)),"")} -> TRX0248 | X60: {=IFERROR(INDEX(Data_Cleaning!$B$2:$B$251,SMALL(IF(Data_Cleaning!$G$2:$G$251=$X5,ROW(Data_Cleaning!$G$2:$G$251)-ROW(Data_Cleaning!$G$2)+1),53)),"")} -> 45534 | Y60: {=IFERROR(INDEX(Data_Cleaning!$D$2:$D$251,SMALL(IF(Data_Cleaning!$G$2:$G$251=$X5,ROW(Data_Cleaning!$G$2:$G$251)-ROW(Data_Cleaning!$G$2)+1),53)),"")} -> Sandra Phillips | Z60: {=IFERROR(INDEX(Data_Cleaning!$F$2:$F$251,SMALL(IF(Data_Cleaning!$G$2:$G$251=$X5,ROW(Data_Cleaning!$G$2:$G$251)-ROW(Data_Cleaning!$G$2)+1),53)),"")} -> Smartphone | AA60: {=IFERROR(INDEX(Data_Cleaning!$N$2:$N$251,SMALL(IF(Data_Cleaning!$G$2:$G$251=$X5,ROW(Data_Cleaning!$G$2:$G$251)-ROW(Data_Cleaning!$G$2)+1),53)),"")} -> 1399.98
W61: {=IFERROR(INDEX(Data_Cleaning!$A$2:$A$251,SMALL(IF(Data_Cleaning!$G$2:$G$251=$X5,ROW(Data_Cleaning!$G$2:$G$251)-ROW(Data_Cleaning!$G$2)+1),54)),"")} -> TRX0099 | X61: {=IFERROR(INDEX(Data_Cleaning!$B$2:$B$251,SMALL(IF(Data_Cleaning!$G$2:$G$251=$X5,ROW(Data_Cleaning!$G$2:$G$251)-ROW(Data_Cleaning!$G$2)+1),54)),"")} -> 45537 | Y61: {=IFERROR(INDEX(Data_Cleaning!$D$2:$D$251,SMALL(IF(Data_Cleaning!$G$2:$G$251=$X5,ROW(Data_Cleaning!$G$2:$G$251)-ROW(Data_Cleaning!$G$2)+1),54)),"")} -> Carol Evans | Z61: {=IFERROR(INDEX(Data_Cleaning!$F$2:$F$251,SMALL(IF(Data_Cleaning!$G$2:$G$251=$X5,ROW(Data_Cleaning!$G$2:$G$251)-ROW(Data_Cleaning!$G$2)+1),54)),"")} -> Monitor | AA61: {=IFERROR(INDEX(Data_Cleaning!$N$2:$N$251,SMALL(IF(Data_Cleaning!$G$2:$G$251=$X5,ROW(Data_Cleaning!$G$2:$G$251)-ROW(Data_Cleaning!$G$2)+1),54)),"")} -> 249.99
W62: {=IFERROR(INDEX(Data_Cleaning!$A$2:$A$251,SMALL(IF(Data_Cleaning!$G$2:$G$251=$X5,ROW(Data_Cleaning!$G$2:$G$251)-ROW(Data_Cleaning!$G$2)+1),55)),"")} -> TRX0074 | X62: {=IFERROR(INDEX(Data_Cleaning!$B$2:$B$251,SMALL(IF(Data_Cleaning!$G$2:$G$251=$X5,ROW(Data_Cleaning!$G$2:$G$251)-ROW(Data_Cleaning!$G$2)+1),55)),"")} -> 45537 | Y62: {=IFERROR(INDEX(Data_Cleaning!$D$2:$D$251,SMALL(IF(Data_Cleaning!$G$2:$G$251=$X5,ROW(Data_Cleaning!$G$2:$G$251)-ROW(Data_Cleaning!$G$2)+1),55)),"")} -> Paul Baker | Z62: {=IFERROR(INDEX(Data_Cleaning!$F$2:$F$251,SMALL(IF(Data_Cleaning!$G$2:$G$251=$X5,ROW(Data_Cleaning!$G$2:$G$251)-ROW(Data_Cleaning!$G$2)+1),55)),"")} -> Monitor | AA62: {=IFERROR(INDEX(Data_Cleaning!$N$2:$N$251,SMALL(IF(Data_Cleaning!$G$2:$G$251=$X5,ROW(Data_Cleaning!$G$2:$G$251)-ROW(Data_Cleaning!$G$2)+1),55)),"")} -> 249.99
W63: {=IFERROR(INDEX(Data_Cleaning!$A$2:$A$251,SMALL(IF(Data_Cleaning!$G$2:$G$251=$X5,ROW(Data_Cleaning!$G$2:$G$251)-ROW(Data_Cleaning!$G$2)+1),56)),"")} -> TRX0225 | X63: {=IFERROR(INDEX(Data_Cleaning!$B$2:$B$251,SMALL(IF(Data_Cleaning!$G$2:$G$251=$X5,ROW(Data_Cleaning!$G$2:$G$251)-ROW(Data_Cleaning!$G$2)+1),56)),"")} -> 45538 | Y63: {=IFERROR(INDEX(Data_Cleaning!$D$2:$D$251,SMALL(IF(Data_Cleaning!$G$2:$G$251=$X5,ROW(Data_Cleaning!$G$2:$G$251)-ROW(Data_Cleaning!$G$2)+1),56)),"")} -> Lawrence Reed | Z63: {=IFERROR(INDEX(Data_Cleaning!$F$2:$F$251,SMALL(IF(Data_Cleaning!$G$2:$G$251=$X5,ROW(Data_Cleaning!$G$2:$G$251)-ROW(Data_Cleaning!$G$2)+1),56)),"")} -> Smartphone | AA63: {=IFERROR(INDEX(Data_Cleaning!$N$2:$N$251,SMALL(IF(Data_Cleaning!$G$2:$G$251=$X5,ROW(Data_Cleaning!$G$2:$G$251)-ROW(Data_Cleaning!$G$2)+1),56)),"")} -> 1399.98
W64: {=IFERROR(INDEX(Data_Cleaning!$A$2:$A$251,SMALL(IF(Data_Cleaning!$G$2:$G$251=$X5,ROW(Data_Cleaning!$G$2:$G$251)-ROW(Data_Cleaning!$G$2)+1),57)),"")} -> TRX0211 | X64: {=IFERROR(INDEX(Data_Cleaning!$B$2:$B$251,SMALL(IF(Data_Cleaning!$G$2:$G$251=$X5,ROW(Data_Cleaning!$G$2:$G$251)-ROW(Data_Cleaning!$G$2)+1),57)),"")} -> 45548 | Y64: {=IFERROR(INDEX(Data_Cleaning!$D$2:$D$251,SMALL(IF(Data_Cleaning!$G$2:$G$251=$X5,ROW(Data_Cleaning!$G$2:$G$251)-ROW(Data_Cleaning!$G$2)+1),57)),"")} -> Kathleen Bennett | Z64: {=IFERROR(INDEX(Data_Cleaning!$F$2:$F$251,SMALL(IF(Data_Cleaning!$G$2:$G$251=$X5,ROW(Data_Cleaning!$G$2:$G$251)-ROW(Data_Cleaning!$G$2)+1),57)),"")} -> Keyboard | AA64: {=IFERROR(INDEX(Data_Cleaning!$N$2:$N$251,SMALL(IF(Data_Cleaning!$G$2:$G$251=$X5,ROW(Data_Cleaning!$G$2:$G$251)-ROW(Data_Cleaning!$G$2)+1),57)),"")} -> 179.98
W65: {=IFERROR(INDEX(Data_Cleaning!$A$2:$A$251,SMALL(IF(Data_Cleaning!$G$2:$G$251=$X5,ROW(Data_Cleaning!$G$2:$G$251)-ROW(Data_Cleaning!$G$2)+1),58)),"")} -> TRX0005 | X65: {=IFERROR(INDEX(Data_Cleaning!$B$2:$B$251,SMALL(IF(Data_Cleaning!$G$2:$G$251=$X5,ROW(Data_Cleaning!$G$2:$G$251)-ROW(Data_Cleaning!$G$2)+1),58)),"")} -> 45550 | Y65: {=IFERROR(INDEX(Data_Cleaning!$D$2:$D$251,SMALL(IF(Data_Cleaning!$G$2:$G$251=$X5,ROW(Data_Cleaning!$G$2:$G$251)-ROW(Data_Cleaning!$G$2)+1),58)),"")} -> Ruth Brooks | Z65: {=IFERROR(INDEX(Data_Cleaning!$F$2:$F$251,SMALL(IF(Data_Cleaning!$G$2:$G$251=$X5,ROW(Data_Cleaning!$G$2:$G$251)-ROW(Data_Cleaning!$G$2)+1),58)),"")} -> Headphones | AA65: {=IFERROR(INDEX(Data_Cleaning!$N$2:$N$251,SMALL(IF(Data_Cleaning!$G$2:$G$251=$X5,ROW(Data_Cleaning!$G$2:$G$251)-ROW(Data_Cleaning!$G$2)+1),58)),"")} -> 599.96
W66: {=IFERROR(INDEX(Data_Cleaning!$A$2:$A$251,SMALL(IF(Data_Cleaning!$G$2:$G$251=$X5,ROW(Data_Cleaning!$G$2:$G$251)-ROW(Data_Cleaning!$G$2)+1),59)),"")} -> TRX0195 | X66: {=IFERROR(INDEX(Data_Cleaning!$B$2:$B$251,SMALL(IF(Data_Cleaning!$G$2:$G$251=$X5,ROW(Data_Cleaning!$G$2:$G$251)-ROW(Data_Cleaning!$G$2)+1),59)),"")} -> 45551 | Y66: {=IFERROR(INDEX(Data_Cleaning!$D$2:$D$251,SMALL(IF(Data_Cleaning!$G$2:$G$251=$X5,ROW(Data_Cleaning!$G$2:$G$251)-ROW(Data_Cleaning!$G$2)+1),59)),"")} -> Karen Hill | Z66: {=IFERROR(INDEX(Data_Cleaning!$F$2:$F$251,SMALL(IF(Data_Cleaning!$G$2:$G$251=$X5,ROW(Data_Cleaning!$G$2:$G$251)-ROW(Data_Cleaning!$G$2)+1),59)),"")} -> Monitor | AA66: {=IFERROR(INDEX(Data_Cleaning!$N$2:$N$251,SMALL(IF(Data_Cleaning!$G$2:$G$251=$X5,ROW(Data_Cleaning!$G$2:$G$251)-ROW(Data_Cleaning!$G$2)+1),59)),"")} -> 499.98
W67: {=IFERROR(INDEX(Data_Cleaning!$A$2:$A$251,SMALL(IF(Data_Cleaning!$G$2:$G$251=$X5,ROW(Data_Cleaning!$G$2:$G$251)-ROW(Data_Cleaning!$G$2)+1),60)),"")} -> TRX0077 | X67: {=IFERROR(INDEX(Data_Cleaning!$B$2:$B$251,SMALL(IF(Data_Cleaning!$G$2:$G$251=$X5,ROW(Data_Cleaning!$G$2:$G$251)-ROW(Data_Cleaning!$G$2)+1),60)),"")} -> 45554 | Y67: {=IFERROR(INDEX(Data_Cleaning!$D$2:$D$251,SMALL(IF(Data_Cleaning!$G$2:$G$251=$X5,ROW(Data_Cleaning!$G$2:$G$251)-ROW(Data_Cleaning!$G$2)+1),60)),"")} -> Daniel King | Z67: {=IFERROR(INDEX(Data_Cleaning!$F$2:$F$251,SMALL(IF(Data_Cleaning!$G$2:$G$251=$X5,ROW(Data_Cleaning!$G$2:$G$251)-ROW(Data_Cleaning!$G$2)+1),60)),"")} -> Keyboard | AA67: {=IFERROR(INDEX(Data_Cleaning!$N$2:$N$251,SMALL(IF(Data_Cleaning!$G$2:$G$251=$X5,ROW(Data_Cleaning!$G$2:$G$251)-ROW(Data_Cleaning!$G$2)+1),60)),"")} -> 449.95
W68: {=IFERROR(INDEX(Data_Cleaning!$A$2:$A$251,SMALL(IF(Data_Cleaning!$G$2:$G$251=$X5,ROW(Data_Cleaning!$G$2:$G$251)-ROW(Data_Cleaning!$G$2)+1),61)),"")} -> TRX0111 | X68: {=IFERROR(INDEX(Data_Cleaning!$B$2:$B$251,SMALL(IF(Data_Cleaning!$G$2:$G$251=$X5,ROW(Data_Cleaning!$G$2:$G$251)-ROW(Data_Cleaning!$G$2)+1),61)),"")} -> 45554 | Y68: {=IFERROR(INDEX(Data_Cleaning!$D$2:$D$251,SMALL(IF(Data_Cleaning!$G$2:$G$251=$X5,ROW(Data_Cleaning!$G$2:$G$251)-ROW(Data_Cleaning!$G$2)+1),61)),"")} -> William White | Z68: {=IFERROR(INDEX(Data_Cleaning!$F$2:$F$251,SMALL(IF(Data_Cleaning!$G$2:$G$251=$X5,ROW(Data_Cleaning!$G$2:$G$251)-ROW(Data_Cleaning!$G$2)+1),61)),"")} -> Headphones | AA68: {=IFERROR(INDEX(Data_Cleaning!$N$2:$N$251,SMALL(IF(Data_Cleaning!$G$2:$G$251=$X5,ROW(Data_Cleaning!$G$2:$G$251)-ROW(Data_Cleaning!$G$2)+1),61)),"")} -> 149.99
W69: {=IFERROR(INDEX(Data_Cleaning!$A$2:$A$251,SMALL(IF(Data_Cleaning!$G$2:$G$251=$X5,ROW(Data_Cleaning!$G$2:$G$251)-ROW(Data_Cleaning!$G$2)+1),62)),"")} -> TRX0123 | X69: {=IFERROR(INDEX(Data_Cleaning!$B$2:$B$251,SMALL(IF(Data_Cleaning!$G$2:$G$251=$X5,ROW(Data_Cleaning!$G$2:$G$251)-ROW(Data_Cleaning!$G$2)+1),62)),"")} -> 45554 | Y69: {=IFERROR(INDEX(Data_Cleaning!$D$2:$D$251,SMALL(IF(Data_Cleaning!$G$2:$G$251=$X5,ROW(Data_Cleaning!$G$2:$G$251)-ROW(Data_Cleaning!$G$2)+1),62)),"")} -> Peter Richardson | Z69: {=IFERROR(INDEX(Data_Cleaning!$F$2:$F$251,SMALL(IF(Data_Cleaning!$G$2:$G$251=$X5,ROW(Data_Cleaning!$G$2:$G$251)-ROW(Data_Cleaning!$G$2)+1),62)),"")} -> Smartphone | AA69: {=IFERROR(INDEX(Data_Cleaning!$N$2:$N$251,SMALL(IF(Data_Cleaning!$G$2:$G$251=$X5,ROW(Data_Cleaning!$G$2:$G$251)-ROW(Data_Cleaning!$G$2)+1),62)),"")} -> 2799.96
W70: {=IFERROR(INDEX(Data_Cleaning!$A$2:$A$251,SMALL(IF(Data_Cleaning!$G$2:$G$251=$X5,ROW(Data_Cleaning!$G$2:$G$251)-ROW(Data_Cleaning!$G$2)+1),63)),"")} -> TRX0177 | X70: {=IFERROR(INDEX(Data_Cleaning!$B$2:$B$251,SMALL(IF(Data_Cleaning!$G$2:$G$251=$X5,ROW(Data_Cleaning!$G$2:$G$251)-ROW(Data_Cleaning!$G$2)+1),63)),"")} -> 45559 | Y70: {=IFERROR(INDEX(Data_Cleaning!$D$2:$D$251,SMALL(IF(Data_Cleaning!$G$2:$G$251=$X5,ROW(Data_Cleaning!$G$2:$G$251)-ROW(Data_Cleaning!$G$2)+1),63)),"")} -> Sandra Phillips | Z70: {=IFERROR(INDEX(Data_Cleaning!$F$2:$F$251,SMALL(IF(Data_Cleaning!$G$2:$G$251=$X5,ROW(Data_Cleaning!$G$2:$G$251)-ROW(Data_Cleaning!$G$2)+1),63)),"")} -> Laptop | AA70: {=IFERROR(INDEX(Data_Cleaning!$N$2:$N$251,SMALL(IF(Data_Cleaning!$G$2:$G$251=$X5,ROW(Data_Cleaning!$G$2:$G$251)-ROW(Data_Cleaning!$G$2)+1),63)),"")} -> 2699.97
W71: {=IFERROR(INDEX(Data_Cleaning!$A$2:$A$251,SMALL(IF(Data_Cleaning!$G$2:$G$251=$X5,ROW(Data_Cleaning!$G$2:$G$251)-ROW(Data_Cleaning!$G$2)+1),64)),"")} -> TRX0203 | X71: {=IFERROR(INDEX(Data_Cleaning!$B$2:$B$251,SMALL(IF(Data_Cleaning!$G$2:$G$251=$X5,ROW(Data_Cleaning!$G$2:$G$251)-ROW(Data_Cleaning!$G$2)+1),64)),"")} -> 45572 | Y71: {=IFERROR(INDEX(Data_Cleaning!$D$2:$D$251,SMALL(IF(Data_Cleaning!$G$2:$G$251=$X5,ROW(Data_Cleaning!$G$2:$G$251)-ROW(Data_Cleaning!$G$2)+1),64)),"")} -> Sandra Phillips | Z71: {=IFERROR(INDEX(Data_Cleaning!$F$2:$F$251,SMALL(IF(Data_Cleaning!$G$2:$G$251=$X5,ROW(Data_Cleaning!$G$2:$G$251)-ROW(Data_Cleaning!$G$2)+1),64)),"")} -> Headphones | AA71: {=IFERROR(INDEX(Data_Cleaning!$N$2:$N$251,SMALL(IF(Data_Cleaning!$G$2:$G$251=$X5,ROW(Data_Cleaning!$G$2:$G$251)-ROW(Data_Cleaning!$G$2)+1),64)),"")} -> 599.96
W72: {=IFERROR(INDEX(Data_Cleaning!$A$2:$A$251,SMALL(IF(Data_Cleaning!$G$2:$G$251=$X5,ROW(Data_Cleaning!$G$2:$G$251)-ROW(Data_Cleaning!$G$2)+1),65)),"")} -> TRX0055 | X72: {=IFERROR(INDEX(Data_Cleaning!$B$2:$B$251,SMALL(IF(Data_Cleaning!$G$2:$G$251=$X5,ROW(Data_Cleaning!$G$2:$G$251)-ROW(Data_Cleaning!$G$2)+1),65)),"")} -> 45573 | Y72: {=IFERROR(INDEX(Data_Cleaning!$D$2:$D$251,SMALL(IF(Data_Cleaning!$G$2:$G$251=$X5,ROW(Data_Cleaning!$G$2:$G$251)-ROW(Data_Cleaning!$G$2)+1),65)),"")} -> Elizabeth Hall | Z72: {=IFERROR(INDEX(Data_Cleaning!$F$2:$F$251,SMALL(IF(Data_Cleaning!$G$2:$G$251=$X5,ROW(Data_Cleaning!$G$2:$G$251)-ROW(Data_Cleaning!$G$2)+1),65)),"")} -> Smartphone | AA72: {=IFERROR(INDEX(Data_Cleaning!$N$2:$N$251,SMALL(IF(Data_Cleaning!$G$2:$G$251=$X5,ROW(Data_Cleaning!$G$2:$G$251)-ROW(Data_Cleaning!$G$2)+1),65)),"")} -> 1399.98
W73: {=IFERROR(INDEX(Data_Cleaning!$A$2:$A$251,SMALL(IF(Data_Cleaning!$G$2:$G$251=$X5,ROW(Data_Cleaning!$G$2:$G$251)-ROW(Data_Cleaning!$G$2)+1),66)),"")} -> TRX0158 | X73: {=IFERROR(INDEX(Data_Cleaning!$B$2:$B$251,SMALL(IF(Data_Cleaning!$G$2:$G$251=$X5,ROW(Data_Cleaning!$G$2:$G$251)-ROW(Data_Cleaning!$G$2)+1),66)),"")} -> 45579 | Y73: {=IFERROR(INDEX(Data_Cleaning!$D$2:$D$251,SMALL(IF(Data_Cleaning!$G$2:$G$251=$X5,ROW(Data_Cleaning!$G$2:$G$251)-ROW(Data_Cleaning!$G$2)+1),66)),"")} -> George Adams | Z73: {=IFERROR(INDEX(Data_Cleaning!$F$2:$F$251,SMALL(IF(Data_Cleaning!$G$2:$G$251=$X5,ROW(Data_Cleaning!$G$2:$G$251)-ROW(Data_Cleaning!$G$2)+1),66)),"")} -> Laptop | AA73: {=IFERROR(INDEX(Data_Cleaning!$N$2:$N$251,SMALL(IF(Data_Cleaning!$G$2:$G$251=$X5,ROW(Data_Cleaning!$G$2:$G$251)-ROW(Data_Cleaning!$G$2)+1),66)),"")} -> 2699.97
W74: {=IFERROR(INDEX(Data_Cleaning!$A$2:$A$251,SMALL(IF(Data_Cleaning!$G$2:$G$251=$X5,ROW(Data_Cleaning!$G$2:$G$251)-ROW(Data_Cleaning!$G$2)+1),67)),"")} -> TRX0173 | X74: {=IFERROR(INDEX(Data_Cleaning!$B$2:$B$251,SMALL(IF(Data_Cleaning!$G$2:$G$251=$X5,ROW(Data_Cleaning!$G$2:$G$251)-ROW(Data_Cleaning!$G$2)+1),67)),"")} -> 45581 | Y74: {=IFERROR(INDEX(Data_Cleaning!$D$2:$D$251,SMALL(IF(Data_Cleaning!$G$2:$G$251=$X5,ROW(Data_Cleaning!$G$2:$G$251)-ROW(Data_Cleaning!$G$2)+1),67)),"")} -> Barbara Young | Z74: {=IFERROR(INDEX(Data_Cleaning!$F$2:$F$251,SMALL(IF(Data_Cleaning!$G$2:$G$251=$X5,ROW(Data_Cleaning!$G$2:$G$251)-ROW(Data_Cleaning!$G$2)+1),67)),"")} -> Smartphone | AA74: {=IFERROR(INDEX(Data_Cleaning!$N$2:$N$251,SMALL(IF(Data_Cleaning!$G$2:$G$251=$X5,ROW(Data_Cleaning!$G$2:$G$251)-ROW(Data_Cleaning!$G$2)+1),67)),"")} -> 3499.95
W75: {=IFERROR(INDEX(Data_Cleaning!$A$2:$A$251,SMALL(IF(Data_Cleaning!$G$2:$G$251=$X5,ROW(Data_Cleaning!$G$2:$G$251)-ROW(Data_Cleaning!$G$2)+1),68)),"")} -> TRX0034 | X75: {=IFERROR(INDEX(Data_Cleaning!$B$2:$B$251,SMALL(IF(Data_Cleaning!$G$2:$G$251=$X5,ROW(Data_Cleaning!$G$2:$G$251)-ROW(Data_Cleaning!$G$2)+1),68)),"")} -> 45581 | Y75: {=IFERROR(INDEX(Data_Cleaning!$D$2:$D$251,SMALL(IF(Data_Cleaning!$G$2:$G$251=$X5,ROW(Data_Cleaning!$G$2:$G$251)-ROW(Data_Cleaning!$G$2)+1),68)),"")} -> Raymond Ross | Z75: {=IFERROR(INDEX(Data_Cleaning!$F$2:$F$251,SMALL(IF(Data_Cleaning!$G$2:$G$251=$X5,ROW(Data_Cleaning!$G$2:$G$251)-ROW(Data_Cleaning!$G$2)+1),68)),"")} -> Smartphone | AA75: {=IFERROR(INDEX(Data_Cleaning!$N$2:$N$251,SMALL(IF(Data_Cleaning!$G$2:$G$251=$X5,ROW(Data_Cleaning!$G$2:$G$251)-ROW(Data_Cleaning!$G$2)+1),68)),"")} -> 2799.96
W76: {=IFERROR(INDEX(Data_Cleaning!$A$2:$A$251,SMALL(IF(Data_Cleaning!$G$2:$G$251=$X5,ROW(Data_Cleaning!$G$2:$G$251)-ROW(Data_Cleaning!$G$2)+1),69)),"")} -> TRX0189 | X76: {=IFERROR(INDEX(Data_Cleaning!$B$2:$B$251,SMALL(IF(Data_Cleaning!$G$2:$G$251=$X5,ROW(Data_Cleaning!$G$2:$G$251)-ROW(Data_Cleaning!$G$2)+1),69)),"")} -> 45581 | Y76: {=IFERROR(INDEX(Data_Cleaning!$D$2:$D$251,SMALL(IF(Data_Cleaning!$G$2:$G$251=$X5,ROW(Data_Cleaning!$G$2:$G$251)-ROW(Data_Cleaning!$G$2)+1),69)),"")} -> Sharon Butler | Z76: {=IFERROR(INDEX(Data_Cleaning!$F$2:$F$251,SMALL(IF(Data_Cleaning!$G$2:$G$251=$X5,ROW(Data_Cleaning!$G$2:$G$251)-ROW(Data_Cleaning!$G$2)+1),69)),"")} -> Laptop | AA76: {=IFERROR(INDEX(Data_Cleaning!$N$2:$N$251,SMALL(IF(Data_Cleaning!$G$2:$G$251=$X5,ROW(Data_Cleaning!$G$2:$G$251)-ROW(Data_Cleaning!$G$2)+1),69)),"")} -> 899.99
W77: {=IFERROR(INDEX(Data_Cleaning!$A$2:$A$251,SMALL(IF(Data_Cleaning!$G$2:$G$251=$X5,ROW(Data_Cleaning!$G$2:$G$251)-ROW(Data_Cleaning!$G$2)+1),70)),"")} -> TRX0190 | X77: {=IFERROR(INDEX(Data_Cleaning!$B$2:$B$251,SMALL(IF(Data_Cleaning!$G$2:$G$251=$X5,ROW(Data_Cleaning!$G$2:$G$251)-ROW(Data_Cleaning!$G$2)+1),70)),"")} -> 45583 | Y77: {=IFERROR(INDEX(Data_Cleaning!$D$2:$D$251,SMALL(IF(Data_Cleaning!$G$2:$G$251=$X5,ROW(Data_Cleaning!$G$2:$G$251)-ROW(Data_Cleaning!$G$2)+1),70)),"")} -> Lawrence Reed | Z77: {=IFERROR(INDEX(Data_Cleaning!$F$2:$F$251,SMALL(IF(Data_Cleaning!$G$2:$G$251=$X5,ROW(Data_Cleaning!$G$2:$G$251)-ROW(Data_Cleaning!$G$2)+1),70)),"")} -> Headphones | AA77: {=IFERROR(INDEX(Data_Cleaning!$N$2:$N$251,SMALL(IF(Data_Cleaning!$G$2:$G$251=$X5,ROW(Data_Cleaning!$G$2:$G$251)-ROW(Data_Cleaning!$G$2)+1),70)),"")} -> 299.98
W78: {=IFERROR(INDEX(Data_Cleaning!$A$2:$A$251,SMALL(IF(Data_Cleaning!$G$2:$G$251=$X5,ROW(Data_Cleaning!$G$2:$G$251)-ROW(Data_Cleaning!$G$2)+1),71)),"")} -> TRX0079 | X78: {=IFERROR(INDEX(Data_Cleaning!$B$2:$B$251,SMALL(IF(Data_Cleaning!$G$2:$G$251=$X5,ROW(Data_Cleaning!$G$2:$G$251)-ROW(Data_Cleaning!$G$2)+1),71)),"")} -> 45586 | Y78: {=IFERROR(INDEX(Data_Cleaning!$D$2:$D$251,SMALL(IF(Data_Cleaning!$G$2:$G$251=$X5,ROW(Data_Cleaning!$G$2:$G$251)-ROW(Data_Cleaning!$G$2)+1),71)),"")} -> Lawrence Reed | Z78: {=IFERROR(INDEX(Data_Cleaning!$F$2:$F$251,SMALL(IF(Data_Cleaning!$G$2:$G$251=$X5,ROW(Data_Cleaning!$G$2:$G$251)-ROW(Data_Cleaning!$G$2)+1),71)),"")} -> Keyboard | AA78: {=IFERROR(INDEX(Data_Cleaning!$N$2:$N$251,SMALL(IF(Data_Cleaning!$G$2:$G$251=$X5,ROW(Data_Cleaning!$G$2:$G$251)-ROW(Data_Cleaning!$G$2)+1),71)),"")} -> 269.97
W79: {=IFERROR(INDEX(Data_Cleaning!$A$2:$A$251,SMALL(IF(Data_Cleaning!$G$2:$G$251=$X5,ROW(Data_Cleaning!$G$2:$G$251)-ROW(Data_Cleaning!$G$2)+1),72)),"")} -> TRX0095 | X79: {=IFERROR(INDEX(Data_Cleaning!$B$2:$B$251,SMALL(IF(Data_Cleaning!$G$2:$G$251=$X5,ROW(Data_Cleaning!$G$2:$G$251)-ROW(Data_Cleaning!$G$2)+1),72)),"")} -> 45588 | Y79: {=IFERROR(INDEX(Data_Cleaning!$D$2:$D$251,SMALL(IF(Data_Cleaning!$G$2:$G$251=$X5,ROW(Data_Cleaning!$G$2:$G$251)-ROW(Data_Cleaning!$G$2)+1),72)),"")} -> Kathleen Bennett | Z79: {=IFERROR(INDEX(Data_Cleaning!$F$2:$F$251,SMALL(IF(Data_Cleaning!$G$2:$G$251=$X5,ROW(Data_Cleaning!$G$2:$G$251)-ROW(Data_Cleaning!$G$2)+1),72)),"")} -> Headphones | AA79: {=IFERROR(INDEX(Data_Cleaning!$N$2:$N$251,SMALL(IF(Data_Cleaning!$G$2:$G$251=$X5,ROW(Data_Cleaning!$G$2:$G$251)-ROW(Data_Cleaning!$G$2)+1),72)),"")} -> 299.98
W80: {=IFERROR(INDEX(Data_Cleaning!$A$2:$A$251,SMALL(IF(Data_Cleaning!$G$2:$G$251=$X5,ROW(Data_Cleaning!$G$2:$G$251)-ROW(Data_Cleaning!$G$2)+1),73)),"")} -> TRX0009 | X80: {=IFERROR(INDEX(Data_Cleaning!$B$2:$B$251,SMALL(IF(Data_Cleaning!$G$2:$G$251=$X5,ROW(Data_Cleaning!$G$2:$G$251)-ROW(Data_Cleaning!$G$2)+1),73)),"")} -> 45588 | Y80: {=IFERROR(INDEX(Data_Cleaning!$D$2:$D$251,SMALL(IF(Data_Cleaning!$G$2:$G$251=$X5,ROW(Data_Cleaning!$G$2:$G$251)-ROW(Data_Cleaning!$G$2)+1),73)),"")} -> Sarah Davis | Z80: {=IFERROR(INDEX(Data_Cleaning!$F$2:$F$251,SMALL(IF(Data_Cleaning!$G$2:$G$251=$X5,ROW(Data_Cleaning!$G$2:$G$251)-ROW(Data_Cleaning!$G$2)+1),73)),"")} -> Smartphone | AA80: {=IFERROR(INDEX(Data_Cleaning!$N$2:$N$251,SMALL(IF(Data_Cleaning!$G$2:$G$251=$X5,ROW(Data_Cleaning!$G$2:$G$251)-ROW(Data_Cleaning!$G$2)+1),73)),"")} -> 1399.98
W81: {=IFERROR(INDEX(Data_Cleaning!$A$2:$A$251,SMALL(IF(Data_Cleaning!$G$2:$G$251=$X5,ROW(Data_Cleaning!$G$2:$G$251)-ROW(Data_Cleaning!$G$2)+1),74)),"")} -> TRX0167 | X81: {=IFERROR(INDEX(Data_Cleaning!$B$2:$B$251,SMALL(IF(Data_Cleaning!$G$2:$G$251=$X5,ROW(Data_Cleaning!$G$2:$G$251)-ROW(Data_Cleaning!$G$2)+1),74)),"")} -> 45589 | Y81: {=IFERROR(INDEX(Data_Cleaning!$D$2:$D$251,SMALL(IF(Data_Cleaning!$G$2:$G$251=$X5,ROW(Data_Cleaning!$G$2:$G$251)-ROW(Data_Cleaning!$G$2)+1),74)),"")} -> Betty Campbell | Z81: {=IFERROR(INDEX(Data_Cleaning!$F$2:$F$251,SMALL(IF(Data_Cleaning!$G$2:$G$251=$X5,ROW(Data_Cleaning!$G$2:$G$251)-ROW(Data_Cleaning!$G$2)+1),74)),"")} -> Smartphone | AA81: {=IFERROR(INDEX(Data_Cleaning!$N$2:$N$251,SMALL(IF(Data_Cleaning!$G$2:$G$251=$X5,ROW(Data_Cleaning!$G$2:$G$251)-ROW(Data_Cleaning!$G$2)+1),74)),"")} -> 3499.95
W82: {=IFERROR(INDEX(Data_Cleaning!$A$2:$A$251,SMALL(IF(Data_Cleaning!$G$2:$G$251=$X5,ROW(Data_Cleaning!$G$2:$G$251)-ROW(Data_Cleaning!$G$2)+1),75)),"")} -> TRX0153 | X82: {=IFERROR(INDEX(Data_Cleaning!$B$2:$B$251,SMALL(IF(Data_Cleaning!$G$2:$G$251=$X5,ROW(Data_Cleaning!$G$2:$G$251)-ROW(Data_Cleaning!$G$2)+1),75)),"")} -> 45592 | Y82: {=IFERROR(INDEX(Data_Cleaning!$D$2:$D$251,SMALL(IF(Data_Cleaning!$G$2:$G$251=$X5,ROW(Data_Cleaning!$G$2:$G$251)-ROW(Data_Cleaning!$G$2)+1),75)),"")} -> Raymond Ross | Z82: {=IFERROR(INDEX(Data_Cleaning!$F$2:$F$251,SMALL(IF(Data_Cleaning!$G$2:$G$251=$X5,ROW(Data_Cleaning!$G$2:$G$251)-ROW(Data_Cleaning!$G$2)+1),75)),"")} -> Keyboard | AA82: {=IFERROR(INDEX(Data_Cleaning!$N$2:$N$251,SMALL(IF(Data_Cleaning!$G$2:$G$251=$X5,ROW(Data_Cleaning!$G$2:$G$251)-ROW(Data_Cleaning!$G$2)+1),75)),"")} -> 269.97
W83: {=IFERROR(INDEX(Data_Cleaning!$A$2:$A$251,SMALL(IF(Data_Cleaning!$G$2:$G$251=$X5,ROW(Data_Cleaning!$G$2:$G$251)-ROW(Data_Cleaning!$G$2)+1),76)),"")} -> TRX0057 | X83: {=IFERROR(INDEX(Data_Cleaning!$B$2:$B$251,SMALL(IF(Data_Cleaning!$G$2:$G$251=$X5,ROW(Data_Cleaning!$G$2:$G$251)-ROW(Data_Cleaning!$G$2)+1),76)),"")} -> 45597 | Y83: {=IFERROR(INDEX(Data_Cleaning!$D$2:$D$251,SMALL(IF(Data_Cleaning!$G$2:$G$251=$X5,ROW(Data_Cleaning!$G$2:$G$251)-ROW(Data_Cleaning!$G$2)+1),76)),"")} -> Paul Baker | Z83: {=IFERROR(INDEX(Data_Cleaning!$F$2:$F$251,SMALL(IF(Data_Cleaning!$G$2:$G$251=$X5,ROW(Data_Cleaning!$G$2:$G$251)-ROW(Data_Cleaning!$G$2)+1),76)),"")} -> Monitor | AA83: {=IFERROR(INDEX(Data_Cleaning!$N$2:$N$251,SMALL(IF(Data_Cleaning!$G$2:$G$251=$X5,ROW(Data_Cleaning!$G$2:$G$251)-ROW(Data_Cleaning!$G$2)+1),76)),"")} -> 1249.95
W84: {=IFERROR(INDEX(Data_Cleaning!$A$2:$A$251,SMALL(IF(Data_Cleaning!$G$2:$G$251=$X5,ROW(Data_Cleaning!$G$2:$G$251)-ROW(Data_Cleaning!$G$2)+1),77)),"")} -> TRX0060 | X84: {=IFERROR(INDEX(Data_Cleaning!$B$2:$B$251,SMALL(IF(Data_Cleaning!$G$2:$G$251=$X5,ROW(Data_Cleaning!$G$2:$G$251)-ROW(Data_Cleaning!$G$2)+1),77)),"")} -> 45603 | Y84: {=IFERROR(INDEX(Data_Cleaning!$D$2:$D$251,SMALL(IF(Data_Cleaning!$G$2:$G$251=$X5,ROW(Data_Cleaning!$G$2:$G$251)-ROW(Data_Cleaning!$G$2)+1),77)),"")} -> Patricia Moore | Z84: {=IFERROR(INDEX(Data_Cleaning!$F$2:$F$251,SMALL(IF(Data_Cleaning!$G$2:$G$251=$X5,ROW(Data_Cleaning!$G$2:$G$251)-ROW(Data_Cleaning!$G$2)+1),77)),"")} -> Keyboard | AA84: {=IFERROR(INDEX(Data_Cleaning!$N$2:$N$251,SMALL(IF(Data_Cleaning!$G$2:$G$251=$X5,ROW(Data_Cleaning!$G$2:$G$251)-ROW(Data_Cleaning!$G$2)+1),77)),"")} -> 269.97
W85: {=IFERROR(INDEX(Data_Cleaning!$A$2:$A$251,SMALL(IF(Data_Cleaning!$G$2:$G$251=$X5,ROW(Data_Cleaning!$G$2:$G$251)-ROW(Data_Cleaning!$G$2)+1),78)),"")} -> TRX0090 | X85: {=IFERROR(INDEX(Data_Cleaning!$B$2:$B$251,SMALL(IF(Data_Cleaning!$G$2:$G$251=$X5,ROW(Data_Cleaning!$G$2:$G$251)-ROW(Data_Cleaning!$G$2)+1),78)),"")} -> 45605 | Y85: {=IFERROR(INDEX(Data_Cleaning!$D$2:$D$251,SMALL(IF(Data_Cleaning!$G$2:$G$251=$X5,ROW(Data_Cleaning!$G$2:$G$251)-ROW(Data_Cleaning!$G$2)+1),78)),"")} -> Margaret Wright | Z85: {=IFERROR(INDEX(Data_Cleaning!$F$2:$F$251,SMALL(IF(Data_Cleaning!$G$2:$G$251=$X5,ROW(Data_Cleaning!$G$2:$G$251)-ROW(Data_Cleaning!$G$2)+1),78)),"")} -> Monitor | AA85: {=IFERROR(INDEX(Data_Cleaning!$N$2:$N$251,SMALL(IF(Data_Cleaning!$G$2:$G$251=$X5,ROW(Data_Cleaning!$G$2:$G$251)-ROW(Data_Cleaning!$G$2)+1),78)),"")} -> 249.99
W86: {=IFERROR(INDEX(Data_Cleaning!$A$2:$A$251,SMALL(IF(Data_Cleaning!$G$2:$G$251=$X5,ROW(Data_Cleaning!$G$2:$G$251)-ROW(Data_Cleaning!$G$2)+1),79)),"")} -> TRX0035 | X86: {=IFERROR(INDEX(Data_Cleaning!$B$2:$B$251,SMALL(IF(Data_Cleaning!$G$2:$G$251=$X5,ROW(Data_Cleaning!$G$2:$G$251)-ROW(Data_Cleaning!$G$2)+1),79)),"")} -> 45607 | Y86: {=IFERROR(INDEX(Data_Cleaning!$D$2:$D$251,SMALL(IF(Data_Cleaning!$G$2:$G$251=$X5,ROW(Data_Cleaning!$G$2:$G$251)-ROW(Data_Cleaning!$G$2)+1),79)),"")} -> Peter Richardson | Z86: {=IFERROR(INDEX(Data_Cleaning!$F$2:$F$251,SMALL(IF(Data_Cleaning!$G$2:$G$251=$X5,ROW(Data_Cleaning!$G$2:$G$251)-ROW(Data_Cleaning!$G$2)+1),79)),"")} -> Headphones | AA86: {=IFERROR(INDEX(Data_Cleaning!$N$2:$N$251,SMALL(IF(Data_Cleaning!$G$2:$G$251=$X5,ROW(Data_Cleaning!$G$2:$G$251)-ROW(Data_Cleaning!$G$2)+1),79)),"")} -> 449.97
W87: {=IFERROR(INDEX(Data_Cleaning!$A$2:$A$251,SMALL(IF(Data_Cleaning!$G$2:$G$251=$X5,ROW(Data_Cleaning!$G$2:$G$251)-ROW(Data_Cleaning!$G$2)+1),80)),"")} -> TRX0076 | X87: {=IFERROR(INDEX(Data_Cleaning!$B$2:$B$251,SMALL(IF(Data_Cleaning!$G$2:$G$251=$X5,ROW(Data_Cleaning!$G$2:$G$251)-ROW(Data_Cleaning!$G$2)+1),80)),"")} -> 45607 | Y87: {=IFERROR(INDEX(Data_Cleaning!$D$2:$D$251,SMALL(IF(Data_Cleaning!$G$2:$G$251=$X5,ROW(Data_Cleaning!$G$2:$G$251)-ROW(Data_Cleaning!$G$2)+1),80)),"")} -> Patricia Moore | Z87: {=IFERROR(INDEX(Data_Cleaning!$F$2:$F$251,SMALL(IF(Data_Cleaning!$G$2:$G$251=$X5,ROW(Data_Cleaning!$G$2:$G$251)-ROW(Data_Cleaning!$G$2)+1),80)),"")} -> Monitor | AA87: {=IFERROR(INDEX(Data_Cleaning!$N$2:$N$251,SMALL(IF(Data_Cleaning!$G$2:$G$251=$X5,ROW(Data_Cleaning!$G$2:$G$251)-ROW(Data_Cleaning!$G$2)+1),80)),"")} -> 999.96
W88: {=IFERROR(INDEX(Data_Cleaning!$A$2:$A$251,SMALL(IF(Data_Cleaning!$G$2:$G$251=$X5,ROW(Data_Cleaning!$G$2:$G$251)-ROW(Data_Cleaning!$G$2)+1),81)),"")} -> TRX0033 | X88: {=IFERROR(INDEX(Data_Cleaning!$B$2:$B$251,SMALL(IF(Data_Cleaning!$G$2:$G$251=$X5,ROW(Data_Cleaning!$G$2:$G$251)-ROW(Data_Cleaning!$G$2)+1),81)),"")} -> 45613 | Y88: {=IFERROR(INDEX(Data_Cleaning!$D$2:$D$251,SMALL(IF(Data_Cleaning!$G$2:$G$251=$X5,ROW(Data_Cleaning!$G$2:$G$251)-ROW(Data_Cleaning!$G$2)+1),81)),"")} -> Mark Carter | Z88: {=IFERROR(INDEX(Data_Cleaning!$F$2:$F$251,SMALL(IF(Data_Cleaning!$G$2:$G$251=$X5,ROW(Data_Cleaning!$G$2:$G$251)-ROW(Data_Cleaning!$G$2)+1),81)),"")} -> Smartphone | AA88: {=IFERROR(INDEX(Data_Cleaning!$N$2:$N$251,SMALL(IF(Data_Cleaning!$G$2:$G$251=$X5,ROW(Data_Cleaning!$G$2:$G$251)-ROW(Data_Cleaning!$G$2)+1),81)),"")} -> 1399.98
W89: {=IFERROR(INDEX(Data_Cleaning!$A$2:$A$251,SMALL(IF(Data_Cleaning!$G$2:$G$251=$X5,ROW(Data_Cleaning!$G$2:$G$251)-ROW(Data_Cleaning!$G$2)+1),82)),"")} -> TRX0148 | X89: {=IFERROR(INDEX(Data_Cleaning!$B$2:$B$251,SMALL(IF(Data_Cleaning!$G$2:$G$251=$X5,ROW(Data_Cleaning!$G$2:$G$251)-ROW(Data_Cleaning!$G$2)+1),82)),"")} -> 45619 | Y89: {=IFERROR(INDEX(Data_Cleaning!$D$2:$D$251,SMALL(IF(Data_Cleaning!$G$2:$G$251=$X5,ROW(Data_Cleaning!$G$2:$G$251)-ROW(Data_Cleaning!$G$2)+1),82)),"")} -> Sarah Davis | Z89: {=IFERROR(INDEX(Data_Cleaning!$F$2:$F$251,SMALL(IF(Data_Cleaning!$G$2:$G$251=$X5,ROW(Data_Cleaning!$G$2:$G$251)-ROW(Data_Cleaning!$G$2)+1),82)),"")} -> Smartphone | AA89: {=IFERROR(INDEX(Data_Cleaning!$N$2:$N$251,SMALL(IF(Data_Cleaning!$G$2:$G$251=$X5,ROW(Data_Cleaning!$G$2:$G$251)-ROW(Data_Cleaning!$G$2)+1),82)),"")} -> 2099.97
W90: {=IFERROR(INDEX(Data_Cleaning!$A$2:$A$251,SMALL(IF(Data_Cleaning!$G$2:$G$251=$X5,ROW(Data_Cleaning!$G$2:$G$251)-ROW(Data_Cleaning!$G$2)+1),83)),"")} -> TRX0012 | X90: {=IFERROR(INDEX(Data_Cleaning!$B$2:$B$251,SMALL(IF(Data_Cleaning!$G$2:$G$251=$X5,ROW(Data_Cleaning!$G$2:$G$251)-ROW(Data_Cleaning!$G$2)+1),83)),"")} -> 45622 | Y90: {=IFERROR(INDEX(Data_Cleaning!$D$2:$D$251,SMALL(IF(Data_Cleaning!$G$2:$G$251=$X5,ROW(Data_Cleaning!$G$2:$G$251)-ROW(Data_Cleaning!$G$2)+1),83)),"")} -> Douglas Watson | Z90: {=IFERROR(INDEX(Data_Cleaning!$F$2:$F$251,SMALL(IF(Data_Cleaning!$G$2:$G$251=$X5,ROW(Data_Cleaning!$G$2:$G$251)-ROW(Data_Cleaning!$G$2)+1),83)),"")} -> Monitor | AA90: {=IFERROR(INDEX(Data_Cleaning!$N$2:$N$251,SMALL(IF(Data_Cleaning!$G$2:$G$251=$X5,ROW(Data_Cleaning!$G$2:$G$251)-ROW(Data_Cleaning!$G$2)+1),83)),"")} -> 1249.95
W91: {=IFERROR(INDEX(Data_Cleaning!$A$2:$A$251,SMALL(IF(Data_Cleaning!$G$2:$G$251=$X5,ROW(Data_Cleaning!$G$2:$G$251)-ROW(Data_Cleaning!$G$2)+1),84)),"")} -> TRX0094 | X91: {=IFERROR(INDEX(Data_Cleaning!$B$2:$B$251,SMALL(IF(Data_Cleaning!$G$2:$G$251=$X5,ROW(Data_Cleaning!$G$2:$G$251)-ROW(Data_Cleaning!$G$2)+1),84)),"")} -> 45627 | Y91: {=IFERROR(INDEX(Data_Cleaning!$D$2:$D$251,SMALL(IF(Data_Cleaning!$G$2:$G$251=$X5,ROW(Data_Cleaning!$G$2:$G$251)-ROW(Data_Cleaning!$G$2)+1),84)),"")} -> Charles Allen | Z91: {=IFERROR(INDEX(Data_Cleaning!$F$2:$F$251,SMALL(IF(Data_Cleaning!$G$2:$G$251=$X5,ROW(Data_Cleaning!$G$2:$G$251)-ROW(Data_Cleaning!$G$2)+1),84)),"")} -> Monitor | AA91: {=IFERROR(INDEX(Data_Cleaning!$N$2:$N$251,SMALL(IF(Data_Cleaning!$G$2:$G$251=$X5,ROW(Data_Cleaning!$G$2:$G$251)-ROW(Data_Cleaning!$G$2)+1),84)),"")} -> 1249.95
W92: {=IFERROR(INDEX(Data_Cleaning!$A$2:$A$251,SMALL(IF(Data_Cleaning!$G$2:$G$251=$X5,ROW(Data_Cleaning!$G$2:$G$251)-ROW(Data_Cleaning!$G$2)+1),85)),"")} -> TRX0133 | X92: {=IFERROR(INDEX(Data_Cleaning!$B$2:$B$251,SMALL(IF(Data_Cleaning!$G$2:$G$251=$X5,ROW(Data_Cleaning!$G$2:$G$251)-ROW(Data_Cleaning!$G$2)+1),85)),"")} -> 45627 | Y92: {=IFERROR(INDEX(Data_Cleaning!$D$2:$D$251,SMALL(IF(Data_Cleaning!$G$2:$G$251=$X5,ROW(Data_Cleaning!$G$2:$G$251)-ROW(Data_Cleaning!$G$2)+1),85)),"")} -> Joseph Jackson | Z92: {=IFERROR(INDEX(Data_Cleaning!$F$2:$F$251,SMALL(IF(Data_Cleaning!$G$2:$G$251=$X5,ROW(Data_Cleaning!$G$2:$G$251)-ROW(Data_Cleaning!$G$2)+1),85)),"")} -> Headphones | AA92: {=IFERROR(INDEX(Data_Cleaning!$N$2:$N$251,SMALL(IF(Data_Cleaning!$G$2:$G$251=$X5,ROW(Data_Cleaning!$G$2:$G$251)-ROW(Data_Cleaning!$G$2)+1),85)),"")} -> 299.98
W93: {=IFERROR(INDEX(Data_Cleaning!$A$2:$A$251,SMALL(IF(Data_Cleaning!$G$2:$G$251=$X5,ROW(Data_Cleaning!$G$2:$G$251)-ROW(Data_Cleaning!$G$2)+1),86)),"")} -> TRX0201 | X93: {=IFERROR(INDEX(Data_Cleaning!$B$2:$B$251,SMALL(IF(Data_Cleaning!$G$2:$G$251=$X5,ROW(Data_Cleaning!$G$2:$G$251)-ROW(Data_Cleaning!$G$2)+1),86)),"")} -> 45627 | Y93: {=IFERROR(INDEX(Data_Cleaning!$D$2:$D$251,SMALL(IF(Data_Cleaning!$G$2:$G$251=$X5,ROW(Data_Cleaning!$G$2:$G$251)-ROW(Data_Cleaning!$G$2)+1),86)),"")} -> Mark Carter | Z93: {=IFERROR(INDEX(Data_Cleaning!$F$2:$F$251,SMALL(IF(Data_Cleaning!$G$2:$G$251=$X5,ROW(Data_Cleaning!$G$2:$G$251)-ROW(Data_Cleaning!$G$2)+1),86)),"")} -> Smartphone | AA93: {=IFERROR(INDEX(Data_Cleaning!$N$2:$N$251,SMALL(IF(Data_Cleaning!$G$2:$G$251=$X5,ROW(Data_Cleaning!$G$2:$G$251)-ROW(Data_Cleaning!$G$2)+1),86)),"")} -> 3499.95
W94: {=IFERROR(INDEX(Data_Cleaning!$A$2:$A$251,SMALL(IF(Data_Cleaning!$G$2:$G$251=$X5,ROW(Data_Cleaning!$G$2:$G$251)-ROW(Data_Cleaning!$G$2)+1),87)),"")} -> TRX0137 | X94: {=IFERROR(INDEX(Data_Cleaning!$B$2:$B$251,SMALL(IF(Data_Cleaning!$G$2:$G$251=$X5,ROW(Data_Cleaning!$G$2:$G$251)-ROW(Data_Cleaning!$G$2)+1),87)),"")} -> 45629 | Y94: {=IFERROR(INDEX(Data_Cleaning!$D$2:$D$251,SMALL(IF(Data_Cleaning!$G$2:$G$251=$X5,ROW(Data_Cleaning!$G$2:$G$251)-ROW(Data_Cleaning!$G$2)+1),87)),"")} -> William White | Z94: {=IFERROR(INDEX(Data_Cleaning!$F$2:$F$251,SMALL(IF(Data_Cleaning!$G$2:$G$251=$X5,ROW(Data_Cleaning!$G$2:$G$251)-ROW(Data_Cleaning!$G$2)+1),87)),"")} -> Monitor | AA94: {=IFERROR(INDEX(Data_Cleaning!$N$2:$N$251,SMALL(IF(Data_Cleaning!$G$2:$G$251=$X5,ROW(Data_Cleaning!$G$2:$G$251)-ROW(Data_Cleaning!$G$2)+1),87)),"")} -> 999.96
W95: {=IFERROR(INDEX(Data_Cleaning!$A$2:$A$251,SMALL(IF(Data_Cleaning!$G$2:$G$251=$X5,ROW(Data_Cleaning!$G$2:$G$251)-ROW(Data_Cleaning!$G$2)+1),88)),"")} -> TRX0066 | X95: {=IFERROR(INDEX(Data_Cleaning!$B$2:$B$251,SMALL(IF(Data_Cleaning!$G$2:$G$251=$X5,ROW(Data_Cleaning!$G$2:$G$251)-ROW(Data_Cleaning!$G$2)+1),88)),"")} -> 45630 | Y95: {=IFERROR(INDEX(Data_Cleaning!$D$2:$D$251,SMALL(IF(Data_Cleaning!$G$2:$G$251=$X5,ROW(Data_Cleaning!$G$2:$G$251)-ROW(Data_Cleaning!$G$2)+1),88)),"")} -> Dorothy Nelson | Z95: {=IFERROR(INDEX(Data_Cleaning!$F$2:$F$251,SMALL(IF(Data_Cleaning!$G$2:$G$251=$X5,ROW(Data_Cleaning!$G$2:$G$251)-ROW(Data_Cleaning!$G$2)+1),88)),"")} -> Smartphone | AA95: {=IFERROR(INDEX(Data_Cleaning!$N$2:$N$251,SMALL(IF(Data_Cleaning!$G$2:$G$251=$X5,ROW(Data_Cleaning!$G$2:$G$251)-ROW(Data_Cleaning!$G$2)+1),88)),"")} -> 2799.96
W96: {=IFERROR(INDEX(Data_Cleaning!$A$2:$A$251,SMALL(IF(Data_Cleaning!$G$2:$G$251=$X5,ROW(Data_Cleaning!$G$2:$G$251)-ROW(Data_Cleaning!$G$2)+1),89)),"")} -> TRX0180 | X96: {=IFERROR(INDEX(Data_Cleaning!$B$2:$B$251,SMALL(IF(Data_Cleaning!$G$2:$G$251=$X5,ROW(Data_Cleaning!$G$2:$G$251)-ROW(Data_Cleaning!$G$2)+1),89)),"")} -> 45635 | Y96: {=IFERROR(INDEX(Data_Cleaning!$D$2:$D$251,SMALL(IF(Data_Cleaning!$G$2:$G$251=$X5,ROW(Data_Cleaning!$G$2:$G$251)-ROW(Data_Cleaning!$G$2)+1),89)),"")} -> Nancy Collins | Z96: {=IFERROR(INDEX(Data_Cleaning!$F$2:$F$251,SMALL(IF(Data_Cleaning!$G$2:$G$251=$X5,ROW(Data_Cleaning!$G$2:$G$251)-ROW(Data_Cleaning!$G$2)+1),89)),"")} -> Monitor | AA96: {=IFERROR(INDEX(Data_Cleaning!$N$2:$N$251,SMALL(IF(Data_Cleaning!$G$2:$G$251=$X5,ROW(Data_Cleaning!$G$2:$G$251)-ROW(Data_Cleaning!$G$2)+1),89)),"")} -> 499.98
W97: {=IFERROR(INDEX(Data_Cleaning!$A$2:$A$251,SMALL(IF(Data_Cleaning!$G$2:$G$251=$X5,ROW(Data_Cleaning!$G$2:$G$251)-ROW(Data_Cleaning!$G$2)+1),90)),"")} -> TRX0032 | X97: {=IFERROR(INDEX(Data_Cleaning!$B$2:$B$251,SMALL(IF(Data_Cleaning!$G$2:$G$251=$X5,ROW(Data_Cleaning!$G$2:$G$251)-ROW(Data_Cleaning!$G$2)+1),90)),"")} -> 45638 | Y97: {=IFERROR(INDEX(Data_Cleaning!$D$2:$D$251,SMALL(IF(Data_Cleaning!$G$2:$G$251=$X5,ROW(Data_Cleaning!$G$2:$G$251)-ROW(Data_Cleaning!$G$2)+1),90)),"")} -> Peter Richardson | Z97: {=IFERROR(INDEX(Data_Cleaning!$F$2:$F$251,SMALL(IF(Data_Cleaning!$G$2:$G$251=$X5,ROW(Data_Cleaning!$G$2:$G$251)-ROW(Data_Cleaning!$G$2)+1),90)),"")} -> Laptop | AA97: {=IFERROR(INDEX(Data_Cleaning!$N$2:$N$251,SMALL(IF(Data_Cleaning!$G$2:$G$251=$X5,ROW(Data_Cleaning!$G$2:$G$251)-ROW(Data_Cleaning!$G$2)+1),90)),"")} -> 1799.98
W98: {=IFERROR(INDEX(Data_Cleaning!$A$2:$A$251,SMALL(IF(Data_Cleaning!$G$2:$G$251=$X5,ROW(Data_Cleaning!$G$2:$G$251)-ROW(Data_Cleaning!$G$2)+1),91)),"")} -> TRX0183 | X98: {=IFERROR(INDEX(Data_Cleaning!$B$2:$B$251,SMALL(IF(Data_Cleaning!$G$2:$G$251=$X5,ROW(Data_Cleaning!$G$2:$G$251)-ROW(Data_Cleaning!$G$2)+1),91)),"")} -> 45645 | Y98: {=IFERROR(INDEX(Data_Cleaning!$D$2:$D$251,SMALL(IF(Data_Cleaning!$G$2:$G$251=$X5,ROW(Data_Cleaning!$G$2:$G$251)-ROW(Data_Cleaning!$G$2)+1),91)),"")} -> David Martinez | Z98: {=IFERROR(INDEX(Data_Cleaning!$F$2:$F$251,SMALL(IF(Data_Cleaning!$G$2:$G$251=$X5,ROW(Data_Cleaning!$G$2:$G$251)-ROW(Data_Cleaning!$G$2)+1),91)),"")} -> Keyboard | AA98: {=IFERROR(INDEX(Data_Cleaning!$N$2:$N$251,SMALL(IF(Data_Cleaning!$G$2:$G$251=$X5,ROW(Data_Cleaning!$G$2:$G$251)-ROW(Data_Cleaning!$G$2)+1),91)),"")} -> 89.99
W99: {=IFERROR(INDEX(Data_Cleaning!$A$2:$A$251,SMALL(IF(Data_Cleaning!$G$2:$G$251=$X5,ROW(Data_Cleaning!$G$2:$G$251)-ROW(Data_Cleaning!$G$2)+1),92)),"")} -> TRX0163 | X99: {=IFERROR(INDEX(Data_Cleaning!$B$2:$B$251,SMALL(IF(Data_Cleaning!$G$2:$G$251=$X5,ROW(Data_Cleaning!$G$2:$G$251)-ROW(Data_Cleaning!$G$2)+1),92)),"")} -> 45645 | Y99: {=IFERROR(INDEX(Data_Cleaning!$D$2:$D$251,SMALL(IF(Data_Cleaning!$G$2:$G$251=$X5,ROW(Data_Cleaning!$G$2:$G$251)-ROW(Data_Cleaning!$G$2)+1),92)),"")} -> Daniel King | Z99: {=IFERROR(INDEX(Data_Cleaning!$F$2:$F$251,SMALL(IF(Data_Cleaning!$G$2:$G$251=$X5,ROW(Data_Cleaning!$G$2:$G$251)-ROW(Data_Cleaning!$G$2)+1),92)),"")} -> Laptop | AA99: {=IFERROR(INDEX(Data_Cleaning!$N$2:$N$251,SMALL(IF(Data_Cleaning!$G$2:$G$251=$X5,ROW(Data_Cleaning!$G$2:$G$251)-ROW(Data_Cleaning!$G$2)+1),92)),"")} -> 4499.95
W100: {=IFERROR(INDEX(Data_Cleaning!$A$2:$A$251,SMALL(IF(Data_Cleaning!$G$2:$G$251=$X5,ROW(Data_Cleaning!$G$2:$G$251)-ROW(Data_Cleaning!$G$2)+1),93)),"")} -> TRX0164 | X100: {=IFERROR(INDEX(Data_Cleaning!$B$2:$B$251,SMALL(IF(Data_Cleaning!$G$2:$G$251=$X5,ROW(Data_Cleaning!$G$2:$G$251)-ROW(Data_Cleaning!$G$2)+1),93)),"")} -> 45648 | Y100: {=IFERROR(INDEX(Data_Cleaning!$D$2:$D$251,SMALL(IF(Data_Cleaning!$G$2:$G$251=$X5,ROW(Data_Cleaning!$G$2:$G$251)-ROW(Data_Cleaning!$G$2)+1),93)),"")} -> Linda Martin | Z100: {=IFERROR(INDEX(Data_Cleaning!$F$2:$F$251,SMALL(IF(Data_Cleaning!$G$2:$G$251=$X5,ROW(Data_Cleaning!$G$2:$G$251)-ROW(Data_Cleaning!$G$2)+1),93)),"")} -> Headphones | AA100: {=IFERROR(INDEX(Data_Cleaning!$N$2:$N$251,SMALL(IF(Data_Cleaning!$G$2:$G$251=$X5,ROW(Data_Cleaning!$G$2:$G$251)-ROW(Data_Cleaning!$G$2)+1),93)),"")} -> 299.98
W101: {=IFERROR(INDEX(Data_Cleaning!$A$2:$A$251,SMALL(IF(Data_Cleaning!$G$2:$G$251=$X5,ROW(Data_Cleaning!$G$2:$G$251)-ROW(Data_Cleaning!$G$2)+1),94)),"")} -> TRX0156 | X101: {=IFERROR(INDEX(Data_Cleaning!$B$2:$B$251,SMALL(IF(Data_Cleaning!$G$2:$G$251=$X5,ROW(Data_Cleaning!$G$2:$G$251)-ROW(Data_Cleaning!$G$2)+1),94)),"")} -> 45655 | Y101: {=IFERROR(INDEX(Data_Cleaning!$D$2:$D$251,SMALL(IF(Data_Cleaning!$G$2:$G$251=$X5,ROW(Data_Cleaning!$G$2:$G$251)-ROW(Data_Cleaning!$G$2)+1),94)),"")} -> Robert Thomas | Z101: {=IFERROR(INDEX(Data_Cleaning!$F$2:$F$251,SMALL(IF(Data_Cleaning!$G$2:$G$251=$X5,ROW(Data_Cleaning!$G$2:$G$251)-ROW(Data_Cleaning!$G$2)+1),94)),"")} -> Keyboard | AA101: {=IFERROR(INDEX(Data_Cleaning!$N$2:$N$251,SMALL(IF(Data_Cleaning!$G$2:$G$251=$X5,ROW(Data_Cleaning!$G$2:$G$251)-ROW(Data_Cleaning!$G$2)+1),94)),"")} -> 89.99
W102: {=IFERROR(INDEX(Data_Cleaning!$A$2:$A$251,SMALL(IF(Data_Cleaning!$G$2:$G$251=$X5,ROW(Data_Cleaning!$G$2:$G$251)-ROW(Data_Cleaning!$G$2)+1),95)),"")} -> TRX0207 | X102: {=IFERROR(INDEX(Data_Cleaning!$B$2:$B$251,SMALL(IF(Data_Cleaning!$G$2:$G$251=$X5,ROW(Data_Cleaning!$G$2:$G$251)-ROW(Data_Cleaning!$G$2)+1),95)),"")} -> 45657 | Y102: {=IFERROR(INDEX(Data_Cleaning!$D$2:$D$251,SMALL(IF(Data_Cleaning!$G$2:$G$251=$X5,ROW(Data_Cleaning!$G$2:$G$251)-ROW(Data_Cleaning!$G$2)+1),95)),"")} -> Mark Carter | Z102: {=IFERROR(INDEX(Data_Cleaning!$F$2:$F$251,SMALL(IF(Data_Cleaning!$G$2:$G$251=$X5,ROW(Data_Cleaning!$G$2:$G$251)-ROW(Data_Cleaning!$G$2)+1),95)),"")} -> Laptop | AA102: {=IFERROR(INDEX(Data_Cleaning!$N$2:$N$251,SMALL(IF(Data_Cleaning!$G$2:$G$251=$X5,ROW(Data_Cleaning!$G$2:$G$251)-ROW(Data_Cleaning!$G$2)+1),95)),"")} -> 899.99
...

Sheet WhatIf
A1: 1. GOAL SEEK - LAPTOP REVENUE TARGET
A3: Product: | B3: Laptop
A4: Unit Price: | B4: =VLOOKUP("P001",Data_Cleaning!E2:I251,5,FALSE()) -> 899.99
A5: Quantity Sold (input - Goal Seek changes this): | B5: 75
A6: Calculated Revenue (= Unit Price x Quantity): | B6: =B4*B5 -> 67499.25
A7: Target Revenue: | B7: 50000
A8: Required Quantity (cross-check = Target / Unit Price): | B8: =B7/B4 -> 55.556173
A13: 2. SCENARIO MANAGER - REVENUE PROJECTION (Best / Likely / Worst Case)
A15: Current Total Revenue (all transactions): | B15: =SUM(Data_Cleaning!N2:N251) -> 229192.47
A17: Scenario | B17: Price_Adjustment_% | C17: Quantity_Adjustment_% | D17: Projected_Revenue
A18: Best Case | B18: 0.05 | C18: 0.1 | D18: =$B$15*(1+B18)*(1+C18) -> 264717.3
A19: Likely Case | B19: 0 | C19: 0 | D19: =$B$15*(1+B19)*(1+C19) -> 229192.47
A20: Worst Case | B20: -0.05 | C20: -0.1 | D20: =$B$15*(1+B20)*(1+C20) -> 195959.56
A25: 3. LINEAR REGRESSION - QUANTITY vs TOTAL AMOUNT
A27: SUMMARY OUTPUT
A29: Regression Statistics
A30: Multiple R | B30: 0.45808036
A31: R Square | B31: 0.20983762
A32: Adjusted R Square | B32: 0.20665148
A33: Standard Error | B33: 919.60715
A34: Observations | B34: 250
A36: ANOVA
B37: df | C37: SS | D37: MS | E37: F | F37: Significance F
A38: Regression | B38: 1 | C38: 55695917 | D38: 55695917 | E38: 65.859537 | F38: 2.2586479e-14
A39: Residual | B39: 248 | C39: 2.0972797e+08 | D39: 845677.32
A40: Total | B40: 249 | C40: 2.6542389e+08
B42: Coefficients | C42: Standard Error | D42: t Stat | E42: P-value | F42: Lower 95% | G42: Upper 95% | H42: Lower 95.0% | I42: Upper 95.0%
A43: Intercept | B43: -148.85465 | C43: 143.61334 | D43: -1.0364959 | E43: 0.3009804 | F43: -431.712 | G43: 134.0027 | H43: -431.712 | I43: 134.0027
A44: Quantity | B44: 353.793 | C44: 43.595323 | D44: 8.1153889 | E44: 2.2586479e-14 | F44: 267.92872 | G44: 439.65729 | H44: 267.92872 | I44: 439.65729

Sheet PivotTables
A1: Revenue by Region (sorted descending)
A2: Region | B2: Sum of Total_Amount
A3: East | B3: =SUMIFS(tblClean[Total_Amount],tblClean[Region],$A3) -> 59288.39
A4: North | B4: =SUMIFS(tblClean[Total_Amount],tblClean[Region],$A4) -> 50808.31
A5: West | B5: =SUMIFS(tblClean[Total_Amount],tblClean[Region],$A5) -> 41408.68
A6: Central | B6: =SUMIFS(tblClean[Total_Amount],tblClean[Region],$A6) -> 41288.34
A7: South | B7: =SUMIFS(tblClean[Total_Amount],tblClean[Region],$A7) -> 36398.75
A8: Grand Total | B8: =SUM(B3:B7) -> 229192.47
P10: Revenue by Customer Segment
A19: Revenue by Category by Month
A20: Month | B20: Appliances | C20: Electronics | D20: Furniture | E20: Grand Total
A21: 2024-04 | B21: =SUMPRODUCT((YEAR(tblClean[Date])=2024)*(MONTH(tblClean[Date])=4)*(tblClean[Category]="Appliances")*tblClean[Total_Amount]) -> 1019.83 | C21: =SUMPRODUCT((YEAR(tblClean[Date])=2024)*(MONTH(tblClean[Date])=4)*(tblClean[Category]="Electronics")*tblClean[Total_Amount]) -> 17199.68 | D21: =SUMPRODUCT((YEAR(tblClean[Date])=2024)*(MONTH(tblClean[Date])=4)*(tblClean[Category]="Furniture")*tblClean[Total_Amount]) -> 2699.82 | E21: =SUM(B21:D21) -> 20919.33
A22: 2024-05 | B22: =SUMPRODUCT((YEAR(tblClean[Date])=2024)*(MONTH(tblClean[Date])=5)*(tblClean[Category]="Appliances")*tblClean[Total_Amount]) -> 919.87 | C22: =SUMPRODUCT((YEAR(tblClean[Date])=2024)*(MONTH(tblClean[Date])=5)*(tblClean[Category]="Electronics")*tblClean[Total_Amount]) -> 10169.73 | D22: =SUMPRODUCT((YEAR(tblClean[Date])=2024)*(MONTH(tblClean[Date])=5)*(tblClean[Category]="Furniture")*tblClean[Total_Amount]) -> 5949.75 | E22: =SUM(B22:D22) -> 17039.35
A23: 2024-06 | B23: =SUMPRODUCT((YEAR(tblClean[Date])=2024)*(MONTH(tblClean[Date])=6)*(tblClean[Category]="Appliances")*tblClean[Total_Amount]) -> 499.92 | C23: =SUMPRODUCT((YEAR(tblClean[Date])=2024)*(MONTH(tblClean[Date])=6)*(tblClean[Category]="Electronics")*tblClean[Total_Amount]) -> 17749.58 | D23: =SUMPRODUCT((YEAR(tblClean[Date])=2024)*(MONTH(tblClean[Date])=6)*(tblClean[Category]="Furniture")*tblClean[Total_Amount]) -> 1049.95 | E23: =SUM(B23:D23) -> 19299.45
A24: 2024-07 | B24: =SUMPRODUCT((YEAR(tblClean[Date])=2024)*(MONTH(tblClean[Date])=7)*(tblClean[Category]="Appliances")*tblClean[Total_Amount]) -> 939.86 | C24: =SUMPRODUCT((YEAR(tblClean[Date])=2024)*(MONTH(tblClean[Date])=7)*(tblClean[Category]="Electronics")*tblClean[Total_Amount]) -> 14439.68 | D24: =SUMPRODUCT((YEAR(tblClean[Date])=2024)*(MONTH(tblClean[Date])=7)*(tblClean[Category]="Furniture")*tblClean[Total_Amount]) -> 3099.86 | E24: =SUM(B24:D24) -> 18479.4
A25: 2024-08 | B25: =SUMPRODUCT((YEAR(tblClean[Date])=2024)*(MONTH(tblClean[Date])=8)*(tblClean[Category]="Appliances")*tblClean[Total_Amount]) -> 239.97 | C25: =SUMPRODUCT((YEAR(tblClean[Date])=2024)*(MONTH(tblClean[Date])=8)*(tblClean[Category]="Electronics")*tblClean[Total_Amount]) -> 10869.69 | D25: =SUMPRODUCT((YEAR(tblClean[Date])=2024)*(MONTH(tblClean[Date])=8)*(tblClean[Category]="Furniture")*tblClean[Total_Amount]) -> 4649.77 | E25: =SUM(B25:D25) -> 15759.43
A26: 2024-09 | B26: =SUMPRODUCT((YEAR(tblClean[Date])=2024)*(MONTH(tblClean[Date])=9)*(tblClean[Category]="Appliances")*tblClean[Total_Amount]) -> 759.89 | C26: =SUMPRODUCT((YEAR(tblClean[Date])=2024)*(MONTH(tblClean[Date])=9)*(tblClean[Category]="Electronics")*tblClean[Total_Amount]) -> 9279.75 | D26: =SUMPRODUCT((YEAR(tblClean[Date])=2024)*(MONTH(tblClean[Date])=9)*(tblClean[Category]="Furniture")*tblClean[Total_Amount]) -> 2949.87 | E26: =SUM(B26:D26) -> 12989.51
A27: 2024-10 | B27: =SUMPRODUCT((YEAR(tblClean[Date])=2024)*(MONTH(tblClean[Date])=10)*(tblClean[Category]="Appliances")*tblClean[Total_Amount]) -> 119.98 | C27: =SUMPRODUCT((YEAR(tblClean[Date])=2024)*(MONTH(tblClean[Date])=10)*(tblClean[Category]="Electronics")*tblClean[Total_Amount]) -> 17939.64 | D27: =SUMPRODUCT((YEAR(tblClean[Date])=2024)*(MONTH(tblClean[Date])=10)*(tblClean[Category]="Furniture")*tblClean[Total_Amount]) -> 2549.9 | E27: =SUM(B27:D27) -> 20609.52
A28: 2024-11 | B28: =SUMPRODUCT((YEAR(tblClean[Date])=2024)*(MONTH(tblClean[Date])=11)*(tblClean[Category]="Appliances")*tblClean[Total_Amount]) -> 539.91 | C28: =SUMPRODUCT((YEAR(tblClean[Date])=2024)*(MONTH(tblClean[Date])=11)*(tblClean[Category]="Electronics")*tblClean[Total_Amount]) -> 7969.74 | D28: =SUMPRODUCT((YEAR(tblClean[Date])=2024)*(MONTH(tblClean[Date])=11)*(tblClean[Category]="Furniture")*tblClean[Total_Amount]) -> 3799.79 | E28: =SUM(B28:D28) -> 12309.44
A29: 2024-12 | B29: =SUMPRODUCT((YEAR(tblClean[Date])=2024)*(MONTH(tblClean[Date])=12)*(tblClean[Category]="Appliances")*tblClean[Total_Amount]) -> 859.88 | C29: =SUMPRODUCT((YEAR(tblClean[Date])=2024)*(MONTH(tblClean[Date])=12)*(tblClean[Category]="Electronics")*tblClean[Total_Amount]) -> 17029.66 | D29: =SUMPRODUCT((YEAR(tblClean[Date])=2024)*(MONTH(tblClean[Date])=12)*(tblClean[Category]="Furniture")*tblClean[Total_Amount]) -> 5149.76 | E29: =SUM(B29:D29) -> 23039.3
A30: 2025-01 | B30: =SUMPRODUCT((YEAR(tblClean[Date])=2025)*(MONTH(tblClean[Date])=1)*(tblClean[Category]="Appliances")*tblClean[Total_Amount]) -> 619.9 | C30: =SUMPRODUCT((YEAR(tblClean[Date])=2025)*(MONTH(tblClean[Date])=1)*(tblClean[Category]="Electronics")*tblClean[Total_Amount]) -> 18429.52 | D30: =SUMPRODUCT((YEAR(tblClean[Date])=2025)*(MONTH(tblClean[Date])=1)*(tblClean[Category]="Furniture")*tblClean[Total_Amount]) -> 6749.73 | E30: =SUM(B30:D30) -> 25799.15
A31: 2025-02 | B31: =SUMPRODUCT((YEAR(tblClean[Date])=2025)*(MONTH(tblClean[Date])=2)*(tblClean[Category]="Appliances")*tblClean[Total_Amount]) -> 839.87 | C31: =SUMPRODUCT((YEAR(tblClean[Date])=2025)*(MONTH(tblClean[Date])=2)*(tblClean[Category]="Electronics")*tblClean[Total_Amount]) -> 8229.83 | D31: =SUMPRODUCT((YEAR(tblClean[Date])=2025)*(MONTH(tblClean[Date])=2)*(tblClean[Category]="Furniture")*tblClean[Total_Amount]) -> 6999.68 | E31: =SUM(B31:D31) -> 16069.38
A32: 2025-03 | B32: =SUMPRODUCT((YEAR(tblClean[Date])=2025)*(MONTH(tblClean[Date])=3)*(tblClean[Category]="Appliances")*tblClean[Total_Amount]) -> 739.89 | C32: =SUMPRODUCT((YEAR(tblClean[Date])=2025)*(MONTH(tblClean[Date])=3)*(tblClean[Category]="Electronics")*tblClean[Total_Amount]) -> 15709.69 | D32: =SUMPRODUCT((YEAR(tblClean[Date])=2025)*(MONTH(tblClean[Date])=3)*(tblClean[Category]="Furniture")*tblClean[Total_Amount]) -> 3449.8 | E32: =SUM(B32:D32) -> 19899.38
A33: 2025-04 | B33: =SUMPRODUCT((YEAR(tblClean[Date])=2025)*(MONTH(tblClean[Date])=4)*(tblClean[Category]="Appliances")*tblClean[Total_Amount]) -> 239.97 | C33: =SUMPRODUCT((YEAR(tblClean[Date])=2025)*(MONTH(tblClean[Date])=4)*(tblClean[Category]="Electronics")*tblClean[Total_Amount]) -> 6739.86 | D33: =SUMPRODUCT((YEAR(tblClean[Date])=2025)*(MONTH(tblClean[Date])=4)*(tblClean[Category]="Furniture")*tblClean[Total_Amount]) -> 0 | E33: =SUM(B33:D33) -> 6979.83
A34: Grand Total | B34: =SUM(B21:B33) -> 8338.74 | C34: =SUM(C21:C33) -> 171756.05 | D34: =SUM(D21:D33) -> 49097.68 | E34: =SUM(E21:E33) -> 229192.47
A38: Top 10 Customers by Revenue | E38: Revenue: Customer Segment × Payment Method
A39: Customer_Name | B39: Sum of Total_Amount | C39: Count of Transaction_ID | E39: Segment | F39: Cash | G39: Credit Card | H39: Debit Card | I39: Paypal | J39: Grand Total
A40: Mark Carter | B40: =SUMIFS(tblClean[Total_Amount],tblClean[Customer_Name],$A40) -> 15659.65 | C40: =COUNTIFS(tblClean[Customer_Name],$A40) -> 12 | E40: Basic | F40: =SUMIFS(tblClean[Total_Amount],tblClean[Customer_Segment],$E40,tblClean[Payment_Method],F$39) -> 15199.44 | G40: =SUMIFS(tblClean[Total_Amount],tblClean[Customer_Segment],$E40,tblClean[Payment_Method],G$39) -> 16009.36 | H40: =SUMIFS(tblClean[Total_Amount],tblClean[Customer_Segment],$E40,tblClean[Payment_Method],H$39) -> 9839.57 | I40: =SUMIFS(tblClean[Total_Amount],tblClean[Customer_Segment],$E40,tblClean[Payment_Method],I$39) -> 21129.44 | J40: =SUM(F40:I40) -> 62177.81
A41: Edward Mitchell | B41: =SUMIFS(tblClean[Total_Amount],tblClean[Customer_Name],$A41) -> 11919.77 | C41: =COUNTIFS(tblClean[Customer_Name],$A41) -> 6 | E41: Standard | F41: =SUMIFS(tblClean[Total_Amount],tblClean[Customer_Segment],$E41,tblClean[Payment_Method],F$39) -> 21279.32 | G41: =SUMIFS(tblClean[Total_Amount],tblClean[Customer_Segment],$E41,tblClean[Payment_Method],G$39) -> 21129.37 | H41: =SUMIFS(tblClean[Total_Amount],tblClean[Customer_Segment],$E41,tblClean[Payment_Method],H$39) -> 23849.28 | I41: =SUMIFS(tblClean[Total_Amount],tblClean[Customer_Segment],$E41,tblClean[Payment_Method],I$39) -> 16099.57 | J41: =SUM(F41:I41) -> 82357.54
A42: Barbara Young | B42: =SUMIFS(tblClean[Total_Amount],tblClean[Customer_Name],$A42) -> 10649.8 | C42: =COUNTIFS(tblClean[Customer_Name],$A42) -> 5 | E42: Premium | F42: =SUMIFS(tblClean[Total_Amount],tblClean[Customer_Segment],$E42,tblClean[Payment_Method],F$39) -> 20949.03 | G42: =SUMIFS(tblClean[Total_Amount],tblClean[Customer_Segment],$E42,tblClean[Payment_Method],G$39) -> 24309.23 | H42: =SUMIFS(tblClean[Total_Amount],tblClean[Customer_Segment],$E42,tblClean[Payment_Method],H$39) -> 18429.46 | I42: =SUMIFS(tblClean[Total_Amount],tblClean[Customer_Segment],$E42,tblClean[Payment_Method],I$39) -> 20969.4 | J42: =SUM(F42:I42) -> 84657.12
A43: Patricia Moore | B43: =SUMIFS(tblClean[Total_Amount],tblClean[Customer_Name],$A43) -> 9799.73 | C43: =COUNTIFS(tblClean[Customer_Name],$A43) -> 8 | E43: Grand Total | F43: =SUM(F40:F42) -> 57427.79 | G43: =SUM(G40:G42) -> 61447.96 | H43: =SUM(H40:H42) -> 52118.31 | I43: =SUM(I40:I42) -> 58198.41 | J43: =SUM(J40:J42) -> 229192.47
A44: Paul Baker | B44: =SUMIFS(tblClean[Total_Amount],tblClean[Customer_Name],$A44) -> 8309.74 | C44: =COUNTIFS(tblClean[Customer_Name],$A44) -> 8
A45: Dorothy Nelson | B45: =SUMIFS(tblClean[Total_Amount],tblClean[Customer_Name],$A45) -> 8269.79 | C45: =COUNTIFS(tblClean[Customer_Name],$A45) -> 6
A46: Karen Hill | B46: =SUMIFS(tblClean[Total_Amount],tblClean[Customer_Name],$A46) -> 8009.77 | C46: =COUNTIFS(tblClean[Customer_Name],$A46) -> 8
A47: Daniel King | B47: =SUMIFS(tblClean[Total_Amount],tblClean[Customer_Name],$A47) -> 7309.8 | C47: =COUNTIFS(tblClean[Customer_Name],$A47) -> 7
A48: Lawrence Reed | B48: =SUMIFS(tblClean[Total_Amount],tblClean[Customer_Name],$A48) -> 6989.77 | C48: =COUNTIFS(tblClean[Customer_Name],$A48) -> 8
A49: Joseph Jackson | B49: =SUMIFS(tblClean[Total_Amount],tblClean[Customer_Name],$A49) -> 6949.84 | C49: =COUNTIFS(tblClean[Customer_Name],$A49) -> 5
